Workbook

Sheet Resumo
B5: Área Responsável: Suprimentos Serede - Gerente: Marcelo de Oliveira Santos - 21 - 98754-9966
B6: Fonte: SAP Serede (extraído em 14/02/2025)
B11: Base de Fornecedores distribuído da forma abaixo:
B13: Possui Contrato? | C13: Qtde Fornecedor
B14: Sim | C14: 93
B15: Não | C15: 4342
B16: Total Geral | C16: 4435
B18: Fornecedores com faturamento em 2024/2025 (não considera 2023):
B20: Faturamento em 2024/25 | C20: Qtde Fornecedor
B21: Sim | C21: 321
B22: Não | C22: 4114
B23: Total Geral | C23: 4435
B25: Grupo de Contas:
B27: Rótulos de Linha | C27: Contagem de Grupo Contas
B28: Prefeituras - PJ | C28: 2599
B29: Fornec. de Serviç. Diversos PJ | C29: 1216
B30: Órgãos Públicos - PJ | C30: 306
B31: Fornecedor de materiais - PJ | C31: 79
B32: Hotéis e Pousadas - PJ | C32: 69
B33: Pagamentos judiciais - PJ | C33: 62
B34: Consultorias - PJ | C34: 21
B35: Fretes - PJ | C35: 12
B36: Locação de Equipamentos - PJ | C36: 12
B37: Serviços de Operaç./Engenh. PJ | C37: 10
B38: TRIBUTOS | C38: 9
B39: Pessoa Física - PF | C39: 8
... B49: Total Geral | C49: 4435

Sheet Tabela Base SAP
A1: Fornecedor | B1: Nome | C1: Fornecedor | D1: Dt. Abertura | E1: Criado por | F1: Rua | G1: Local | H1: Bairro | I1: Região | J1: Cód.postal | K1: País | L1: Telefone 1 | M1: Nº telefax | N1: CNPJ | O1: CPF | P1: Insc Est | Q1: Insc Muni | R1: Endereço de e-mail | S1: Empresa | T1: Sigla Grupo Conta | U1: Grupo Contas | V1: ChvBanco | W1: ContaBanc. | X1: ChvCtrlBco | Y1: Nº Contrato | Z1: Dt. Últ. PC | AA1: Contrato: Sim/Não | AB1: PC e/ou Faturamento em 2024-25? | AC1: zEmpresa
A2: 200669 | B2: PREFEITURA MUNICIPAL DE CURITIBA | C2: 200669 | D2: 41267 | E2: CARGA | F2: AVENIDA CANDIDO DE ABREU 817 817 | G2: CURITIBA | H2: CENTRO CIVICO | I2: PR | J2: 80530-908 | K2: BR | L2: 4133508484 | S2: TSR | T2: FPRE | U2: =VLOOKUP(T2,Apoio!$D$10:$E$55,2,0) -> Prefeituras - PJ | AA2: =IF(Y2="","Não","Sim") -> Não | AB2: =IF(Z2="","Não","Sim") -> Não | AC2: =IF(S2="TSR","Serede","Rede Conecta") -> Serede
A3: 2609626 | B3: MARCOS ANDRE COLETA | C3: 2609626 | D3: 41270 | E3: CARGA | F3: AUGUSTO LIRA 153 | G3: RECIFE | H3: VASCO DA GAMA | I3: PE | J3: 52081-120 | K3: BR | P3: ISENTA | S3: TSR | T3: FPFZ | U3: =VLOOKUP(T3,Apoio!$D$10:$E$55,2,0) -> Pessoa Física - PF | V3: 191833 | W3: 24891 | X3: 36 | AA3: =IF(Y3="","Não","Sim") -> Não | AB3: =IF(Z3="","Não","Sim") -> Não | AC3: =IF(S3="TSR","Serede","Rede Conecta") -> Serede
A4: 204907 | B4: PREFEITURA MUNICIPAL DE SAO CRISTOV | C4: 204907 | D4: 41273 | E4: CARGA | F4: PRACA DR GETULIO VARGAS 298 | G4: SAO CRISTOVAO | H4: CENTRO | I4: SE | J4: 49100-000 | K4: BR | S4: TSR | T4: FPRE | U4: =VLOOKUP(T4,Apoio!$D$10:$E$55,2,0) -> Prefeituras - PJ | AA4: =IF(Y4="","Não","Sim") -> Não | AB4: =IF(Z4="","Não","Sim") -> Não | AC4: =IF(S4="TSR","Serede","Rede Conecta") -> Serede
A5: 2000002 | B5: COMBUSTIVEL | C5: 2000002 | D5: 41273 | E5: R88866521353 | F5: RUA MARCOS MACEDO 1333 | G5: FORTAELZA | I5: CE | J5: 60150-190 | K5: BR | S5: TSR | T5: FTRI | U5: =VLOOKUP(T5,Apoio!$D$10:$E$55,2,0) -> TRIBUTOS | AA5: =IF(Y5="","Não","Sim") -> Não | AB5: =IF(Z5="","Não","Sim") -> Não | AC5: =IF(S5="TSR","Serede","Rede Conecta") -> Serede
A6: 2000005 | B6: LOCACAO DE VEICULOS | C6: 2000005 | D6: 41273 | E6: R88866521353 | F6: RUA MARCOS MACEDO 1333 | G6: FORTALEZA | I6: CE | J6: 60150-190 | K6: BR | S6: TSR | T6: FTRI | U6: =VLOOKUP(T6,Apoio!$D$10:$E$55,2,0) -> TRIBUTOS | AA6: =IF(Y6="","Não","Sim") -> Não | AB6: =IF(Z6="","Não","Sim") -> Não | AC6: =IF(S6="TSR","Serede","Rede Conecta") -> Serede
A7: 2000006 | B7: SECRETARIA DA RECEITA FEDERAL | C7: 2000006 | D7: 41273 | E7: R88866521353 | F7: RUA MARCOS MACEDO 1333 | G7: FORTALEZA | I7: CE | J7: 60150-190 | K7: BR | S7: TSR | T7: FTRI | U7: =VLOOKUP(T7,Apoio!$D$10:$E$55,2,0) -> TRIBUTOS | V7: 0 | W7: 99999999 | X7: 0 | AA7: =IF(Y7="","Não","Sim") -> Não | AB7: =IF(Z7="","Não","Sim") -> Não | AC7: =IF(S7="TSR","Serede","Rede Conecta") -> Serede
A8: 2000007 | B8: INSTITUTO NAC DA SEGURIDADE SOCIAL | C8: 2000007 | D8: 41273 | E8: R88866521353 | F8: RUA MARCOS MACEDO 1333 | G8: FORTALEZA | I8: CE | J8: 60150-190 | K8: BR | S8: TSR | T8: FTRI | U8: =VLOOKUP(T8,Apoio!$D$10:$E$55,2,0) -> TRIBUTOS | V8: 0 | W8: 99999999 | X8: 0 | AA8: =IF(Y8="","Não","Sim") -> Não | AB8: =IF(Z8="","Não","Sim") -> Não | AC8: =IF(S8="TSR","Serede","Rede Conecta") -> Serede
A9: 2000008 | B9: SECRETARIA ESTADUAL DA PARAIBA | C9: 2000008 | D9: 41273 | E9: R88866521353 | F9: RUA JOAO DA MATA SN | G9: AGUA BRANCA | I9: PB | J9: 58015-020 | K9: BR | S9: TSR | T9: FTRI | U9: =VLOOKUP(T9,Apoio!$D$10:$E$55,2,0) -> TRIBUTOS | AA9: =IF(Y9="","Não","Sim") -> Não | AB9: =IF(Z9="","Não","Sim") -> Não | AC9: =IF(S9="TSR","Serede","Rede Conecta") -> Serede
A10: 2000009 | B10: SECRETARIA ESTADUAL DO PIAUI | C10: 2000009 | D10: 41273 | E10: R88866521353 | F10: AVENIDA PEDRO FREITAS SN | G10: TERESINA | I10: PI | J10: 64018-900 | K10: BR | S10: TSR | T10: FTRI | U10: =VLOOKUP(T10,Apoio!$D$10:$E$55,2,0) -> TRIBUTOS | AA10: =IF(Y10="","Não","Sim") -> Não | AB10: =IF(Z10="","Não","Sim") -> Não | AC10: =IF(S10="TSR","Serede","Rede Conecta") -> Serede
A11: 2000010 | B11: SECRETARIA ESTADUAL DO MARANHAO | C11: 2000010 | D11: 41273 | E11: R88866521353 | F11: RUA SANTA ISABEL 40 | G11: SAO LUIS | I11: MA | J11: 65076-090 | K11: BR | S11: TSR | T11: FTRI | U11: =VLOOKUP(T11,Apoio!$D$10:$E$55,2,0) -> TRIBUTOS | AA11: =IF(Y11="","Não","Sim") -> Não | AB11: =IF(Z11="","Não","Sim") -> Não | AC11: =IF(S11="TSR","Serede","Rede Conecta") -> Serede
A12: 2000011 | B12: PREFEITURA MUNICIPAL SAO CRISTOVAO | C12: 2000011 | D12: 41273 | E12: R88866521353 | F12: PRACA DR GETULIO VARGAS 298 | G12: SAO CRISTOVAO | I12: SE | J12: 49100-000 | K12: BR | S12: TSR | T12: FTRI | U12: =VLOOKUP(T12,Apoio!$D$10:$E$55,2,0) -> TRIBUTOS | AA12: =IF(Y12="","Não","Sim") -> Não | AB12: =IF(Z12="","Não","Sim") -> Não | AC12: =IF(S12="TSR","Serede","Rede Conecta") -> Serede
A13: 304032 | B13: PROCURADORIA GERAL | C13: 304032 | D13: 41333 | E13: R01144195314 | F13: RUA MARCOS MACEDO 1333 | G13: FORTALEZA | H13: PAPICU | I13: CE | J13: 60150-190 | K13: BR | S13: TSR | T13: FOPU | U13: =VLOOKUP(T13,Apoio!$D$10:$E$55,2,0) -> Órgãos Públicos - PJ | AA13: =IF(Y13="","Não","Sim") -> Não | AB13: =IF(Z13="","Não","Sim") -> Não | AC13: =IF(S13="TSR","Serede","Rede Conecta") -> Serede
A14: 204931 | B14: GLORIA DE GOITA PREFEITURA | C14: 204931 | D14: 41368 | E14: R01144195314 | F14: PRAÇA CRISTO REDENTOR 08 | G14: GLORIA DO GOITA | H14: CENTRO | I14: PE | J14: 55620-000 | K14: BR | S14: TSR | T14: FPRE | U14: =VLOOKUP(T14,Apoio!$D$10:$E$55,2,0) -> Prefeituras - PJ | AA14: =IF(Y14="","Não","Sim") -> Não | AB14: =IF(Z14="","Não","Sim") -> Não | AC14: =IF(S14="TSR","Serede","Rede Conecta") -> Serede
A15: 304038 | B15: DEPARTAMENTO DE INFRAESTRUTURA | C15: 304038 | D15: 41389 | E15: R01144195314 | F15: 4ª AVENIDA 445 | G15: SALVADOR | H15: CENTRO ADMINISTRATIVO DA BAHIA | I15: BA | J15: 41745-002 | K15: BR | S15: TSR | T15: FOPU | U15: =VLOOKUP(T15,Apoio!$D$10:$E$55,2,0) -> Órgãos Públicos - PJ | AA15: =IF(Y15="","Não","Sim") -> Não | AB15: =IF(Z15="","Não","Sim") -> Não | AC15: =IF(S15="TSR","Serede","Rede Conecta") -> Serede
A16: 304042 | B16: CORPO DE BOMBEIROS MILITAR FUNESBOM | C16: 304042 | D16: 41411 | E16: R01144195314 | F16: RUA SAO LUIZ GONZAGA 2244 | G16: RIO DE JANEIRO | H16: BENFICA | I16: RJ | J16: 20910-062 | K16: BR | S16: TSR | T16: FOPU | U16: =VLOOKUP(T16,Apoio!$D$10:$E$55,2,0) -> Órgãos Públicos - PJ | AA16: =IF(Y16="","Não","Sim") -> Não | AB16: =IF(Z16="","Não","Sim") -> Não | AC16: =IF(S16="TSR","Serede","Rede Conecta") -> Serede
A17: 2700016 | B17: WILLIAMS INTERNACIONAL CO. | C17: 2700016 | D17: 41429 | E17: R01144195314 | F17: 200 P.O BOX | G17: DETROID | H17: WALLED LAKE | I17: XE | J17: 48390-0200 | K17: US | S17: TSR | T17: FEST | U17: =VLOOKUP(T17,Apoio!$D$10:$E$55,2,0) -> Fornecedor Estrangeiro | AA17: =IF(Y17="","Não","Sim") -> Não | AB17: =IF(Z17="","Não","Sim") -> Não | AC17: =IF(S17="TSR","Serede","Rede Conecta") -> Serede
A18: 304053 | B18: JUSTIÇA FEDERAL DO CEARÁ | C18: 304053 | D18: 41528 | E18: R01144195314 | F18: RUA DA ASSUNÇÃO SN | G18: FORTALEZA | H18: CENTRO | I18: CE | J18: 60025-130 | K18: BR | S18: TSR | T18: FOPU | U18: =VLOOKUP(T18,Apoio!$D$10:$E$55,2,0) -> Órgãos Públicos - PJ | AA18: =IF(Y18="","Não","Sim") -> Não | AB18: =IF(Z18="","Não","Sim") -> Não | AC18: =IF(S18="TSR","Serede","Rede Conecta") -> Serede
A19: 2700031 | B19: LINKEDIN IRELAND LIMITED | C19: 2700031 | D19: 41625 | E19: R01144195314 | F19: 9999 HOUSE GARDEN, WILTON PLACE | G19: EXTRANGEIRO | I19: XE | J19: 0 | K19: US | S19: TSR | T19: FEST | U19: =VLOOKUP(T19,Apoio!$D$10:$E$55,2,0) -> Fornecedor Estrangeiro | AA19: =IF(Y19="","Não","Sim") -> Não | AB19: =IF(Z19="","Não","Sim") -> Não | AC19: =IF(S19="TSR","Serede","Rede Conecta") -> Serede
A20: 304057 | B20: INPI - INSTITUTO NACIONAL DA PROPRI | C20: 304057 | D20: 41831 | E20: R01144195314 | F20: RUA MARIO MARTINS COELHO 36 | G20: FORTALEZA | H20: ALDEOTA | I20: CE | J20: 60170-280 | K20: BR | S20: TSR | T20: FOPU | U20: =VLOOKUP(T20,Apoio!$D$10:$E$55,2,0) -> Órgãos Públicos - PJ | AA20: =IF(Y20="","Não","Sim") -> Não | AB20: =IF(Z20="","Não","Sim") -> Não | AC20: =IF(S20="TSR","Serede","Rede Conecta") -> Serede
A21: 304077 | B21: TRIBUNAL DE JUSTIÇA DO ESTADO DO CE | C21: 304077 | D21: 42031 | E21: R01144195314 | F21: AVENIDA GENERAL ALBUQUERQUE LIMA SN | G21: FORTALEZA | H21: CAMBEBA | I21: CE | J21: 60822-325 | K21: BR | S21: TSR | T21: FOPU | U21: =VLOOKUP(T21,Apoio!$D$10:$E$55,2,0) -> Órgãos Públicos - PJ | AA21: =IF(Y21="","Não","Sim") -> Não | AB21: =IF(Z21="","Não","Sim") -> Não | AC21: =IF(S21="TSR","Serede","Rede Conecta") -> Serede
A22: 304092 | B22: CONSELHO REGIONAL DE ENG E AGRON | C22: 304092 | D22: 42384 | E22: R60531985369 | F22: Av. Brigadeiro Faria Lima 1059 | G22: SAO PAULO | H22: PINHEIROS | I22: SP | J22: 014529-20 | K22: BR | R22: atendimento@creasp.org.br | S22: TSR | T22: FOPU | U22: =VLOOKUP(T22,Apoio!$D$10:$E$55,2,0) -> Órgãos Públicos - PJ | V22: 193336 | W22: 70824 | X22: 70 | AA22: =IF(Y22="","Não","Sim") -> Não | AB22: =IF(Z22="","Não","Sim") -> Não | AC22: =IF(S22="TSR","Serede","Rede Conecta") -> Serede
A23: 304099 | B23: DEPÓSITO JUDICIAL-TRESPASSE RS | C23: 304099 | D23: 42465 | E23: R04835156390 | F23: RUA MARCOS MACEDO 1333 | G23: FORTALEZA | H23: ALDEOTA | I23: CE | J23: 60150-190 | K23: BR | S23: TSR | T23: FOPU | U23: =VLOOKUP(T23,Apoio!$D$10:$E$55,2,0) -> Órgãos Públicos - PJ | AA23: =IF(Y23="","Não","Sim") -> Não | AB23: =IF(Z23="","Não","Sim") -> Não | AC23: =IF(S23="TSR","Serede","Rede Conecta") -> Serede
A24: 304114 | B24: DEPARTAMENTO ESTADUAL DE TRANSITO | C24: 304114 | D24: 42710 | E24: R04835156390 | F24: AV. MARQUES DE SANTA CRUZ 218 | G24: MANAUS | H24: CENTRO | I24: AM | J24: 69005-050 | K24: BR | S24: TSR | T24: FOPU | U24: =VLOOKUP(T24,Apoio!$D$10:$E$55,2,0) -> Órgãos Públicos - PJ | AA24: =IF(Y24="","Não","Sim") -> Não | AB24: =IF(Z24="","Não","Sim") -> Não | AC24: =IF(S24="TSR","Serede","Rede Conecta") -> Serede
A25: 304115 | B25: DEPARTAMENTO ESTADUAL DE TRANSITO | C25: 304115 | D25: 42710 | E25: R04835156390 | F25: AV. BRG. EDUARDO GOMES 4214 | G25: BOA VISTA | H25: AEROPORTO | I25: RR | J25: 69305-455 | K25: BR | S25: TSR | T25: FOPU | U25: =VLOOKUP(T25,Apoio!$D$10:$E$55,2,0) -> Órgãos Públicos - PJ | AA25: =IF(Y25="","Não","Sim") -> Não | AB25: =IF(Z25="","Não","Sim") -> Não | AC25: =IF(S25="TSR","Serede","Rede Conecta") -> Serede
A26: 304116 | B26: DEPARTAMENTO ESTADUAL DE TRANSITO | C26: 304116 | D26: 42711 | E26: R04835156390 | F26: AV. ANTONIO BORGES 212 | G26: GRAJAÚ | H26: TRIZIDELA | I26: MA | J26: 65940-000 | K26: BR | S26: TSR | T26: FOPU | U26: =VLOOKUP(T26,Apoio!$D$10:$E$55,2,0) -> Órgãos Públicos - PJ | AA26: =IF(Y26="","Não","Sim") -> Não | AB26: =IF(Z26="","Não","Sim") -> Não | AC26: =IF(S26="TSR","Serede","Rede Conecta") -> Serede
A27: 304117 | B27: DEPARTAMENTO ESTADUAL DE TRANSITO | C27: 304117 | D27: 42711 | E27: R04835156390 | F27: AV. INDUSTRIAL GIL MARTINS 2000 | G27: TERESINA | H27: REDENÇÃO | I27: PI | J27: 64019-630 | K27: BR | S27: TSR | T27: FOPU | U27: =VLOOKUP(T27,Apoio!$D$10:$E$55,2,0) -> Órgãos Públicos - PJ | AA27: =IF(Y27="","Não","Sim") -> Não | AB27: =IF(Z27="","Não","Sim") -> Não | AC27: =IF(S27="TSR","Serede","Rede Conecta") -> Serede
A28: 304118 | B28: DEPARTAMENTO ESTADUAL DE TRANSITO | C28: 304118 | D28: 42711 | E28: R04835156390 | F28: RUA RIO BRANCO 493 | G28: SANTA CRUZ | H28: CENTRO | I28: RN | J28: 59200-000 | K28: BR | S28: TSR | T28: FOPU | U28: =VLOOKUP(T28,Apoio!$D$10:$E$55,2,0) -> Órgãos Públicos - PJ | AA28: =IF(Y28="","Não","Sim") -> Não | AB28: =IF(Z28="","Não","Sim") -> Não | AC28: =IF(S28="TSR","Serede","Rede Conecta") -> Serede
A29: 304119 | B29: DEPARTAMENTO ESTADUAL DE TRANSITO | C29: 304119 | D29: 42711 | E29: R04835156390 | F29: RUA EMILIA BATISTA CELANE | G29: JOÃO PESSOA | H29: MANGABEIRA VII | I29: PB | J29: 58058-280 | K29: BR | S29: TSR | T29: FOPU | U29: =VLOOKUP(T29,Apoio!$D$10:$E$55,2,0) -> Órgãos Públicos - PJ | AA29: =IF(Y29="","Não","Sim") -> Não | AB29: =IF(Z29="","Não","Sim") -> Não | AC29: =IF(S29="TSR","Serede","Rede Conecta") -> Serede
A30: 304120 | B30: DEPARTAMENTO ESTADUAL DE TRANSITO | C30: 304120 | D30: 42711 | E30: R04835156390 | F30: AV. PRESIDENTE KENNEDY 1001 | G30: OLINDA | H30: PEIXINHOS | I30: PE | J30: 53230-630 | K30: BR | S30: TSR | T30: FOPU | U30: =VLOOKUP(T30,Apoio!$D$10:$E$55,2,0) -> Órgãos Públicos - PJ | AA30: =IF(Y30="","Não","Sim") -> Não | AB30: =IF(Z30="","Não","Sim") -> Não | AC30: =IF(S30="TSR","Serede","Rede Conecta") -> Serede
A31: 304121 | B31: DEPARTAMENTO ESTADUAL DE TRANSITO | C31: 304121 | D31: 42711 | E31: R04835156390 | F31: AV. MENINO MARCELO 99 | G31: MACEIÓ | H31: CIDADE UNIVERSITÁRIA | I31: AL | J31: 57073-470 | K31: BR | S31: TSR | T31: FOPU | U31: =VLOOKUP(T31,Apoio!$D$10:$E$55,2,0) -> Órgãos Públicos - PJ | AA31: =IF(Y31="","Não","Sim") -> Não | AB31: =IF(Z31="","Não","Sim") -> Não | AC31: =IF(S31="TSR","Serede","Rede Conecta") -> Serede
A32: 304122 | B32: DEPARTAMENTO ESTADUAL DE TRANSITO | C32: 304122 | D32: 42711 | E32: R04835156390 | F32: AV. TRANCREDO NEVES | G32: ARACAJU | H32: PONTO NOVO | I32: SE | J32: 49040-490 | K32: BR | S32: TSR | T32: FOPU | U32: =VLOOKUP(T32,Apoio!$D$10:$E$55,2,0) -> Órgãos Públicos - PJ | AA32: =IF(Y32="","Não","Sim") -> Não | AB32: =IF(Z32="","Não","Sim") -> Não | AC32: =IF(S32="TSR","Serede","Rede Conecta") -> Serede
A33: 304123 | B33: DEPARTAMENTO ESTADUAL DE TRANSITO | C33: 304123 | D33: 42711 | E33: R04835156390 | F33: RUA ANTONIO BARBOSA NASCIMENTO | G33: CANARANA | I33: BA | J33: 44890-000 | K33: BR | S33: TSR | T33: FOPU | U33: =VLOOKUP(T33,Apoio!$D$10:$E$55,2,0) -> Órgãos Públicos - PJ | AA33: =IF(Y33="","Não","Sim") -> Não | AB33: =IF(Z33="","Não","Sim") -> Não | AC33: =IF(S33="TSR","Serede","Rede Conecta") -> Serede
A34: 304124 | B34: DEPARTAMENTO ESTADUAL DE TRANSITO | C34: 304124 | D34: 42711 | E34: R04835156390 | F34: RUA TRANCREDO NEVES 217 | G34: MACAPÁ | H34: SÃO LÁZARO | I34: AP | J34: 68909-130 | K34: BR | S34: TSR | T34: FOPU | U34: =VLOOKUP(T34,Apoio!$D$10:$E$55,2,0) -> Órgãos Públicos - PJ | AA34: =IF(Y34="","Não","Sim") -> Não | AB34: =IF(Z34="","Não","Sim") -> Não | AC34: =IF(S34="TSR","Serede","Rede Conecta") -> Serede
A35: 304172 | B35: RECEITA FEDERAL DO BRASIL - CAC | C35: 304172 | D35: 43290 | E35: R04835156390 | F35: RUA CLAUDINO BENTO DA SILVA 11 | G35: FLORIANOPOLIS | H35: CENTRO | I35: SC | J35: 88010-135 | K35: BR | S35: TSR | T35: FOPU | U35: =VLOOKUP(T35,Apoio!$D$10:$E$55,2,0) -> Órgãos Públicos - PJ | AA35: =IF(Y35="","Não","Sim") -> Não | AB35: =IF(Z35="","Não","Sim") -> Não | AC35: =IF(S35="TSR","Serede","Rede Conecta") -> Serede
A36: 304173 | B36: PREVIDENCIA SOCIAL - AGENCIA | C36: 304173 | D36: 43290 | E36: R04835156390 | F36: RUA FELIPE SCHMIDT 331 | G36: FLORIANOPOLIS | H36: CENTRO | I36: SC | J36: 88010-000 | K36: BR | L36: (48) 3298-8000 | S36: TSR | T36: FOPU | U36: =VLOOKUP(T36,Apoio!$D$10:$E$55,2,0) -> Órgãos Públicos - PJ | AA36: =IF(Y36="","Não","Sim") -> Não | AB36: =IF(Z36="","Não","Sim") -> Não | AC36: =IF(S36="TSR","Serede","Rede Conecta") -> Serede
A37: 304174 | B37: SECRETARIA DA RECEITA FEDERAL | C37: 304174 | D37: 43290 | E37: R04835156390 | F37: AVENIDA PRESIDENTE CARLOS, 375 | G37: RIO DE JANEIRO | H37: CENTRO | I37: RJ | J37: 20020-001 | K37: BR | S37: TSR | T37: FOPU | U37: =VLOOKUP(T37,Apoio!$D$10:$E$55,2,0) -> Órgãos Públicos - PJ | AA37: =IF(Y37="","Não","Sim") -> Não | AB37: =IF(Z37="","Não","Sim") -> Não | AC37: =IF(S37="TSR","Serede","Rede Conecta") -> Serede
A38: 304175 | B38: INSTITUTO NACIONAL DO SEGURO SOCIAL | C38: 304175 | D38: 43290 | E38: R04835156390 | F38: RUA PEDRO LESSA | G38: RIO DE JANEIRO | H38: CENTRO | I38: RJ | J38: 20030-030 | K38: BR | S38: TSR | T38: FOPU | U38: =VLOOKUP(T38,Apoio!$D$10:$E$55,2,0) -> Órgãos Públicos - PJ | AA38: =IF(Y38="","Não","Sim") -> Não | AB38: =IF(Z38="","Não","Sim") -> Não | AC38: =IF(S38="TSR","Serede","Rede Conecta") -> Serede
A39: 205294 | B39: MUNICIPIO DE CAMPOS DOS GOYTACAZES | C39: 205294 | D39: 43291 | E39: R04835156390 | F39: R PONCIANO DE AZEVEDO FURTADO 47 | G39: CAMPOS DOS GOYTACAZES | H39: PARQUE SANTO AMARO | I39: RJ | J39: 28030-045 | K39: BR | S39: TSR | T39: FPRE | U39: =VLOOKUP(T39,Apoio!$D$10:$E$55,2,0) -> Prefeituras - PJ | AA39: =IF(Y39="","Não","Sim") -> Não | AB39: =IF(Z39="","Não","Sim") -> Não | AC39: =IF(S39="TSR","Serede","Rede Conecta") -> Serede
A40: 205295 | B40: MUNICIPIO DE VOLTA REDONDA | C40: 205295 | D40: 43291 | E40: R04835156390 | F40: PC SAVIO GAMA 53 | G40: VOLTA REDONDA | H40: ATERRADO | I40: RJ | J40: 27215-620 | K40: BR | S40: TSR | T40: FPRE | U40: =VLOOKUP(T40,Apoio!$D$10:$E$55,2,0) -> Prefeituras - PJ | AA40: =IF(Y40="","Não","Sim") -> Não | AB40: =IF(Z40="","Não","Sim") -> Não | AC40: =IF(S40="TSR","Serede","Rede Conecta") -> Serede
A41: 304176 | B41: TRIBUNAL REGIONAL DO TRABALHO DA | C41: 304176 | D41: 43291 | E41: R04835156390 | F41: RUA ALAMEDA DR. CARLOS DE CARVA 528 | G41: CURITIBA | H41: CENTRO | I41: PR | J41: 80430-180 | K41: BR | S41: TSR | T41: FOPU | U41: =VLOOKUP(T41,Apoio!$D$10:$E$55,2,0) -> Órgãos Públicos - PJ | AA41: =IF(Y41="","Não","Sim") -> Não | AB41: =IF(Z41="","Não","Sim") -> Não | AC41: =IF(S41="TSR","Serede","Rede Conecta") -> Serede
A42: 304177 | B42: RECEITA FEDERAL RS | C42: 304177 | D42: 43291 | E42: R04835156390 | F42: AV. LOUREIRO DA SILVA 445 | G42: PORTO ALEGRE | H42: CENTRO | I42: RS | J42: 90013-900 | K42: BR | S42: TSR | T42: FOPU | U42: =VLOOKUP(T42,Apoio!$D$10:$E$55,2,0) -> Órgãos Públicos - PJ | AA42: =IF(Y42="","Não","Sim") -> Não | AB42: =IF(Z42="","Não","Sim") -> Não | AC42: =IF(S42="TSR","Serede","Rede Conecta") -> Serede
A43: 304178 | B43: TRIBUNAL DE JUSTIÇA DO ESTADO DE | C43: 304178 | D43: 43291 | E43: R04835156390 | F43: PRAÇA DA SÉ S/N | G43: SAO PAULO | H43: CENTRO | I43: SP | J43: 01018-010 | K43: BR | S43: TSR | T43: FOPU | U43: =VLOOKUP(T43,Apoio!$D$10:$E$55,2,0) -> Órgãos Públicos - PJ | AA43: =IF(Y43="","Não","Sim") -> Não | AB43: =IF(Z43="","Não","Sim") -> Não | AC43: =IF(S43="TSR","Serede","Rede Conecta") -> Serede
A44: 304179 | B44: SECRETARIA DO ESTADO DA FAZENDA | C44: 304179 | D44: 43291 | E44: R04835156390 | F44: RUA SIQUEIRA CAMPOS 1044 | G44: PORTO ALEGRE | H44: CENTRO | I44: RS | J44: 90010-001 | K44: BR | S44: TSR | T44: FOPU | U44: =VLOOKUP(T44,Apoio!$D$10:$E$55,2,0) -> Órgãos Públicos - PJ | AA44: =IF(Y44="","Não","Sim") -> Não | AB44: =IF(Z44="","Não","Sim") -> Não | AC44: =IF(S44="TSR","Serede","Rede Conecta") -> Serede
A45: 304180 | B45: ESTADO DO PARA | C45: 304180 | D45: 43291 | E45: R04835156390 | F45: AV DOUTOR FREITAS 2531 | G45: BELEM | H45: PEDREIRA | I45: PA | J45: 66087-812 | K45: BR | S45: TSR | T45: FOPU | U45: =VLOOKUP(T45,Apoio!$D$10:$E$55,2,0) -> Órgãos Públicos - PJ | AA45: =IF(Y45="","Não","Sim") -> Não | AB45: =IF(Z45="","Não","Sim") -> Não | AC45: =IF(S45="TSR","Serede","Rede Conecta") -> Serede
A46: 304181 | B46: ESTADO DO RIO GRANDE DO SUL | C46: 304181 | D46: 43291 | E46: R04835156390 | F46: P MARECHAL DEODORO S/N | G46: PORTO ALEGRE | H46: CENTRO | I46: RS | J46: 90010-900 | K46: BR | S46: TSR | T46: FOPU | U46: =VLOOKUP(T46,Apoio!$D$10:$E$55,2,0) -> Órgãos Públicos - PJ | AA46: =IF(Y46="","Não","Sim") -> Não | AB46: =IF(Z46="","Não","Sim") -> Não | AC46: =IF(S46="TSR","Serede","Rede Conecta") -> Serede
A47: 304183 | B47: INSS - EMPRESA | C47: 304183 | D47: 43292 | E47: S02819545777 | F47: AV AFONSO PENA 342 | G47: BELO HORIZONTE | I47: MG | J47: 30130-001 | K47: BR | S47: TSR | T47: FOPU | U47: =VLOOKUP(T47,Apoio!$D$10:$E$55,2,0) -> Órgãos Públicos - PJ | AA47: =IF(Y47="","Não","Sim") -> Não | AB47: =IF(Z47="","Não","Sim") -> Não | AC47: =IF(S47="TSR","Serede","Rede Conecta") -> Serede
A48: 304188 | B48: INSS - EMPRESA | C48: 304188 | D48: 43315 | E48: C76149420353 | F48: AV AFONSO PENA 342 | G48: BELO HORIZONTE | H48: CENTRO | I48: MG | J48: 30130-001 | K48: BR | L48: 3132015511 | S48: TSR | T48: FOPU | U48: =VLOOKUP(T48,Apoio!$D$10:$E$55,2,0) -> Órgãos Públicos - PJ | AA48: =IF(Y48="","Não","Sim") -> Não | AB48: =IF(Z48="","Não","Sim") -> Não | AC48: =IF(S48="TSR","Serede","Rede Conecta") -> Serede
A49: 205364 | B49: SECRETARIA DE MUNICIPAL DE TRIBUTAÇ | C49: 205364 | D49: 44285 | E49: S09972319717 | F49: AÇU 394 | G49: NATAL | H49: TIROL | I49: RN | J49: 59020-110 | K49: BR | S49: TSR | T49: FPRE | U49: =VLOOKUP(T49,Apoio!$D$10:$E$55,2,0) -> Prefeituras - PJ | AA49: =IF(Y49="","Não","Sim") -> Não | AB49: =IF(Z49="","Não","Sim") -> Não | AC49: =IF(S49="TSR","Serede","Rede Conecta") -> Serede
A50: 2700076 | B50: Pipefy Inc | C50: 2700076 | D50: 45027 | E50: S13651914780 | F50: 548 MARKET STREET | G50: SAN FRANCISCO | J50: 94104-5401 | K50: UM | S50: TSR | T50: FEST | U50: =VLOOKUP(T50,Apoio!$D$10:$E$55,2,0) -> Fornecedor Estrangeiro | Z50: 45658 | AA50: =IF(Y50="","Não","Sim") -> Não | AB50: =IF(Z50="","Não","Sim") -> Sim | AC50: =IF(S50="TSR","Serede","Rede Conecta") -> Serede
A51: 2700081 | B51: THINK-CELL SOFTWARE GMBH | C51: 2700081 | D51: 45119 | E51: S14577845725 | F51: Leipziger Str. 51 | I51: 11 | J51: 10117 | K51: DE | L51: (030)3407-3618 | M51: (0 30) 34 07-24 65 | R51: sales@think-cell.com | S51: TSR | T51: FEST | U51: =VLOOKUP(T51,Apoio!$D$10:$E$55,2,0) -> Fornecedor Estrangeiro | AA51: =IF(Y51="","Não","Sim") -> Não | AB51: =IF(Z51="","Não","Sim") -> Não | AC51: =IF(S51="TSR","Serede","Rede Conecta") -> Serede
A52: 2700086 | B52: Web Services, Inc. | C52: 2700086 | D52: 45582 | E52: S14132293793 | F52: 420 Montgomery Street | G52: San Francisco | J52: 94163 | K52: UM | S52: TSR | T52: FEST | U52: =VLOOKUP(T52,Apoio!$D$10:$E$55,2,0) -> Fornecedor Estrangeiro | Z52: 45566 | AA52: =IF(Y52="","Não","Sim") -> Não | AB52: =IF(Z52="","Não","Sim") -> Sim | AC52: =IF(S52="TSR","Serede","Rede Conecta") -> Serede
A53: 304154 | B53: BANCO DO BRASIL SA | C53: 304154 | D53: 43278 | E53: C76149420353 | F53: R BUENOS AIRES 264 | G53: RIO DE JANEIRO | H53: CENTRO | I53: RJ | J53: 20061-000 | K53: BR | L53: 2122212877 | N53: 18309 | P53: ISENTO | Q53: ISENTO | S53: TSR | T53: FOPU | U53: =VLOOKUP(T53,Apoio!$D$10:$E$55,2,0) -> Órgãos Públicos - PJ | V53: 1911 | W53: X | X53: 6 | AA53: =IF(Y53="","Não","Sim") -> Não | AB53: =IF(Z53="","Não","Sim") -> Não | AC53: =IF(S53="TSR","Serede","Rede Conecta") -> Serede
A54: 100207 | B54: BANCO DO BRASIL SA | C54: 100207 | D54: 45373 | E54: S11995275727 | F54: QUINZE DE NOVEMBRO #20 13 a sl1302 | G54: RIO DE JANEIRO | H54: CENTRO | I54: RJ | J54: 20010-010 | K54: BR | L54: 21 32627300 | N54: 490695 | R54: AGE2234@BB.COM.BR | S54: TSR | T54: FPJU | U54: =VLOOKUP(T54,Apoio!$D$10:$E$55,2,0) -> Pagamentos judiciais - PJ | AA54: =IF(Y54="","Não","Sim") -> Não | AB54: =IF(Z54="","Não","Sim") -> Não | AC54: =IF(S54="TSR","Serede","Rede Conecta") -> Serede
A55: 2700066 | B55: LCG Analytics - Consultoria, Lda | C55: 2700066 | D55: 42690 | E55: R60531985369 | F55: António Champalimaud 3 – 114 | G55: 546 Lisboa | I55: 31 | J55: 1600 | K55: PT | N55: 510479383 | S55: TSR | T55: FEST | U55: =VLOOKUP(T55,Apoio!$D$10:$E$55,2,0) -> Fornecedor Estrangeiro | AA55: =IF(Y55="","Não","Sim") -> Não | AB55: =IF(Z55="","Não","Sim") -> Não | AC55: =IF(S55="TSR","Serede","Rede Conecta") -> Serede
A56: 304166 | B56: FUNDAÇÃO DE APOIO CEFET-RJ - FUNCEF | C56: 304166 | D56: 43278 | E56: C76149420353 | F56: RUA PEDRO GUEDES 74, CASA | G56: RIO DE AJNEIRO | H56: MARACANA | I56: RJ | J56: 20271-040 | K56: BR | L56: 2138725502 | N56: 92956000160 | P56: ISENTO | Q56: 2115158 | R56: pereira@brasilsigmatelecom.com.br | S56: TSR | T56: FOPU | U56: =VLOOKUP(T56,Apoio!$D$10:$E$55,2,0) -> Órgãos Públicos - PJ | V56: 2372666 | W56: 9100 | X56: 16 | AA56: =IF(Y56="","Não","Sim") -> Não | AB56: =IF(Z56="","Não","Sim") -> Não | AC56: =IF(S56="TSR","Serede","Rede Conecta") -> Serede
A57: 1816679 | B57: ATIC Tecnologia do Brasil Ltda | C57: 1816679 | D57: 44966 | E57: S13651914780 | F57: RUA AURIVERDE 1057 | G57: SÃO PAULO | I57: SP | J57: 04222-001 | K57: BR | L57: (11) 2925-5265 | N57: 118244000173 | P57: 147365673114 | R57: treinamento@aticdobrasil.com.br | S57: TSR | T57: FSDI | U57: =VLOOKUP(T57,Apoio!$D$10:$E$55,2,0) -> Fornec. de Serviç. Diversos PJ | V57: 40300001 | W57: 3683989 | X57: 3 | AA57: =IF(Y57="","Não","Sim") -> Não | AB57: =IF(Z57="","Não","Sim") -> Não | AC57: =IF(S57="TSR","Serede","Rede Conecta") -> Serede
A58: 300040 | B58: SINDIMEST- SIND. DA IND DE INST E M | C58: 300040 | D58: 41267 | E58: CARGA | F58: ARQUITETO LUIZ NUNES 1200 1200 | G58: RECIFE | H58: IMBIRIBEIRA | I58: PE | J58: 51170-430 | K58: BR | N58: 254217000128 | P58: 891827 | S58: TSR | T58: FOPU | U58: =VLOOKUP(T58,Apoio!$D$10:$E$55,2,0) -> Órgãos Públicos - PJ | V58: 10400651 | W58: 3264 | X58: 4 | AA58: =IF(Y58="","Não","Sim") -> Não | AB58: =IF(Z58="","Não","Sim") -> Não | AC58: =IF(S58="TSR","Serede","Rede Conecta") -> Serede
A59: 1817339 | B59: SOLO NETWORK BRASIL S/A | C59: 1817339 | D59: 45653 | E59: S14132293793 | F59: RODOVIA DEP. JOÃO LEOPOLDO 12.162 | G59: Pinhais | H59: Centro | I59: PR | J59: 83323-410 | K59: BR | L59: 21-989937277 | N59: 258246000168 | P59: 9058679116 | Q59: 69604 | R59: galber.figueiredo@solonetwork.com.br | S59: TSR | T59: FSDI | U59: =VLOOKUP(T59,Apoio!$D$10:$E$55,2,0) -> Fornec. de Serviç. Diversos PJ | V59: 34171568 | W59: 20222 | X59: 8 | AA59: =IF(Y59="","Não","Sim") -> Não | AB59: =IF(Z59="","Não","Sim") -> Não | AC59: =IF(S59="TSR","Serede","Rede Conecta") -> Serede
A60: 400020 | B60: ANTONIA S. DE SANTANA | C60: 400020 | D60: 41267 | E60: CARGA | F60: AVENIDA SANTOS DUMONT 2141 2141 | G60: SAO LUIS | H60: SAO CRISTOVAO | I60: MA | J60: 65000-000 | K60: BR | L60: 9832455040 | M60: 9832452828 | N60: 274326000107 | R60: atendimento@hotelitatiaiaslz.com.br | S60: TSR | T60: FHTP | U60: =VLOOKUP(T60,Apoio!$D$10:$E$55,2,0) -> Hotéis e Pousadas - PJ | V60: 23722121 | W60: 9855 | X60: 8 | AA60: =IF(Y60="","Não","Sim") -> Não | AB60: =IF(Z60="","Não","Sim") -> Não | AC60: =IF(S60="TSR","Serede","Rede Conecta") -> Serede
A61: 304095 | B61: CONSELHO REGIONAL DE ENG E AGRO | C61: 304095 | D61: 42390 | E61: R06187849345 | F61: SGAS Qd. 901 CJ D | G61: BRASILIA | H61: ASA SUL | I61: DF | J61: 70390-010 | K61: BR | L61: 61- 3961-280 | N61: 304725000173 | R61: atendimento@creadf.org.br | S61: TSR | T61: FOPU | U61: =VLOOKUP(T61,Apoio!$D$10:$E$55,2,0) -> Órgãos Públicos - PJ | V61: 194200 | W61: 200188 | X61: 58 | AA61: =IF(Y61="","Não","Sim") -> Não | AB61: =IF(Z61="","Não","Sim") -> Não | AC61: =IF(S61="TSR","Serede","Rede Conecta") -> Serede
A62: 1504112 | B62: AIR LIQUIDE BRASIL LTDA | C62: 1504112 | D62: 43279 | E62: C76149420353 | F62: ESTRADA BOA ESPERANÇA 650 | G62: BELFORD ROXO | H62: CENTRO | I62: RJ | J62: 26110-100 | K62: BR | L62: 2135413890 | N62: 331788000623 | P62: ISENTO | Q62: 3819 | R62: fabio.alves@airliquide.com | S62: TSR | T62: FMAT | U62: =VLOOKUP(T62,Apoio!$D$10:$E$55,2,0) -> Fornecedor de materiais - PJ | V62: 34171246 | W62: 18250 | X62: 3 | Z62: 45658 | AA62: =IF(Y62="","Não","Sim") -> Não | AB62: =IF(Z62="","Não","Sim") -> Sim | AC62: =IF(S62="TSR","Serede","Rede Conecta") -> Serede
A63: 1504067 | B63: AIR LIQUIDE BRASIL LTDA | C63: 1504067 | D63: 43278 | E63: C76149420353 | F63: RUA GENERAL DAVID CANABARRO 600 | G63: CANOAS | H63: CENTRO | I63: RS | J63: 92320-110 | K63: BR | L63: 1129154819 | N63: 331788002758 | P63: 024/0339754 | Q63: 58736 | R63: gabriela.rosa@airliquide.com | S63: TSR | T63: FMAT | U63: =VLOOKUP(T63,Apoio!$D$10:$E$55,2,0) -> Fornecedor de materiais - PJ | V63: 3417296 | W63: 42388 | X63: 2 | AA63: =IF(Y63="","Não","Sim") -> Não | AB63: =IF(Z63="","Não","Sim") -> Não | AC63: =IF(S63="TSR","Serede","Rede Conecta") -> Serede
A64: 1504072 | B64: AIR LIQUIDE BRASIL LTDA | C64: 1504072 | D64: 43278 | E64: C76149420353 | F64: RUA JOSÉ RODRIGUES PINHEIRO 3033 | G64: CURITIBA | H64: CIDADE INDL DE CURITIBA | I64: PR | J64: 81170-200 | K64: BR | N64: 331788003304 | P64: 101.49713-58 | Q64: 14.01.0466186-9 | R64: amanda.acetozzi@airliquide.com | S64: TSR | T64: FMAT | U64: =VLOOKUP(T64,Apoio!$D$10:$E$55,2,0) -> Fornecedor de materiais - PJ | V64: 3417624 | W64: 31725 | X64: 1 | AA64: =IF(Y64="","Não","Sim") -> Não | AB64: =IF(Z64="","Não","Sim") -> Não | AC64: =IF(S64="TSR","Serede","Rede Conecta") -> Serede
A65: 1504114 | B65: AIR LIQUIDE BRASIL LTDA | C65: 1504114 | D65: 43279 | E65: C76149420353 | F65: CORCOVADO 235, LOTE9 QD | G65: MACAE | H65: CAMBIUNAS | I65: RJ | J65: 27977-335 | K65: BR | N65: 331788004025 | P65: 77.900.56-0 | Q65: 195585 | R65: william.alencar@airliquide.com | S65: TSR | T65: FMAT | U65: =VLOOKUP(T65,Apoio!$D$10:$E$55,2,0) -> Fornecedor de materiais - PJ | V65: 34171246 | W65: 18250 | X65: 3 | AA65: =IF(Y65="","Não","Sim") -> Não | AB65: =IF(Z65="","Não","Sim") -> Não | AC65: =IF(S65="TSR","Serede","Rede Conecta") -> Serede
A66: 1815192 | B66: AIR LIQUIDE BRASIL LTDA | C66: 1815192 | D66: 43381 | E66: R04835156390 | F66: RUA PION GERTRUDE HECK FRITZEN 249 | G66: MARINGÁ | H66: JARDIM BERTIOGA | I66: PR | J66: 87055-406 | K66: BR | L66: 11-55096468 | N66: 331788004106 | P66: 9037113376 | Q66: 134453 | R66: marcelo.ferreira@airliquide.com | S66: TSR | T66: FSDI | U66: =VLOOKUP(T66,Apoio!$D$10:$E$55,2,0) -> Fornec. de Serviç. Diversos PJ | V66: 3417932 | W66: 57512 | X66: 9 | AA66: =IF(Y66="","Não","Sim") -> Não | AB66: =IF(Z66="","Não","Sim") -> Não | AC66: =IF(S66="TSR","Serede","Rede Conecta") -> Serede
A67: 1504121 | B67: AIR LIQUIDE BRASIL LTDA | C67: 1504121 | D67: 43279 | E67: C76149420353 | F67: AV. FERNANDO OSÓRIO 4476 | G67: PELOTAS | H67: TRÊS VENDAS | I67: RS | J67: 96065-000 | K67: BR | L67: 1129154819 | N67: 331788005269 | P67: 093/0419979 | Q67: 5979110 | R67: gabriela.rosa@airliquide.com | S67: TSR | T67: FMAT | U67: =VLOOKUP(T67,Apoio!$D$10:$E$55,2,0) -> Fornecedor de materiais - PJ | V67: 34177142 | W67: 3336 | X67: 9 | AA67: =IF(Y67="","Não","Sim") -> Não | AB67: =IF(Z67="","Não","Sim") -> Não | AC67: =IF(S67="TSR","Serede","Rede Conecta") -> Serede
A68: 1504070 | B68: AIR LIQUIDE BRASIL LTDA | C68: 1504070 | D68: 43278 | E68: C76149420353 | F68: HUMBERTO ZANONI 111 | G68: CAXIAS DO SUL | H68: CINQUENTENÁRIO | I68: RS | J68: 95012-410 | K68: BR | N68: 331788005420 | P68: 029/0551048 | Q68: 123934 | R68: tatiana.bucheroni@airliquide.com | S68: TSR | T68: FMAT | U68: =VLOOKUP(T68,Apoio!$D$10:$E$55,2,0) -> Fornecedor de materiais - PJ | V68: 3417480 | W68: 1699 | X68: 7 | AA68: =IF(Y68="","Não","Sim") -> Não | AB68: =IF(Z68="","Não","Sim") -> Não | AC68: =IF(S68="TSR","Serede","Rede Conecta") -> Serede
A69: 1815864 | B69: AIR LIQUIDE BRASIL LTDA | C69: 1815864 | D69: 43934 | E69: S00069814708 | F69: EXPEDICIONARIO JOAO B ALBERTON 500 | G69: GARIBALDI | H69: TAMANDARÉ | I69: RS | J69: 95720-000 | K69: BR | L69: 31 3119 9236 | N69: 331788005501 | P69: 050/0071764 | Q69: 33276 | R69: br-atendimento-serede@airliquide.com | S69: TSR | T69: FSDI | U69: =VLOOKUP(T69,Apoio!$D$10:$E$55,2,0) -> Fornec. de Serviç. Diversos PJ | V69: 34170574 | W69: 48509 | X69: 0 | AA69: =IF(Y69="","Não","Sim") -> Não | AB69: =IF(Z69="","Não","Sim") -> Não | AC69: =IF(S69="TSR","Serede","Rede Conecta") -> Serede
A70: 1504118 | B70: AIR LIQUIDE BRASIL LTDA | C70: 1504118 | D70: 43279 | E70: C76149420353 | F70: TRAVESSA ADÃO COMASSETO 170 | G70: SANTA MARIA | H70: DIACONO JOÃO LUIZ POZZO | I70: RS | J70: 97060-485 | K70: BR | N70: 331788006583 | P70: 109/0371621 | Q70: 98314540 | R70: gabriela.rosa@airliquide.com | S70: TSR | T70: FMAT | U70: =VLOOKUP(T70,Apoio!$D$10:$E$55,2,0) -> Fornecedor de materiais - PJ | V70: 34175434 | W70: 5529 | X70: 8 | AA70: =IF(Y70="","Não","Sim") -> Não | AB70: =IF(Z70="","Não","Sim") -> Não | AC70: =IF(S70="TSR","Serede","Rede Conecta") -> Serede
A71: 1815194 | B71: AIR LIQUIDE BRASIL LTDA | C71: 1815194 | D71: 43381 | E71: R04835156390 | F71: RUA GENERAL OSORIO 1716 | G71: CASCAVEL | H71: PARQUE SAO PAULO | I71: PR | J71: 85803-760 | K71: BR | L71: 11-55096468 | N71: 331788007040 | P71: 9065369513 | Q71: 86989 | R71: marcelo.ferreira@airliquide.com | S71: TSR | T71: FSDI | U71: =VLOOKUP(T71,Apoio!$D$10:$E$55,2,0) -> Fornec. de Serviç. Diversos PJ | V71: 34173322 | W71: 21615 | X71: 5 | AA71: =IF(Y71="","Não","Sim") -> Não | AB71: =IF(Z71="","Não","Sim") -> Não | AC71: =IF(S71="TSR","Serede","Rede Conecta") -> Serede
A72: 300139 | B72: EMPRESA BRASILEIRA DE INFRA-ESTRUTU | C72: 300139 | D72: 41267 | E72: CARGA | F72: SCS - QUADRA 04 BLOCO A SN | G72: BRASILIA | H72: VIA SUL | I72: DF | J72: 70310-500 | K72: BR | M72: 6133123542 | N72: 352294000110 | R72: cobranca@infraero.gov.br | S72: TSR | T72: FOPU | U72: =VLOOKUP(T72,Apoio!$D$10:$E$55,2,0) -> Órgãos Públicos - PJ | AA72: =IF(Y72="","Não","Sim") -> Não | AB72: =IF(Z72="","Não","Sim") -> Não | AC72: =IF(S72="TSR","Serede","Rede Conecta") -> Serede
A73: 1817137 | B73: AUTO POSTO PRUDENTE LTDA | C73: 1817137 | D73: 45572 | E73: LSMW | F73: RUA BLUMENAU,3011 | G73: JOINVILLE | H73: SANTO ANTONIO | I73: SC | J73: 89204-251 | K73: BR | L73: 47 32415016 | N73: 354911000117 | P73: 252983017 | S73: TSR | T73: FSDI | U73: =VLOOKUP(T73,Apoio!$D$10:$E$55,2,0) -> Fornec. de Serviç. Diversos PJ | AA73: =IF(Y73="","Não","Sim") -> Não | AB73: =IF(Z73="","Não","Sim") -> Não | AC73: =IF(S73="TSR","Serede","Rede Conecta") -> Serede
A74: 1813959 | B74: GERSON ANTONIO GONÇALVES - ME | C74: 1813959 | D74: 42202 | E74: R96203110353 | F74: AV. AMARÍLIO THIAGO 52 | G74: LAURO DE FREITAS | H74: CENTRO | I74: BA | J74: 42700-000 | K74: BR | L74: 7133785362 | N74: 355435000159 | P74: 40912635 | Q74: 10004801 | S74: TSR | T74: FSDI | U74: =VLOOKUP(T74,Apoio!$D$10:$E$55,2,0) -> Fornec. de Serviç. Diversos PJ | V74: 23723549 | W74: 12314 | X74: 5 | AA74: =IF(Y74="","Não","Sim") -> Não | AB74: =IF(Z74="","Não","Sim") -> Não | AC74: =IF(S74="TSR","Serede","Rede Conecta") -> Serede
A75: 100011 | B75: CAIXA ECONOMICA FEDERAL | C75: 100011 | D75: 41267 | E75: CARGA | F75: SBS QUADRA 4 BLOCO A LOTE SN SN | G75: BRASILIA | H75: ASA SUL | I75: DF | J75: 70092-900 | K75: BR | N75: 360305000104 | S75: TSR | T75: FPJU | U75: =VLOOKUP(T75,Apoio!$D$10:$E$55,2,0) -> Pagamentos judiciais - PJ | V75: 0 | W75: 99999999 | X75: 0 | AA75: =IF(Y75="","Não","Sim") -> Não | AB75: =IF(Z75="","Não","Sim") -> Não | AC75: =IF(S75="TSR","Serede","Rede Conecta") -> Serede
A76: 304182 | B76: CAIXA ECONOMICA FEDERAL | C76: 304182 | D76: 43292 | E76: S02819545777 | F76: R MARIZ E BARROS 79 A | G76: PRACA DA BANDEIRA | I76: RJ | J76: 20270-001 | K76: BR | L76: 2125020044 | N76: 360305020210 | P76: ISENTO | Q76: ISENTO | S76: TSR | T76: FOPU | U76: =VLOOKUP(T76,Apoio!$D$10:$E$55,2,0) -> Órgãos Públicos - PJ | V76: 198 | W76: X | X76: 6 | AA76: =IF(Y76="","Não","Sim") -> Não | AB76: =IF(Z76="","Não","Sim") -> Não | AC76: =IF(S76="TSR","Serede","Rede Conecta") -> Serede
A77: 304159 | B77: CAIXA ECONOMICA FEDERAL | C77: 304159 | D77: 43278 | E77: C76149420353 | F77: AV RIO BRANCO 174 | G77: RIO DE JANEIRO | H77: CENTRO | I77: RJ | J77: 20040-003 | K77: BR | L77: 2122023861 | N77: 360305267453 | P77: 84.120.97-9 | Q77: ISENTO | S77: TSR | T77: FOPU | U77: =VLOOKUP(T77,Apoio!$D$10:$E$55,2,0) -> Órgãos Públicos - PJ | V77: 191605 | W77: Y | X77: 5 | AA77: =IF(Y77="","Não","Sim") -> Não | AB77: =IF(Z77="","Não","Sim") -> Não | AC77: =IF(S77="TSR","Serede","Rede Conecta") -> Serede
A78: 304191 | B78: ORDEM DOS ADVOGADOS DO BRASIL - DF | C78: 304191 | D78: 43315 | E78: C76149420353 | F78: SEPN NORTE 516, LOTE 07 | G78: BRASÍLIA | H78: ASA NORTE | I78: DF | J78: 70770-552 | K78: BR | L78: (61) 3035 7234 | N78: 368019000195 | S78: TSR | T78: FOPU | U78: =VLOOKUP(T78,Apoio!$D$10:$E$55,2,0) -> Órgãos Públicos - PJ | AA78: =IF(Y78="","Não","Sim") -> Não | AB78: =IF(Z78="","Não","Sim") -> Não | AC78: =IF(S78="TSR","Serede","Rede Conecta") -> Serede
A79: 300138 | B79: INSTITUTO NACIONAL DE COLONIZACAO E | C79: 300138 | D79: 41267 | E79: CARGA | F79: ED PAL DESENVOLVIMENTO SN | G79: BRASILIA | H79: SBN | I79: DF | J79: 70310-500 | K79: BR | N79: 375972000160 | S79: TSR | T79: FOPU | U79: =VLOOKUP(T79,Apoio!$D$10:$E$55,2,0) -> Órgãos Públicos - PJ | AA79: =IF(Y79="","Não","Sim") -> Não | AB79: =IF(Z79="","Não","Sim") -> Não | AC79: =IF(S79="TSR","Serede","Rede Conecta") -> Serede
A80: 1817127 | B80: POSTO BERTAMONI LTDA | C80: 1817127 | D80: 45572 | E80: LSMW | F80: RUA WILLY BARTH,3845 | G80: SAO MIGUEL DO OESTE | H80: CENTRO | I80: SC | J80: 89900-000 | K80: BR | L80: 47 32415016 | N80: 376885000128 | P80: 252936221 | S80: TSR | T80: FSDI | U80: =VLOOKUP(T80,Apoio!$D$10:$E$55,2,0) -> Fornec. de Serviç. Diversos PJ | AA80: =IF(Y80="","Não","Sim") -> Não | AB80: =IF(Z80="","Não","Sim") -> Não | AC80: =IF(S80="TSR","Serede","Rede Conecta") -> Serede
A81: 100190 | B81: MINISTÉRIO DA ECONOMIA | C81: 100190 | D81: 43900 | E81: S18172880758 | F81: Esplanada dos Ministérios, BLOCO F | G81: BRASÍLIA - DF | H81: Zona Cívico-Administrativ | I81: DF | J81: 70050-000 | K81: BR | N81: 394460000141 | S81: TSR | T81: FPJU | U81: =VLOOKUP(T81,Apoio!$D$10:$E$55,2,0) -> Pagamentos judiciais - PJ | AA81: =IF(Y81="","Não","Sim") -> Não | AB81: =IF(Z81="","Não","Sim") -> Não | AC81: =IF(S81="TSR","Serede","Rede Conecta") -> Serede
A82: 1816309 | B82: Receita Federal | C82: 1816309 | D82: 44523 | E82: S09972319717 | F82: Pres. Antônio Carlos 375 | G82: Rio de Janeiro | H82: Centro | I82: RJ | J82: 20020-010 | K82: BR | N82: 394460005887 | S82: TSR | T82: FSDI | U82: =VLOOKUP(T82,Apoio!$D$10:$E$55,2,0) -> Fornec. de Serviç. Diversos PJ | AA82: =IF(Y82="","Não","Sim") -> Não | AB82: =IF(Z82="","Não","Sim") -> Não | AC82: =IF(S82="TSR","Serede","Rede Conecta") -> Serede
A83: 100060 | B83: UNIAO PRFN | C83: 100060 | D83: 42432 | E83: R04835156390 | F83: AV. A. J. RENNER 681 | G83: PORTO ALEGRE | H83: FARRAPOS | I83: RS | J83: 9024-5000 | K83: BR | N83: 394460021653 | S83: TSR | T83: FPJU | U83: =VLOOKUP(T83,Apoio!$D$10:$E$55,2,0) -> Pagamentos judiciais - PJ | AA83: =IF(Y83="","Não","Sim") -> Não | AB83: =IF(Z83="","Não","Sim") -> Não | AC83: =IF(S83="TSR","Serede","Rede Conecta") -> Serede
A84: 304200 | B84: CUSTAS - MINISTÉRIO DA FAZENDA | C84: 304200 | D84: 43333 | E84: R04835156390 | F84: ED. SEDE DO MINISTERIO DA FAZENDA | G84: BRASILIA | H84: ESPLANADA DOS MINISTERIOS | I84: DF | J84: 70048-900 | K84: BR | N84: 394460033236 | S84: TSR | T84: FOPU | U84: =VLOOKUP(T84,Apoio!$D$10:$E$55,2,0) -> Órgãos Públicos - PJ | AA84: =IF(Y84="","Não","Sim") -> Não | AB84: =IF(Z84="","Não","Sim") -> Não | AC84: =IF(S84="TSR","Serede","Rede Conecta") -> Serede
A85: 304160 | B85: MINISTERIO DA FAZENDA | C85: 304160 | D85: 43278 | E85: C76149420353 | F85: AV. PRES. ANTONIO CARLO 375, SL.421 | G85: RIO DE JANEIRO | H85: CASTELO | I85: RJ | J85: 20062-970 | K85: BR | L85: 2138052000 | N85: 394460034631 | P85: ISENTO | Q85: ISENTO | S85: TSR | T85: FOPU | U85: =VLOOKUP(T85,Apoio!$D$10:$E$55,2,0) -> Órgãos Públicos - PJ | V85: 191605 | W85: X | X85: 5 | AA85: =IF(Y85="","Não","Sim") -> Não | AB85: =IF(Z85="","Não","Sim") -> Não | AC85: =IF(S85="TSR","Serede","Rede Conecta") -> Serede
A86: 1817015 | B86: MINISTERIO DA JUSTICA E SEGURANCA P | C86: 1817015 | D86: 45506 | E86: S14577845725 | F86: SETOR POLICIAL LOTE 5 | G86: BRASILIA | I86: DF | J86: 70610-200 | K86: BR | N86: 394494010441 | S86: TSR | T86: FSDI | U86: =VLOOKUP(T86,Apoio!$D$10:$E$55,2,0) -> Fornec. de Serviç. Diversos PJ | AA86: =IF(Y86="","Não","Sim") -> Não | AB86: =IF(Z86="","Não","Sim") -> Não | AC86: =IF(S86="TSR","Serede","Rede Conecta") -> Serede
A87: 300111 | B87: SECRETARIA DE RECEITA ESTADUAL DO A | C87: 300111 | D87: 41267 | E87: CARGA | F87: AVENIDA RAIMUNDO ALVARES DA COS 367 | G87: MACAPA | H87: CENTRAL | I87: AP | J87: 68900-074 | K87: BR | L87: 9621013122 | N87: 394577000125 | R87: secretario@sre.ap.gov.br | S87: TSR | T87: FOPU | U87: =VLOOKUP(T87,Apoio!$D$10:$E$55,2,0) -> Órgãos Públicos - PJ | AA87: =IF(Y87="","Não","Sim") -> Não | AB87: =IF(Z87="","Não","Sim") -> Não | AC87: =IF(S87="TSR","Serede","Rede Conecta") -> Serede
A88: 1816909 | B88: SECRETARIA DA FAZENDA DO DOSTRITO F | C88: 1816909 | D88: 45308 | E88: S14577845725 | F88: Anexo Do Palacio Buriti 1032 | G88: BRASILIA | H88: Eixo Monumental | I88: DF | J88: 70075-900 | K88: BR | L88: 0613414-6181 | N88: 394601000126 | S88: TSR | T88: FSDI | U88: =VLOOKUP(T88,Apoio!$D$10:$E$55,2,0) -> Fornec. de Serviç. Diversos PJ | AA88: =IF(Y88="","Não","Sim") -> Não | AB88: =IF(Z88="","Não","Sim") -> Não | AC88: =IF(S88="TSR","Serede","Rede Conecta") -> Serede
A89: 400116 | B89: FERNANDO LUIS MENGER | C89: 400116 | D89: 41267 | E89: CARGA | F89: RUA FERNANDO AMARAL 19 SN | G89: TRAMANDAI | H89: CENTRO | I89: RS | J89: 95590-000 | K89: BR | L89: 5136611154 | N89: 395206000168 | S89: TSR | T89: FHTP | U89: =VLOOKUP(T89,Apoio!$D$10:$E$55,2,0) -> Hotéis e Pousadas - PJ | V89: 23721878 | W89: 11267 | X89: 34 | AA89: =IF(Y89="","Não","Sim") -> Não | AB89: =IF(Z89="","Não","Sim") -> Não | AC89: =IF(S89="TSR","Serede","Rede Conecta") -> Serede
A90: 1815139 | B90: DPR TELECOMUNICACOES LTDA | C90: 1815139 | D90: 43325 | E90: R04835156390 | F90: YASHICA 65 | G90: SOROCABA | H90: JARDIM GONCALVES | I90: SP | J90: 18016-440 | K90: BR | L90: 11 3934-2000 | N90: 422413000407 | P90: 798140000000 | Q90: 360683 | R90: njoviano@dpr.com.br | S90: TSR | T90: FSDI | U90: =VLOOKUP(T90,Apoio!$D$10:$E$55,2,0) -> Fornec. de Serviç. Diversos PJ | V90: 34176485 | W90: 1569 | X90: 4 | AA90: =IF(Y90="","Não","Sim") -> Não | AB90: =IF(Z90="","Não","Sim") -> Não | AC90: =IF(S90="TSR","Serede","Rede Conecta") -> Serede
A91: 1814759 | B91: CALASANS PRESTADORA DE SERVICOS LTD | C91: 1814759 | D91: 43024 | E91: R04835156390 | F91: AV. LUIZ GONZAGA (ANTIGA AV. O 58 A | G91: CAMACARI | H91: POOCK II | I91: BA | J91: 42805-001 | K91: BR | L91: (71) 3621-3154 | N91: 450680000145 | R91: pousadaideal@pousadaideal.com.br | S91: TSR | T91: FSDI | U91: =VLOOKUP(T91,Apoio!$D$10:$E$55,2,0) -> Fornec. de Serviç. Diversos PJ | V91: 191238 | W91: 11013 | X91: 62 | AA91: =IF(Y91="","Não","Sim") -> Não | AB91: =IF(Z91="","Não","Sim") -> Não | AC91: =IF(S91="TSR","Serede","Rede Conecta") -> Serede
A92: 1816745 | B92: UPS LOGISTICA (BRASIL) LTDA | C92: 1816745 | D92: 45057 | E92: S14577845725 | F92: RUA ALVARES CABRAL, 943 | G92: FORTALEZA | H92: SERRINHA | I92: CE | J92: 60741-200 | K92: BR | L92: 8118 2942 | N92: 462691001389 | P92: 67141056 | R92: helpfuljaislainesantos@ups.com | S92: TSR | T92: FSDI | U92: =VLOOKUP(T92,Apoio!$D$10:$E$55,2,0) -> Fornec. de Serviç. Diversos PJ | AA92: =IF(Y92="","Não","Sim") -> Não | AB92: =IF(Z92="","Não","Sim") -> Não | AC92: =IF(S92="TSR","Serede","Rede Conecta") -> Serede
A93: 1817039 | B93: Sky Servicos De Banda Larga Ltda | C93: 1817039 | D93: 45540 | E93: S14132293793 | F93: RUA ALBINO KAMINSKI 645 | G93: curitiba | H93: BAIRRO ALTO | I93: PR | J93: 82820-310 | K93: BR | L93: 11 2123-0192 | N93: 497373004026 | P93: 9072645992 | R93: felipe.garcia@sky.com.br | S93: TSR | T93: FSDI | U93: =VLOOKUP(T93,Apoio!$D$10:$E$55,2,0) -> Fornec. de Serviç. Diversos PJ | AA93: =IF(Y93="","Não","Sim") -> Não | AB93: =IF(Z93="","Não","Sim") -> Não | AC93: =IF(S93="TSR","Serede","Rede Conecta") -> Serede
A94: 1817038 | B94: Sky Servicos De Banda Larga Ltda | C94: 1817038 | D94: 45539 | E94: S14132293793 | F94: Rua Ernesto Fontoura 1500 | G94: Porto Alegre | H94: Sao Geraldo | I94: RS | J94: 902300-90 | K94: BR | L94: (11) 2123-0224 | N94: 497373004611 | P94: 963691767 | R94: skyoperacoestributariascenu@sky.com.br | S94: TSR | T94: FSDI | U94: =VLOOKUP(T94,Apoio!$D$10:$E$55,2,0) -> Fornec. de Serviç. Diversos PJ | AA94: =IF(Y94="","Não","Sim") -> Não | AB94: =IF(Z94="","Não","Sim") -> Não | AC94: =IF(S94="TSR","Serede","Rede Conecta") -> Serede
A95: 1816635 | B95: Frazillio Solucoes de Tecnologia Lt | C95: 1816635 | D95: 44882 | E95: S13651914780 | F95: Avenida Marquês de 2219, Sala 1008 | G95: São Paulo | H95: Agua Branca | I95: SP | J95: 05036-040 | K95: BR | L95: (11) 3224-1900 | N95: 510077000101 | P95: 114369000000 | Q95: 23637030 | R95: leticia.almeida@ff.solutions | S95: TSR | T95: FSDI | U95: =VLOOKUP(T95,Apoio!$D$10:$E$55,2,0) -> Fornec. de Serviç. Diversos PJ | V95: 191195 | W95: 380922 | X95: 96 | AA95: =IF(Y95="","Não","Sim") -> Não | AB95: =IF(Z95="","Não","Sim") -> Não | AC95: =IF(S95="TSR","Serede","Rede Conecta") -> Serede
A96: 1816975 | B96: SILVETUR AGENCIA DE VIAGEM E TURISM | C96: 1816975 | D96: 45443 | E96: S11995275727 | F96: R CEL PEDRO DEMORO 2063 | G96: FLORIANOPOLIS | H96: ESTREITO | I96: SC | J96: 88075-301 | K96: BR | L96: 048 99822462 | N96: 517288000176 | R96: SILVETURTURISMO@TERRA.COM.BR | S96: TSR | T96: FSDI | U96: =VLOOKUP(T96,Apoio!$D$10:$E$55,2,0) -> Fornec. de Serviç. Diversos PJ | V96: 191386 | W96: 31817 | X96: 25 | Z96: 45444 | AA96: =IF(Y96="","Não","Sim") -> Não | AB96: =IF(Z96="","Não","Sim") -> Sim | AC96: =IF(S96="TSR","Serede","Rede Conecta") -> Serede
A97: 1816932 | B97: Art Factory Industrial e Comercial | C97: 1816932 | D97: 45363 | E97: S11995275727 | F97: Rua Antonio Garcia Domingue 125/127 | G97: Itaquaquecetuba | H97: Vila Menezes | I97: SP | J97: 08599-390 | K97: BR | L97: 11 4645-2058 | M97: 11 4645-1077 | N97: 527781000177 | P97: 379048000000 | R97: cleo.almeida@artfactoryind.com.br | S97: TSR | T97: FSDI | U97: =VLOOKUP(T97,Apoio!$D$10:$E$55,2,0) -> Fornec. de Serviç. Diversos PJ | V97: 23721261 | W97: 33225 | X97: 9 | Z97: 45352 | AA97: =IF(Y97="","Não","Sim") -> Não | AB97: =IF(Z97="","Não","Sim") -> Sim | AC97: =IF(S97="TSR","Serede","Rede Conecta") -> Serede
A98: 304196 | B98: SUPREMO TRIBUNAL FEDERAL | C98: 304196 | D98: 43315 | E98: C76149420353 | F98: LOC PCA DOS TRES PODERES S/N | G98: BRASILIA | H98: EIXO MONUMENTAL | I98: DF | J98: 70175-900 | K98: BR | N98: 531640000128 | S98: TSR | T98: FOPU | U98: =VLOOKUP(T98,Apoio!$D$10:$E$55,2,0) -> Órgãos Públicos - PJ | AA98: =IF(Y98="","Não","Sim") -> Não | AB98: =IF(Z98="","Não","Sim") -> Não | AC98: =IF(S98="TSR","Serede","Rede Conecta") -> Serede
A99: 1814871 | B99: DEDETIZACAO CAMPO GRANDE LTDA ME | C99: 1814871 | D99: 43278 | E99: C76149420353 | F99: Cachamorra 2.441 | G99: RIO DE JANEIRO | H99: CAMPO GRANDE | I99: RJ | J99: 23040-150 | K99: BR | L99: 21 2413-3178 | N99: 665150000114 | P99: 01.869.66-3 | Q99: 1869663 | R99: cgdedetizacao20@gmail.com | S99: TSR | T99: FSDI | U99: =VLOOKUP(T99,Apoio!$D$10:$E$55,2,0) -> Fornec. de Serviç. Diversos PJ | V99: 19127 | W99: 30149 | X99: 93 | Z99: 45658 | AA99: =IF(Y99="","Não","Sim") -> Não | AB99: =IF(Z99="","Não","Sim") -> Sim | AC99: =IF(S99="TSR","Serede","Rede Conecta") -> Serede
A100: 300147 | B100: SINDICATO DAS IND E EMPRESAS DE INS | C100: 300147 | D100: 41267 | E100: CARGA | F100: AVENIDA CANDIDO DE ABREU 427 427 | G100: CURITIBA | H100: CENTRO CIVICO | I100: PR | J100: 80530-000 | K100: BR | N100: 668588000156 | R100: siitep@siitep.com.br | S100: TSR | T100: FOPU | U100: =VLOOKUP(T100,Apoio!$D$10:$E$55,2,0) -> Órgãos Públicos - PJ | V100: 23721342 | W100: 47242 | X100: 5 | AA100: =IF(Y100="","Não","Sim") -> Não | AB100: =IF(Z100="","Não","Sim") -> Não | AC100: =IF(S100="TSR","Serede","Rede Conecta") -> Serede
...

Sheet Apoio
C3: Utilizados hoje | D3: FSDI | E3: Serviços
D4: FFUN | E4: Funcionários
D5: FPFZ | E5: PF
D6: FPRE | E6: Prefeitura
D10: 1 | E10: Fornecedor
D11: 2 | E11: Fornecedor de mercadoria
D12: 3 | E12: Recebedor alternativo pgto.
D13: 4 | E13: Emissor da fatura
D14: 5 | E14: Agente de frete
D15: 6 | E15: Endereço de pedido
D16: 7 | E16: Centros
D17: 12 | E17: Nó de hierarquia
D18: 100 | E18: Fornecedor-centro de distrib.
D19: CPD | E19: Fornecedores CD (atrib.int.nº)
D20: CPDL | E20: Fornecedores CD (atrib.ext.nº)
D21: DARL | E21: Mutuante
D22: FCON | E22: Consultorias - PJ
D23: FESA | E23: Segurança e Monitoramento - PJ
D24: FEST | E24: Fornecedor Estrangeiro
D25: FEXM | E25: Exames médicos - PJ
D26: FFRT | E26: Fretes - PJ
D27: FFUN | E27: Funcionários - PF
D28: FHTP | E28: Hotéis e Pousadas - PJ
D29: FLEP | E29: Locação de Equipamentos - PJ
D30: FLVE | E30: Locação de veículos - PJ
... D55: YPFI | E55: Fornecedor Pessoa Física
