Workbook

Sheet Resumo
C2: 46021 | D2: 45660
B3: Aquisição CNPJ | C3: V1 | D3: 22 VIRTUAL + 5 FÍSICAS | E3: 27 FÍSICAS | G3: Confirmado?
B4: ='Custos De Compra CNPJ - Societ.'!B4 -> Honorários + Impostos a calcular - ISS (5%), PIS/COFINS (9,25%) | C4: ='Custos De Compra CNPJ - Societ.'!C4 -> 9248.55 | D4: 9248.55 | E4: 9248.55 | G4: NA | H4: 15500
B5: ='Custos De Compra CNPJ - Societ.'!B22 -> Taxa de registro na JUCERJA | C5: ='Custos De Compra CNPJ - Societ.'!C22 -> 754 | D5: 1000 | E5: 1000 | G5: ok - Marina | H5: 4000
B6: Públicação da ata de AGE (alteração estatutária) e Estatuto Social (ato registrado pelo Eduardo Duarte), alteração de objeto social | C6: ='Custos De Compra CNPJ - Societ.'!C25 -> 28644 | D6: 3000 | E6: 3000 | G6: ok - Marina | H6: =H4-H5 -> 11500
B7: Custos de ATD à fiscalização para matriz* (1 no RJ) | C7: ='Custos para Abertura de Filiais'!C3 -> 4000 | D7: 4000 | E7: 4000 | G7: Ver c/ ATF
B8: Certificado Digital | C8: ='Custos para Abertura de Filiais'!C4 -> 3000 | D8: 3000 | E8: 3000 | G8: Ver c/ ATF
B9: Total | C9: =SUM(C4:C8) -> 45646.55 | D9: =SUM(D4:D8) -> 20248.55 | E9: =SUM(E4:E8) -> 20248.55
B11: Abertura de Filiais
B12: Procurações públicas da ClientCo (13 despachantes, sendo R$ 550 por procuração) | C12: ='Custos De Compra CNPJ - Societ.'!F33 -> 7150 | D12: =C12 -> 7150 | E12: =C12 -> 7150 | G12: Ver c/ ATF
B13: Registro das atas de ReDir da ClientCo (abertura de filiais - R$ 1000 por ata) | C13: ='Custos De Compra CNPJ - Societ.'!F31 -> 19604 | D13: =1000*26 -> 26000 | E13: =1000*26 -> 26000 | G13: ok - Marina
B14: Publicação de ReDir ClientCo (abertura de filiais - R$ 1000,00 por ata publicada) | C14: ='Custos De Compra CNPJ - Societ.'!F32 -> 16380 | D14: =1000*26 -> 26000 | E14: =1000*26 -> 26000 | G14: ok - Marina
B15: Custos de ATD à fiscalização para abertura de filial RN física = R$4.000/ Virtual = R$300,00 unit | D15: 4000 | E15: 4000 | G15: Ver c/ ATF
B16: Custos de ATD à fiscalização para abertura de filial (25 UFs - R$4.000/ 25 Ufs virtuais - R$300,00 unit) | C16: ='Custos para Abertura de Filiais'!J7-C7 -> 11500 | D16: =25*300 -> 7500 | E16: =25*4000 -> 100000 | G16: Ver c/ ATF
B17: Total | C17: =SUM(C12:C16) -> 54634 | D17: =SUM(D12:D16) -> 70650 | E17: =SUM(E12:E16) -> 163150
B19: Valores aluguel de filiais (Ends Oi + Wework e Company Hero) - estimados por 3 Meses | D19: =('Aluguel_Oi e 3º_Previsão'!G2+'Aluguel_Oi e 3º_Previsão'!G12+'Aluguel_Oi e 3º_Previsão'!G10+'Aluguel_Oi e 3º_Previsão'!G23+'Aluguel_Oi e 3º_Previsão'!G20)*3 -> 20349.93 | E19: =35019.66*3 -> 105058.98
C21: =C9+C17+C19 -> 100280.55 | D21: =D9+D17+D19 -> 111248.48 | E21: =E9+E17+E19 -> 288457.53
B22: *Já temos filiais físicas abertas: RJ, PR, GO e SC
B23: (*) Itens envolvidos
B24: Confecção de DBE junto a Receita Federal para Abertura de Filial
B25: Inscrição do CNPJ
B26: Inscrição Municipal
B27: Alvará de Funcionamento

Sheet CREA
B2: Segue os valores envolvidos referentes as Taxas do CREA praticados em 2024.
B4: Taxa ART Cargo e Função (Profissional) | C4: 99.64
B5: Taxa registro de empresa - Exercício 2024 | C5: 298.44
B6: ANUIDADE: 2024(5/12 da anuidade integral) ** | C6: 255.25
B7: Taxa ART Projeto | C7: 99.64
B8: CREA Engenheiro | C8: 860.27
B10: ** Taxa da Anuidade pode alterar devido ser proporcional

Sheet Custos De Compra CNPJ - Societ.
C2: Custo Unitário | D2: Qtde Empresas | E2: Custo Total
B3: Honorário Liquido de compra empresa: | C3: 8000
B4: Honorários + Impostos a calcular - ISS (5%), PIS/COFINS (9,25%) | C4: 9248.55 | D4: 1 | E4: =C4*D4 -> 9248.55
B5: Não incluso no valor acima o IRPJ, CSSL | C5: << Valor ajustado após receber o valor do fornecedor em 27/03/24
B7: Despesa Inclusa:
B8: Inclusos ao valor dos honorários de regularização (*) da Companhia na Cidade do Rio de Janeiro, perante a Junta Comercial, Secretaria da Receita Federal, Prefeitura, inscrição junto ao cadastro da Secretaria de Estado de Fazenda (se necessário).
B9: (*) HONORÁRIOS DE REGULARIZAÇÃO: ALTERAÇÕES CONSTANTES NA 1ª AGE, DOCUMENTOS POSTERIORES SERÃO COBRADOS.
B11: Despesas não inclusas:
B12: Não inclusos as despesas e os impostos incidentes na nota fiscal de serviços.
B13: Outras Despesas não inclusas: taxa da Junta Comercial, cópias, autenticações, e outras despesas necessárias à regularização, essas despesas serão adiantadas pelo cliente e serão devidamente comprovadas com o envio dos comprovantes de pagamento, e ainda, os impostos incidentes sobre a Nota Fiscal, podendo a NF ser emitida pelas empresas do nosso grupo, são elas: EDCA Serviços Societários Ltda. – CNPJ/ME nº 30.321.763/0001-03 e Vec Editora e Serviços Ltda. – CNPJ/ME nº 30.279.129/0001-41.
B14: Não está incluso ao valor da aquisição, o registro da empresa junto à qualquer Conselho (CRC, CRA, CRM, CREA, Licenças, etc.), se necessário, os honorários ficarão à combinar.
B15: Caso o pagamento seja efetuado através de câmbio, as despesas com o fechamento do câmbio não estão inclusas no valor de aquisição da sociedade.
B18: REGULARIZAÇÃO DA MESMA NOS ÓRGÃOS COMPETENTES.
B19: Cenário 1 (Somente o registro na JUCERJA) | C19: Custo Unitário | D19: Qtde Empresas | E19: Custo Total
B20: Reembolso da taxa de registro na JUCERJA – R$ 754,00 | C20: 754 | D20: 1 | E20: =C20*D20 -> 754
B21: Honorários – Isento | C21: 0
B22: Taxa de registro na JUCERJA | C22: =SUM(C20:C21) -> 754 | D22: 1 | E22: =C22*D22 -> 754
C24: Custo Unitário | D24: Qtde Empresas | E24: Custo Total
B25: Públicação da ata de AGE (alteração estatutária) e Estatuto Social (ato registrado pelo Eduardo Duarte) | C25: 28644 | D25: 1 | E25: =C25*D25 -> 28644
B27: Total para Aquisição dos 1 CNPJs | E27: =E25+E22+E4 -> 38646.55
B30: Custos Societários para Abertura de Filiais por Client Co | C30: UPI | D30: Custo Unitário | E30: Qtde filiais ex-matriz/ Despachantes | F30: Custo Total
B31: Registro das atas de ReDir da UPI (abertura de x filiais e 7 CD/CA) | C31: 1 | D31: 754 | E31: ='Custos para Abertura de Filiais'!C7-'Custos para Abertura de Filiais'!D7 -> 26 | F31: =D31*E31 -> 19604
B32: Publicação de ReDir UPI (abertura de x filiais - R$ 630,00 por ata publicada) | C32: 1 | D32: 630 | E32: =E31 -> 26 | F32: =D32*E32 -> 16380
B33: Procurações públicas da ClientCo (13 despachantes, sendo R$ 550 por procuração) | C33: 1 | D33: 550 | E33: 13 | F33: =D33*E33 -> 7150
B34: Total | F34: =SUM(F31:F33) -> 43134
B36: Total da Abertura de Filiais | F36: =F34 -> 43134

Sheet Custos para Abertura de Filiais
B2: Custo Médio - filial Virtual | C2: 300 | D2: =C2*25 -> 7500
B3: Custo Médio de Mars para abertura de Filial na capital (*) | C3: 4000 | D3: =C3*2 -> 8000
B4: Custo dos Certificados Digitais por empresa | C4: 3000
J5: Cenário Filial Virtual
C6: Qtde Filial | D6: Matriz Empresa | E6: Filiais p/ ClientCo - Clientes | F6: Filial Virtual | G6: Filiais de RH | H6: Filiais CD/CA de Logistica | I6: Filiais de SVA de TV | J6: Custo para Regularização das Filiais | K6: Custo dos Certificados Digitais | L6: Custo Total
B7: TV | C7: =SUM(D7:I7) -> 27 | D7: =SUM(D8:D34) -> 1 | E7: =SUM(E8:E34) -> 1 | F7: =SUM(F8:F34) -> 25 | G7: =SUM(G8:G34) -> 0 | H7: =SUM(H8:H34) -> 0 | I7: =SUM(I8:I34) -> 0 | J7: =((D7+E7)*$C$3)+(F7*$C$2) -> 15500 | K7: =$C$4 -> 3000 | L7: =SUM(J7:K7) -> 18500
B8: AC | C8: =SUM(D8:I8) -> 1 | D8: =SUM(G8:J8) -> 0 | E8: 0 | F8: 1 | G8: 0 | H8: 0 | I8: 0
B9: AL | C9: =SUM(D9:I9) -> 1 | D9: =SUM(G9:J9) -> 0 | E9: 0 | F9: 1 | G9: 0 | H9: 0 | I9: 0
B10: AM | C10: =SUM(D10:I10) -> 1 | D10: =SUM(G10:J10) -> 0 | E10: 0 | F10: 1 | G10: 0 | H10: 0 | I10: 0
B11: AP | C11: =SUM(D11:I11) -> 1 | D11: =SUM(G11:J11) -> 0 | E11: 0 | F11: 1 | G11: 0 | H11: 0 | I11: 0
B12: BA | C12: =SUM(D12:I12) -> 1 | D12: =SUM(G12:J12) -> 0 | E12: 0 | F12: 1 | G12: 0 | H12: 0 | I12: 0
B13: CE | C13: =SUM(D13:I13) -> 1 | D13: =SUM(G13:J13) -> 0 | E13: 0 | F13: 1 | G13: 0 | H13: 0 | I13: 0
B14: DF | C14: =SUM(D14:I14) -> 1 | D14: =SUM(G14:J14) -> 0 | E14: 0 | F14: 1 | G14: 0 | H14: 0 | I14: 0
B15: ES | C15: =SUM(D15:I15) -> 1 | D15: =SUM(G15:J15) -> 0 | E15: 0 | F15: 1 | G15: 0 | H15: 0 | I15: 0
B16: GO | C16: =SUM(D16:I16) -> 1 | D16: =SUM(G16:J16) -> 0 | E16: 0 | F16: 1 | G16: 0 | H16: 0 | I16: 0
B17: MA | C17: =SUM(D17:I17) -> 1 | D17: =SUM(G17:J17) -> 0 | E17: 0 | F17: 1 | G17: 0 | H17: 0 | I17: 0
B18: MG | C18: =SUM(D18:I18) -> 1 | D18: =SUM(G18:J18) -> 0 | E18: 0 | F18: 1 | G18: 0 | H18: 0 | I18: 0
B19: MS | C19: =SUM(D19:I19) -> 1 | D19: =SUM(G19:J19) -> 0 | E19: 0 | F19: 1 | G19: 0 | H19: 0 | I19: 0
... B25: PR | C25: =SUM(D25:I25) -> 1 | D25: =SUM(G25:J25) -> 0 | E25: 0 | F25: 1 | G25: 0 | H25: 0 | I25: 0
B26: RJ | C26: =SUM(D26:I26) -> 1 | D26: 1 | E26: 0 | F26: 0 | G26: 0 | H26: 0 | I26: 0
B27: RN | C27: =SUM(D27:I27) -> 1 | D27: =SUM(G27:J27) -> 0 | E27: 1 | F27: 0 | G27: 0 | H27: 0 | I27: 0
B28: RO | C28: =SUM(D28:I28) -> 1 | D28: =SUM(G28:J28) -> 0 | E28: 0 | F28: 1 | G28: 0 | H28: 0 | I28: 0
B29: RR | C29: =SUM(D29:I29) -> 1 | D29: =SUM(G29:J29) -> 0 | E29: 0 | F29: 1 | G29: 0 | H29: 0 | I29: 0
B30: RS | C30: =SUM(D30:I30) -> 1 | D30: =SUM(G30:J30) -> 0 | E30: 0 | F30: 1 | G30: 0 | H30: 0 | I30: 0
B31: SC | C31: =SUM(D31:I31) -> 1 | D31: =SUM(G31:J31) -> 0 | E31: 0 | F31: 1 | G31: 0 | H31: 0 | I31: 0
B32: SE | C32: =SUM(D32:I32) -> 1 | D32: =SUM(G32:J32) -> 0 | E32: 0 | F32: 1 | G32: 0 | H32: 0 | I32: 0
B33: SP | C33: =SUM(D33:I33) -> 1 | D33: =SUM(G33:J33) -> 0 | E33: 0 | F33: 1 | G33: 0 | H33: 0 | I33: 0
B34: TO | C34: =SUM(D34:I34) -> 1 | D34: =SUM(G34:J34) -> 0 | E34: 0 | F34: 1 | G34: 0 | H34: 0 | I34: 0
B36: (*) Considerações:
B37: 1 - Há Capitais em que o custo chegou a ~R$ 22 mil, mas adotaram a média dos valores para capital realizados em Mars. Localidades fora da Capital podem ter custos maiores;
B38: 2 - Não inclusos custos associados aos despachantes, entre eles de locomoção, serviços, etc. Considerado como premissa que não irão nos cobrar, mas há chance de existir cobrança nos locais mais distantes.
B39: 3 - Não estão contempladas eventuais diligências (Ex.: AVCB, registro de contrato) para cumprimento de exigências, nem os custos societários (Ex: registro da Ata Societária, procuração) que devem ser avaliados com a área competente.
B40: 4 - Não temos essa verba orçada para 2024.
B41: 5 - Localidades Previstas nas abas Municipios Logistica e Capitais Societário
B43: Relação de Itens relacionados ao custo médio que pode variar de acordo com a localidade:
A44: 6 | B44: Confecção de DBE junto a Receita Federal para Abertura de Filial
A45: 14 | B45: Inscrição do CNPJ
A46: 16 | B46: Inscrição Municipal
A47: 19 | B47: Alvará de Funcionamento

Sheet Aluguel_Oi e 3º_Previsão
B1: # | C1: UF | D1: Tipo estabelecimento | E1: Endereço | F1: M² | G1: Valor Aluguel
B2: 1 | C2: RJ | D2: MATRIZ | E2: Rua Correa Vasques, 69 - 3 andar | F2: 33.74 | G2: 1806.91
B3: 2 | C3: BA | D3: End Oi | E3: Avenida Antônio Carlos Magalhães | F3: 22 | G3: 903.73
B4: 3 | C4: CE | D4: End Oi | E4: RUA SENA MADUREIRA 1020 - térreo | F4: 10 | G4: 550.1
B5: 4 | C5: MA | D5: End Oi | E5: AV. DANIEL DE LA TOUCHE, 31 | F5: 36 | G5: 2169.66
B6: 5 | C6: PA | D6: End Oi | E6: Travessa Dr Moraes, 121 | F6: 18.3 | G6: 1405.11
B7: 6 | C7: RO | D7: End Oi | E7: Rua Dom Pedro II, no. 1213 | F7: 20.8 | G7: 369.49
B8: 7 | C8: TO | D8: End Oi | E8: ACSU SO 20 AVENIDA NS A, SN | F8: 16.74 | G8: 1037.88
B9: 8 | C9: AC | D9: End Oi | E9: Av. Brasil, 381 | F9: 10 | G9: 391.15
B10: 9 | C10: SC | D10: End Oi | E10: RUA - LAURO LINHARES, 1729 | F10: 20 | G10: 770.82
B11: 10 | C11: MG | D11: End Oi | E11: Pça Milton Campos 16 | F11: 30 | G11: 1002.4
B12: 11 | C12: PR | D12: End Oi | E12: Rua Visconde de Nacar, nº 1421 | F12: 18 | G12: 695.58
B13: 12 | C13: RS | D13: End Oi | E13: AV PROTASIO ALVES, 4809 | F13: 10 | G13: 355.71
... B17: 16 | C17: DF | D17: End Oi | E17: Setor SCN Quadra 03 Bloco A; | F17: 20 | G17: 658.46
B18: 17 | C18: AL | D18: COMPANY HERO | E18: Av. Fernandes Lima 8 | F18: - | G18: 450
B19: 18 | C19: AP | D19: COMPANY HERO | E19: AV CARAMURU, 1293, BURITIZAL | F19: - | G19: 300
B20: 19 | C20: RN | D20: COMPANY HERO | E20: Rua Doutor Poty Nóbrega, 1946 | F20: - | G20: 210
B21: 20 | C21: RR | D21: COMPANY HERO | E21: Avenida General Ataíde Teive, n° 832/01 | F21: - | G21: 374.25
B22: 21 | C22: AM | D22: WEWORK | E22: Avenida Rodrigo Otávio | F22: - | G22: 3960
B23: 22 | C23: GO | D23: WEWORK | E23: Rua do Parque, nº 361 | F23: - | G23: 3300
B24: 23 | C24: MS | D24: WEWORK | E24: Rua Fagundes Varela, n.477 | F24: - | G24: 2880
B25: 24 | C25: MT | D25: WEWORK | E25: Rua 24 de Outubro, nº 520 | F25: - | G25: 2990
B26: 25 | C26: PE | D26: WEWORK | E26: Rua Ernesto de Paula Santos 960 | F26: - | G26: 1950
B27: 26 | C27: SE | D27: WEWORK | E27: Rua Padre Nestor Sampaio, nº 140 | F27: - | G27: 1900
B28: 27 | C28: SP | D28: WEWORK | E28: Avenida das Nações Unidas, 12901 | F28: - | G28: 2550
G29: =SUM(G2:G28) -> 35019.66 | H29: =G29*3 -> 105058.98 | I29: >> 3 Meses
G31: =SUM(G18:G28) -> 20864.25 | H31: Comp Hero e WW
G33: =SUM(G2:G17) -> 14155.41 | H33: End Oi
