Workbook
Name emailLink: MTZ_Steakholders!$J$2

Sheet MTZ_Steakholders
A1: NOME N1 | B1: E-mail | C1: NOME N2 | D1: E-mail | E1: NOME N3 | F1: E-mail | G1: GESTOR IMEDIATO | H1: E-mail | I1: PONTO FOCAL | J1: E-mail | K1: Área
A2: Duilio De Novaes Alves | B2: duilio.alves@oi.net.br | G2: Kamila De Vasconcelos Vieira | H2: kamila.vieira@oi.net.br | I2: Alana de Souza Silva | J2: alana.silva@oi.net.br | K2: Riscos/Controles
A3: Adriana da Cunha Costa | B3: adriana.costa@oi.net.br | C3: Viviane Prado Perdigao | D3: viviane.perdigao@oi.net.br | G3: Jorge Luiz Da Silva Correia | H3: jorgelsc@oi.net.br | K3: Regulatório
A4: Adriana da Cunha Costa | B4: adriana.costa@oi.net.br | C4: Viviane Prado Perdigao | D4: viviane.perdigao@oi.net.br | G4: Carlos Vasconcelos Galvão | H4: carlosgalvao@oi.net.br | I4: Mayara Florencio Alves Rios | J4: mayara.rios@oi.net.br | K4: Regulatório
A5: Adriana da Cunha Costa | B5: adriana.costa@oi.net.br | C5: Viviane Prado Perdigao | D5: viviane.perdigao@oi.net.br | G5: Carlos Vasconcelos Galvão | H5: carlosgalvao@oi.net.br | I5: Adilson de Souza e Silva | J5: adilson.souza@oi.net.br | K5: Regulatório
A6: Adriana da Cunha Costa | B6: adriana.costa@oi.net.br | C6: Viviane Prado Perdigao | D6: viviane.perdigao@oi.net.br | G6: Carlos Vasconcelos Galvão | H6: carlosgalvao@oi.net.br | I6: Liliane Marins Diniz | J6: liliane.diniz@oi.net.br | K6: Regulatório
A7: Adriana da Cunha Costa | B7: adriana.costa@oi.net.br | C7: Viviane Prado Perdigao | D7: viviane.perdigao@oi.net.br | G7: Carlos Vasconcelos Galvão | H7: carlosgalvao@oi.net.br | I7: Paulo Erny Souza De Freitas | J7: pfreitas@oi.net.br | K7: Regulatório
A8: Adriana da Cunha Costa | B8: adriana.costa@oi.net.br | C8: Viviane Prado Perdigao | D8: viviane.perdigao@oi.net.br | G8: Carlos Vasconcelos Galvão | H8: carlosgalvao@oi.net.br | I8: Sandro Esteves Pires Martins | J8: sandro.martins@oi.net.br | K8: Regulatório
A9: Adriana da Cunha Costa | B9: adriana.costa@oi.net.br | C9: Viviane Prado Perdigao | D9: viviane.perdigao@oi.net.br | G9: Mariana Oliveira Massuh Doher | H9: mariana.doher@oi.net.br | I9: Monica Cristina Felizardo Vasconcellos Dos Anjos | J9: monica.anjos@oi.net.br | K9: Regulatório
A10: Adriana da Cunha Costa | B10: adriana.costa@oi.net.br | C10: Viviane Prado Perdigao | D10: viviane.perdigao@oi.net.br | G10: Maria Margarete da Rocha | H10: maria.rocha@oi.net.br | K10: Regulatório
A11: Adriana da Cunha Costa | B11: adriana.costa@oi.net.br | C11: Eduardo Levy Cardoso Moreira | D11: eduardo.levy@oi.net.br | G11: Ildeu Randolfo Borges Junior | H11: ildeu.borges@oi.net.br | K11: Regulatório
A12: Rogerio Takayanagi | B12: rogerio.t@oi.net.br | C12: Luiz Henrique Soares Rosa | D12: luiz.rosa@oi.net.br | G12: Alessandro de Magalhães Barbosa | H12: alessandro.magalhaes@oi.net.br | I12: Charlene Santino da Silva | J12: charlene.silva@oi.net.br | K12: M&A
A13: Rogerio Takayanagi | B13: rogerio.t@oi.net.br | C13: Luiz Henrique Soares Rosa | D13: luiz.rosa@oi.net.br | G13: Alessandro de Magalhães Barbosa | H13: alessandro.magalhaes@oi.net.br | I13: Francisco Anderson Pereira De Paiva | J13: francisco.paiva@oi.net.br | K13: M&A
A14: Rogerio Takayanagi | B14: rogerio.t@oi.net.br | C14: Luiz Henrique Soares Rosa | D14: luiz.rosa@oi.net.br | G14: Alessandro de Magalhães Barbosa | H14: alessandro.magalhaes@oi.net.br | I14: Nathalia Piltz Correa | J14: nathalia.correa@oi.net.br | K14: M&A
A15: Rogerio Takayanagi | B15: rogerio.t@oi.net.br | C15: Luiz Henrique Soares Rosa | D15: luiz.rosa@oi.net.br | G15: Eduardo Reis Beraldo | H15: eduardo.beraldo@oi.net.br | I15: Viviane De Medeiros Calaca Gomes | J15: viviane.calaca@oi.net.br | K15: M&A
A16: Rogerio Takayanagi | B16: rogerio.t@oi.net.br | C16: Luiz Henrique Soares Rosa | D16: luiz.rosa@oi.net.br | G16: Eduardo Reis Beraldo | H16: eduardo.beraldo@oi.net.br | I16: Thais Hiromi Nakazone | J16: thais.nakazone@oi.net.br | K16: M&A
A17: Rogerio Takayanagi | B17: rogerio.t@oi.net.br | C17: Luiz Henrique Soares Rosa | D17: luiz.rosa@oi.net.br | G17: Eduardo Reis Beraldo | H17: eduardo.beraldo@oi.net.br | I17: Thiago Marcos Da Silva Barbosa | J17: thiagobarbosa@oi.net.br | K17: M&A
A18: Rogerio Takayanagi | B18: rogerio.t@oi.net.br | C18: Elly Resende Silva | D18: elly.resende@oi.net.br | G18: Karina Duprat Fortes | H18: karina.fortes@oi.net.br | K18: Transição
A19: Rogerio Takayanagi | B19: rogerio.t@oi.net.br | C19: NI | G19: Vanda Coutinho Neves De Almeida | H19: vandacna@oi.net.br | K19: Suporte Técnico
A20: Rogerio Takayanagi | B20: rogerio.t@oi.net.br | C20: NI | G20: Igor Friedrich Pinheiro | H20: igor.pinheiro@oi.net.br | K20: Suporte Técnico
A21: Cristiane Barretto Sales | B21: cristiane.barretto@oi.net.br | C21: Andre Tavares Paradizi | D21: andre.paradizi@oi.net.br | G21: Patricia Decursi Gouveia de Souza | H21: patricia.gouveia@oi.net.br | I21: Anderson Luis da Silva de Souza | J21: andersonlss@oi.net.br | K21: Controladoria
A22: Cristiane Barretto Sales | B22: cristiane.barretto@oi.net.br | C22: Andre Tavares Paradizi | D22: andre.paradizi@oi.net.br | E22: Francisco Paulo Macambira Haick | F22: francisco.haick@oi.net.br | G22: Patricia Ann Necyk | H22: pan@oi.net.br | I22: Adriana Fragoso | J22: adriana.fragoso@oi.net.br | K22: Contabilidade
A23: Cristiane Barretto Sales | B23: cristiane.barretto@oi.net.br | C23: Andre Tavares Paradizi | D23: andre.paradizi@oi.net.br | E23: Francisco Paulo Macambira Haick | F23: francisco.haick@oi.net.br | G23: Patricia Ann Necyk | H23: pan@oi.net.br | I23: Priscila Duarte De Oliveira | J23: priscila.oliveira@oi.net.br | K23: Contabilidade
A24: Cristiane Barretto Sales | B24: cristiane.barretto@oi.net.br | C24: Andre Tavares Paradizi | D24: andre.paradizi@oi.net.br | E24: Francisco Paulo Macambira Haick | F24: francisco.haick@oi.net.br | G24: Patricia Ann Necyk | H24: pan@oi.net.br | I24: Patricia Almeida | J24: patricia.maria@oi.net.br | K24: Contabilidade
A25: Cristiane Barretto Sales | B25: cristiane.barretto@oi.net.br | C25: Andre Tavares Paradizi | D25: andre.paradizi@oi.net.br | E25: Francisco Paulo Macambira Haick | F25: francisco.haick@oi.net.br | G25: Patricia Ann Necyk | H25: pan@oi.net.br | I25: Celiane Sousa Vieira | J25: celiane.vieira@oi.net.br | K25: Contabilidade
A26: Cristiane Barretto Sales | B26: cristiane.barretto@oi.net.br | C26: Andre Tavares Paradizi | D26: andre.paradizi@oi.net.br | E26: Francisco Paulo Macambira Haick | F26: francisco.haick@oi.net.br | G26: Marcelo Gomes | H26: marcelo.gomes@oi.net.br | I26: Alessandra Leandro de Oliveira | J26: alessandra.leandro@oi.net.br | K26: Contabilidade
A27: Cristiane Barretto Sales | B27: cristiane.barretto@oi.net.br | C27: Andre Tavares Paradizi | D27: andre.paradizi@oi.net.br | E27: Francisco Paulo Macambira Haick | F27: francisco.haick@oi.net.br | G27: Marcelo Gomes | H27: marcelo.gomes@oi.net.br | I27: Jonas de Azevedo Almeida | J27: jonas.almeida@oi.net.br | K27: Contabilidade
A28: Cristiane Barretto Sales | B28: cristiane.barretto@oi.net.br | C28: Andre Tavares Paradizi | D28: andre.paradizi@oi.net.br | E28: Francisco Paulo Macambira Haick | F28: francisco.haick@oi.net.br | G28: Marcelo Gomes | H28: marcelo.gomes@oi.net.br | I28: Mateus Pacheco De Oliveira Santos | J28: mateussantos@oi.net.br | K28: Contabilidade
A29: Cristiane Barretto Sales | B29: cristiane.barretto@oi.net.br | C29: Andre Tavares Paradizi | D29: andre.paradizi@oi.net.br | E29: Francisco Paulo Macambira Haick | F29: francisco.haick@oi.net.br | G29: Marcelo Gomes | H29: marcelo.gomes@oi.net.br | I29: Lilian Carmen de Freitas | J29: lilian.freitas@oi.net.br | K29: Contabilidade
A30: Cristiane Barretto Sales | B30: cristiane.barretto@oi.net.br | C30: Andre Tavares Paradizi | D30: andre.paradizi@oi.net.br | E30: Priscila Bittencourt Martins Mannino | F30: priscila.mannino@oi.net.br | K30: Planejamento Digital
A31: Cristiane Barretto Sales | B31: cristiane.barretto@oi.net.br | C31: Pedro De Andrade Franca | D31: pedro.franca@oi.net.br | E31: Philippe Reis Brasil | F31: pedro.franca@oi.net.br | I31: Elisabete de Sousa Ribeiro | J31: elisabete.ribeiro@oi.net.br | K31: Tesouraria
A32: Cristiane Barretto Sales | B32: cristiane.barretto@oi.net.br | C32: Pedro De Andrade Franca | D32: pedro.franca@oi.net.br | E32: Carolina Gava | F32: carolina.gava@oi.net.br | I32: Daniele Morais Silva Gouvea | J32: daniele.gouvea@oi.net.br | K32: Tesouraria
A33: Cristiane Barretto Sales | B33: cristiane.barretto@oi.net.br | C33: Pedro De Andrade Franca | D33: pedro.franca@oi.net.br | E33: Liege Casqueiro | F33: liege.casqueiro@oi.net.br | I33: Camila Costa da Silva | J33: camilacosta@oi.net.br | K33: Seguros
A34: Cristiane Barretto Sales | B34: cristiane.barretto@oi.net.br | C34: Andre Tavares Paradizi | D34: andre.paradizi@oi.net.br | E34: Liege Casqueiro | F34: liege.casqueiro@oi.net.br | I34: Leonardo Bauer Marinho | J34: leonardo.marinho@oi.net.br | K34: Seguros
A35: Cristiane Barretto Sales | B35: cristiane.barretto@oi.net.br | C35: Pedro De Andrade Franca | D35: pedro.franca@oi.net.br | E35: Ana Kelly Da Silva Carneiro | F35: ana.carneiro@oi.net.br | G35: Manuela Barros de Sá Grande | H35: manuela.grande@oi.net.br | I35: Fernanda Beserra De Almeida | J35: fernanda.almeida@oi.net.br | K35: CAP
A36: Cristiane Barretto Sales | B36: cristiane.barretto@oi.net.br | C36: Pedro De Andrade Franca | D36: pedro.franca@oi.net.br | E36: Eduardo Streit | F36: eduardo.streit@oi.net.br | K36: Caixa
A37: Cristiane Barretto Sales | B37: cristiane.barretto@oi.net.br | C37: Flavia Sobreira Casali Lima Bastos | D37: flaviacasali@oi.net.br | G37: Paulo Roberto Salgueiro Vidal | H37: paulo.vidal@oi.net.br | I37: Cristiana Teixeira de Luna Freire | J37: cristiana.freire@oi.net.br | K37: Tributos/Fiscal
B38: cristiane.barretto@oi.net.br | C38: Flavia Sobreira Casali Lima Bastos | D38: flaviacasali@oi.net.br | G38: Paulo Roberto Salgueiro Vidal | H38: paulo.vidal@oi.net.br | I38: Marcos Carneiro Pereira | J38: marcospereira@oi.net.br | K38: Tributos/Fiscal
A39: Cristiane Barretto Sales | B39: cristiane.barretto@oi.net.br | C39: Flavia Sobreira Casali Lima Bastos | D39: flaviacasali@oi.net.br | G39: Erika Braga | H39: erika.braga@oi.net.br | I39: Elaine Vermil Lima Santiago | J39: elaine.santiago@oi.net.br | K39: Tributos/Fiscal
A40: Cristiane Barretto Sales | B40: cristiane.barretto@oi.net.br | C40: Flavia Sobreira Casali Lima Bastos | D40: flaviacasali@oi.net.br | G40: Erika Braga | H40: erika.braga@oi.net.br | I40: Christie Ramos Opytaciano Dos Santos | J40: christie.santos@oi.net.br | K40: Tributos/Fiscal
A41: Cristiane Barretto Sales | B41: cristiane.barretto@oi.net.br | C41: Flavia Sobreira Casali Lima Bastos | D41: flaviacasali@oi.net.br | G41: Erika Braga | H41: erika.braga@oi.net.br | I41: Diogo Gomes Santos de Santana | J41: diogo.santana@oi.net.br | K41: Tributos/Fiscal
A42: Cristiane Barretto Sales | B42: cristiane.barretto@oi.net.br | C42: Flavia Sobreira Casali Lima Bastos | D42: flaviacasali@oi.net.br | G42: Erika Braga | H42: erika.braga@oi.net.br | I42: Rafael da Silva Farias | J42: rafael.farias@oi.net.br | K42: Tributos/Fiscal
A43: Cristiane Barretto Sales | B43: cristiane.barretto@oi.net.br | C43: Flavia Sobreira Casali Lima Bastos | D43: flaviacasali@oi.net.br | G43: Hozana Guimarães de Sá Braga | H43: hozana.braga@oi.net.br | I43: Francisco Herio Rodrigues Freire | J43: francisco.freire@oi.net.br | K43: Tributos/Fiscal
A44: Cristiane Barretto Sales | B44: cristiane.barretto@oi.net.br | C44: Flavia Sobreira Casali Lima Bastos | D44: flaviacasali@oi.net.br | G44: Hozana Guimarães de Sá Braga | H44: hozana.braga@oi.net.br | I44: Aroldo Candido Junior | J44: aroldo.junior@oi.net.br | K44: Tributos/Fiscal
A45: Cristiane Barretto Sales | B45: cristiane.barretto@oi.net.br | C45: Bruno Macedo Soares | D45: bmacedo@oi.net.br | I45: Paulo Jose Amantino Rodrigues | J45: paulo.amantino@oi.net.br | K45: PDD
A46: Cristiane Barretto Sales | B46: cristiane.barretto@oi.net.br | C46: Bruno Macedo Soares | D46: bmacedo@oi.net.br | E46: Daniel Cattete Sanguedo | F46: daniel.sanguedo@oi.net.br | I46: Camilla Luciano Teixeira | J46: camilla.teixeira@oi.net.br | K46: Contas a receber
A47: Cristiane Barretto Sales | B47: cristiane.barretto@oi.net.br | C47: Bruno Macedo Soares | D47: bmacedo@oi.net.br | E47: Daniel Cattete Sanguedo | F47: daniel.sanguedo@oi.net.br | I47: Bruno de Sousa Oliveira | J47: bruno.sousa@oi.net.br | K47: Cobrança
A48: Cristiane Barretto Sales | B48: cristiane.barretto@oi.net.br | C48: Bruno Macedo Soares | D48: bmacedo@oi.net.br | E48: Altevo Carlos De Sa Volotao | F48: altevo.volotao@oi.net.br | G48: Iara Kelli da Cruz Braga | H48: iara.braga@oi.net.br | I48: Jocely Rocha dos Santos | J48: jocely.santos@oi.net.br | K48: Faturamento
A49: Cristiane Barretto Sales | B49: cristiane.barretto@oi.net.br | C49: Bruno Macedo Soares | D49: bmacedo@oi.net.br | E49: Altevo Carlos De Sa Volotao | F49: altevo.volotao@oi.net.br | G49: Monica Sant Anna Paetzoldt | H49: monica.paetzoldt@oi.net.br | K49: Faturamento
A50: Cristiane Barretto Sales | B50: cristiane.barretto@oi.net.br | C50: Bruno Macedo Soares | D50: bmacedo@oi.net.br | E50: Alessandro Luiz Varme Dias | F50: alessandro.varme@oi.net.br | I50: Andre Pereira Lopes | J50: andrelopes@oi.net.br | K50: Fraude
A51: Daniel Hermeto | B51: daniel.hermeto@oi.net.br | C51: Evandro Schimming Smith Angelo | D51: evandro.angelo@oi.net.br | G51: Bernardo Maturo Ieno | H51: bernardo.ieno@oi.net.br | I51: Miriam Castro Granado Valladas | J51: miriam.valladas@oi.net.br | K51: Patrimonio
A52: Daniel Hermeto | B52: daniel.hermeto@oi.net.br | C52: Evandro Schimming Smith Angelo | D52: evandro.angelo@oi.net.br | G52: Adriano Andrey Israel | H52: adriano.israel@oi.net.br | K52: Patrimonio
A53: Daniel Hermeto | B53: daniel.hermeto@oi.net.br | C53: Marcia Helena da Fonseca | D53: marcia.fonseca@oi.net.br | K53: Imóveis
A54: Daniel Hermeto | B54: daniel.hermeto@oi.net.br | C54: Luiz Fellipe Mendes Vieira | D54: luiz.vieira@oi.net.br | G54: Rafael Maia De Vasconcelos Muniz | H54: rafael.muniz@oi.net.br | K54: Suprimentos
A55: Daniel Hermeto | B55: daniel.hermeto@oi.net.br | C55: Ana Thereza Silva Miguelote | D55: ana.miguelote@oi.net.br | G55: Carolina Arlotta | H55: carolina.arlotta@oi.net.br | K55: Energia
A56: Thalles Paixao | B56: thalles.paixao@oi.net.br | C56: Fernando Raposo Franco | D56: fernando.franco@oi.net.br | G56: Pedro Rique Nepomuceno | H56: pedro.nepomuceno@oi.net.br | I56: Alessandra Lima Ramos de Mattos Benevides | J56: alessandra.benevides@oi.net.br | K56: Jur Tributario
A57: Thalles Paixao | B57: thalles.paixao@oi.net.br | C57: Fernando Raposo Franco | D57: fernando.franco@oi.net.br | G57: Pedro Rique Nepomuceno | H57: pedro.nepomuceno@oi.net.br | I57: Julia Villares Torres | J57: julia.torres@oi.net.br | K57: Jur Tributario
A58: Thalles Paixao | B58: thalles.paixao@oi.net.br | C58: Fernando Raposo Franco | D58: fernando.franco@oi.net.br | G58: Luiz Felipe Neves Do Couto Vargas | H58: luizf.vargas@oi.net,br | K58: Jur Civel Estrategico e Regulamento
A59: Thalles Paixao | B59: thalles.paixao@oi.net.br | C59: Williams Pereira Junior | D59: williams.pereira@oi.net.br | G59: Douglas Tostes Coelho | H59: douglas.coelho@oi.net.br | K59: Jur Trabalhista
A60: Thalles Paixao | B60: thalles.paixao@oi.net.br | C60: Williams Pereira Junior | D60: williams.pereira@oi.net.br | G60: Gustavo Medina Miranda Da Silva | H60: gustavo.medina@oi.net.br | K60: Jur Trabalhista
A61: Thalles Paixao | B61: thalles.paixao@oi.net.br | C61: Williams Pereira Junior | D61: williams.pereira@oi.net.br | G61: Viviane Lima Marques | H61: viviane.marques@oi.net.br | K61: Jur Trabalhista
A62: Thalles Paixao | B62: thalles.paixao@oi.net.br | C62: Elen Marques Souto La Croix | D62: elen.souto@oi.net.br | G62: Fabricio Cardoso De Faria Martins | H62: fabricio.martins@oi.net.br | I62: Derick Ian Ferreira Machado De Assis | J62: derick.assis@oi.net.br | K62: Jur Consumidor
A63: Thalles Paixao | B63: thalles.paixao@oi.net.br | C63: Elen Marques Souto La Croix | D63: elen.souto@oi.net.br | G63: Adriana Velhote | H63: adriana.velhote@oi.net.br | K63: Jur Consumidor
A64: Thalles Paixao | B64: thalles.paixao@oi.net.br | C64: Daniella Geszikter Ventura | D64: daniella.ventura@oi.net.br | G64: Barbara Erthal Pinheiro | H64: barbara.erthal@oi.net.br | K64: Jur Societário
A65: Thalles Paixao | B65: thalles.paixao@oi.net.br | C65: Daniella Geszikter Ventura | D65: daniella.ventura@oi.net.br | G65: Leandro Diogo Luz | H65: leandro.luz@oi.net.br | I65: Marina Silva | J65: marina.maciel@oi.net.br | K65: Jur Societário
A66: Caio Marcio Gusmon | B66: caio.gusmon@oi.net.br | C66: Bruno Diehl | D66: bruno.diehl@oi.net.br | G66: Viviane Aparecida De Jesus | H66: vivian.jesus@oi.net.br | I66: Marcelo Nogueira | J66: marcelo.nogueira@oi.net.br | K66: Sistemas TI
A67: Caio Marcio Gusmon | B67: caio.gusmon@oi.net.br | C67: Bruno Diehl | D67: bruno.diehl@oi.net.br | G67: Viviane Aparecida De Jesus | H67: vivian.jesus@oi.net.br | I67: Marlon Junqueira Reis | J67: marlon.reis@oi.net.br | K67: Sistemas TI
A68: Caio Marcio Gusmon | B68: caio.gusmon@oi.net.br | C68: Bruno Diehl | D68: bruno.diehl@oi.net.br | G68: Viviane Aparecida De Jesus | H68: vivian.jesus@oi.net.br | I68: Melchiades Neto | J68: melchiades.neto@oi.net.br | K68: Sistemas TI
A69: Caio Marcio Gusmon | B69: caio.gusmon@oi.net.br | C69: Bruno Diehl | D69: bruno.diehl@oi.net.br | G69: Viviane Aparecida De Jesus | H69: vivian.jesus@oi.net.br | I69: Gabriel Vidal da Silva | J69: gabriel.vidal@oi.net.br | K69: Sistemas TI
A70: Caio Marcio Gusmon | B70: caio.gusmon@oi.net.br | C70: Bruno Diehl | D70: bruno.diehl@oi.net.br | G70: Viviane Aparecida De Jesus | H70: vivian.jesus@oi.net.br | I70: Francis Valente De Souza | J70: francis.souza@oi.net.br | K70: Sistemas TI
A71: Caio Marcio Gusmon | B71: caio.gusmon@oi.net.br | C71: Bruno Diehl | D71: bruno.diehl@oi.net.br | G71: Viviane Aparecida De Jesus | H71: vivian.jesus@oi.net.br | I71: Willian Harrison de Oliveira Marcelino | J71: willian.marcelino@oi.net.br | K71: Sistemas TI
A72: Caio Marcio Gusmon | B72: caio.gusmon@oi.net.br | C72: Bruno Diehl | D72: bruno.diehl@oi.net.br | G72: Viviane Aparecida De Jesus | H72: vivian.jesus@oi.net.br | I72: Cristiane Dias E Alpoim Jacobson | J72: cristiane.jacobson@oi.net.br | K72: Sistemas TI
A73: Caio Marcio Gusmon | B73: caio.gusmon@oi.net.br | C73: Bruno Diehl | D73: bruno.diehl@oi.net.br | G73: Viviane Aparecida De Jesus | H73: vivian.jesus@oi.net.br | I73: Alexandre De Souza Soares | J73: alexandre.ssoares@oi.net.br | K73: Sistemas TI
A74: Caio Marcio Gusmon | B74: caio.gusmon@oi.net.br | C74: Bruno Diehl | D74: bruno.diehl@oi.net.br | G74: Viviane Aparecida De Jesus | H74: vivian.jesus@oi.net.br | I74: Guilherme Pinheiro Da Fonseca Pascoa | J74: guilherme.pascoa@oi.net.br | K74: Sistemas TI
A75: Caio Marcio Gusmon | B75: caio.gusmon@oi.net.br | C75: Bruno Diehl | D75: bruno.diehl@oi.net.br | G75: Viviane Aparecida De Jesus | H75: vivian.jesus@oi.net.br | I75: Gustavo Queiroz Da Silva Pinto | J75: gustavo.queiroz@oi.net.br | K75: Sistemas TI
A76: Caio Marcio Gusmon | B76: caio.gusmon@oi.net.br | C76: Bruno Diehl | D76: bruno.diehl@oi.net.br | G76: Viviane Aparecida De Jesus | H76: vivian.jesus@oi.net.br | I76: Paulo Cezar Da Silva | J76: paulos@oi.net.br | K76: Sistemas TI
... A90: Caio Marcio Gusmon | B90: caio.gusmon@oi.net.br | C90: Bruno Diehl | D90: bruno.diehl@oi.net.br | G90: Regina Celia de Souza Montes | H90: regina.montes@oi.net.br | I90: Soraia Andreia Casagrande | J90: soraia.casagrande@oi.net.br | K90: Sistemas TI
A91: Caio Marcio Gusmon | B91: caio.gusmon@oi.net.br | C91: Alexandre Luiz Furtado Domingues | D91: alexandre.domingues@oi.net.br | E91: Ana Carolina Sarno De Mattos | F91: anamattos@oi.net.br | G91: Taian Nunes Buriche | H91: taian@oi.net.br | K91: Infra e Operações TI
A92: Caio Marcio Gusmon | B92: caio.gusmon@oi.net.br | C92: Alexandre Luiz Furtado Domingues | D92: alexandre.domingues@oi.net.br | E92: Ana Carolina Sarno De Mattos | F92: anamattos@oi.net.br | G92: Wagner Gomes Triano | H92: wagner.triano@oi.net.br | K92: Infra e Operações TI
A93: Caio Marcio Gusmon | B93: caio.gusmon@oi.net.br | C93: Alexandre Luiz Furtado Domingues | D93: alexandre.domingues@oi.net.br | E93: Ana Carolina Sarno De Mattos | F93: anamattos@oi.net.br | G93: Cid Antunes Horta Junior | H93: cid.junior@oi.net.br | K93: Infra e Operações TI
A94: Caio Marcio Gusmon | B94: caio.gusmon@oi.net.br | C94: Cesar Augusto Bento Do Nascimento | D94: cesar.nascimento@oi.net.br | I94: Luis Felipe De Moura Ramiz Wright | J94: luis.wright@oi.net.br | K94: Arquitetura TI
A95: Caio Marcio Gusmon | B95: caio.gusmon@oi.net.br | C95: Cesar Augusto Bento Do Nascimento | D95: cesar.nascimento@oi.net.br | I95: Sergio Ricardo Neto Figueiredo | J95: sergio.figueiredo@oi.net.br | K95: Arquitetura TI
A96: Caio Marcio Gusmon | B96: caio.gusmon@oi.net.br | C96: Ulisses Fonseca Alves | D96: ulisses.alves@oi.net.br | G96: Bruno De Almeida Palombo | H96: bruno.palombo@oi.net.br | I96: Herivelton Pereira | J96: herivelton.santo@oi.net.br | K96: Data Analytics
A97: Caio Marcio Gusmon | B97: caio.gusmon@oi.net.br | C97: Ulisses Fonseca Alves | D97: ulisses.alves@oi.net.br | G97: Bruno De Almeida Palombo | H97: bruno.palombo@oi.net.br | I97: Paulo Behling | J97: paulo.behling@oi.net.br | K97: Data Analytics
A98: Caio Marcio Gusmon | B98: caio.gusmon@oi.net.br | C98: Ulisses Fonseca Alves | D98: ulisses.alves@oi.net.br | G98: Alessandra Perrelli | H98: alessandra.perrelli@oi.net.br | K98: Data Analytics
A99: Caio Marcio Gusmon | B99: caio.gusmon@oi.net.br | C99: Ulisses Fonseca Alves | D99: ulisses.alves@oi.net.br | G99: Juscelino Ribeiro Carvalho | H99: juscelino.carvalho@oi.net.br | K99: Data Analytics
A100: Gustavo Roberto Brambila | B100: gbrambila@oi.net.br | C100: Rafael Freitas De Amorim | D100: rafael.amorim@oi.net.br | K100: Operação de Rede e SI
A101: Gustavo Roberto Brambila | B101: gbrambila@oi.net.br | C101: Thiago Vasconcelos | D101: thiago.vasconcelos@oi.net.br | E101: Eduardo Pedreira De Oliveira | F101: eduardo.oliveira@oi.net.br | G101: Leonardo Medeiros Serejo | H101: leonardo.serejo@oi.net.br | K101: Logística
A102: Gustavo Roberto Brambila | B102: gbrambila@oi.net.br | C102: Thiago Vasconcelos | D102: thiago.vasconcelos@oi.net.br | E102: Eduardo Pedreira De Oliveira | F102: eduardo.oliveira@oi.net.br | G102: Clarita Ferreira | H102: clarita.ferreira@oi.net.br | I102: Duhare Da Silveira Fernandes | J102: duhare.fernandes@oi.net.br | K102: Logística
A103: Gustavo Roberto Brambila | B103: gbrambila@oi.net.br | C103: River De Morais E Silva | D103: river@oi.net.br | G103: Nivaldo Santos | H103: nivaldo.santos@oi.net.br | I103: Marcio Daudt da Silva | J103: marcio.daudt@oi.net.br | K103: Segurança da Informação
A104: Gustavo Roberto Brambila | B104: gbrambila@oi.net.br | C104: River De Morais E Silva | D104: river@oi.net.br | G104: Nivaldo Santos | H104: nivaldo.santos@oi.net.br | I104: Ricardo Luiz Pereira Cotovio | J104: ricardo.cotovio@oi.net.br | K104: Segurança da Informação
A105: Gustavo Roberto Brambila | B105: gbrambila@oi.net.br | C105: River De Morais E Silva | D105: river@oi.net.br | G105: Nivaldo Santos | H105: nivaldo.santos@oi.net.br | I105: Rafael Pereira Alcantara | J105: rafael.alcantara@oi.net.br | K105: Segurança da Informação
A106: Marcos Mendes | B106: marcos.mendes@oi.net.br | C106: Ricardo Goulart | D106: rgoulart@oi.net.br | G106: Valeria Da Conceicao Braga | H106: valeria.braga@oi.net.br | I106: Raul Luiz Dond Filho | J106: raul.dond@oi.net.br | K106: RH - Remuneração, Planejamento e Gestão
A107: Marcos Mendes | B107: marcos.mendes@oi.net.br | C107: Ricardo Goulart | D107: rgoulart@oi.net.br | G107: Carlos Eduardo da Rocha Andrade | H107: carlos.andrade@oi.net.br> | K107: RH - Remuneração, Planejamento e Gestão
A108: Marcos Mendes | B108: marcos.mendes@oi.net.br | C108: Ricardo Goulart | D108: rgoulart@oi.net.br | G108: Jussara Petra Rocha | H108: jussara.rocha@oi.net.br | K108: RH - Remuneração, Planejamento e Gestão
A109: Marcos Mendes | B109: marcos.mendes@oi.net.br | C109: Ariane Fonseca Vieira | D109: ariane.vieira@oi.net.br | G109: Cintia Zozimo Marques Rau | H109: cintia.rau@oi.net.br | K109: RH - Relac. Trab., Seg.
A110: Fabricio Bindi | B110: fabricio.bindi@oi.net.br | C110: Francisco Jose Thurler Tecles Junior | D110: francisco.tecles@oi.net.br | G110: Felicia Daquino Nonato Rosetti | H110: felicia@oi.net.br | K110: Varejo
A111: Fabricio Bindi | B111: fabricio.bindi@oi.net.br | C111: Francisco Jose Thurler Tecles Junior | D111: francisco.tecles@oi.net.br | G111: Daniela Greco Guasti | H111: daniela.greco@oi.net.br | K111: Varejo
A112: Fabricio Bindi | B112: fabricio.bindi@oi.net.br | C112: Francisco Jose Thurler Tecles Junior | D112: francisco.tecles@oi.net.br | G112: Renato Da Costa Elias | H112: renato.elias@oi.net.br | K112: Varejo
A113: Fabricio Bindi | B113: fabricio.bindi@oi.net.br | C113: Francisco Jose Thurler Tecles Junior | D113: francisco.tecles@oi.net.br | G113: Hugo Leonardo Spiller Nascimento | H113: hugo.nascimento@oi.net.br | K113: Varejo
...

Sheet Lista Única Pessoas
A1: Nomes | B1: E-mails | C1: Área | D1: Nivel | E1: Incluir na reunião | F1: Enviar Material | I1: 1
A2: Adilson de Souza e Silva | B2: adilson.souza@oi.net.br | C2: =VLOOKUP(A2,MTZ_Steakholders!$I$2:$K$123,3,0) -> Regulatório | D2: Ponto Focal | F2: N | I2: 2
A3: Adriana da Cunha Costa | B3: adriana.costa@oi.net.br | C3: =VLOOKUP(A3,MTZ_Steakholders!$A$2:$K$123,11,0) -> Regulatório | D3: N1 | F3: N | I3: 2
A4: Adriana Fragoso | B4: adriana.fragoso@oi.net.br | C4: =VLOOKUP(A4,MTZ_Steakholders!$I$2:$K$123,3,0) -> Contabilidade | D4: Ponto Focal | F4: N
A5: Adriana Velhote | B5: adriana.velhote@oi.net.br | C5: =VLOOKUP(A5,MTZ_Steakholders!$G$2:$K$123,5,0) -> Jur Consumidor | D5: Gestor Imediato | F5: S
A6: Adriano Andrey Israel | B6: adriano.israel@oi.net.br | C6: =VLOOKUP(A6,MTZ_Steakholders!$G$2:$K$123,5,0) -> Patrimonio | D6: Gestor Imediato | F6: S
A7: Alana de Souza Silva | B7: alana.silva@oi.net.br | C7: =VLOOKUP(A7,MTZ_Steakholders!$I$2:$K$123,3,0) -> Riscos/Controles | D7: Ponto Focal | F7: N
A8: Alessandra Leandro de Oliveira | B8: alessandra.leandro@oi.net.br | C8: =VLOOKUP(A8,MTZ_Steakholders!$I$2:$K$123,3,0) -> Contabilidade | D8: Ponto Focal | F8: N
A9: Alessandra Lima Ramos de Mattos Benevides | B9: alessandra.benevides@oi.net.br | C9: =VLOOKUP(A9,MTZ_Steakholders!$I$2:$K$123,3,0) -> Jur Tributario | D9: Ponto Focal | F9: N
A10: Alessandra Perrelli | B10: alessandra.perrelli@oi.net.br | C10: =VLOOKUP(A10,MTZ_Steakholders!$G$2:$K$123,5,0) -> Data Analytics | D10: Gestor Imediato | F10: S
A11: Alessandro de Magalhães Barbosa | B11: alessandro.magalhaes@oi.net.br | C11: =VLOOKUP(A11,MTZ_Steakholders!$G$2:$K$123,5,0) -> M&A | D11: Gestor Imediato | F11: S
A12: Alessandro Luiz Varme Dias | B12: alessandro.varme@oi.net.br | C12: =VLOOKUP(A12,MTZ_Steakholders!$E$2:$K$123,7,0) -> Fraude | D12: N3 | F12: S
A13: Alexandre De Souza Soares | B13: alexandre.ssoares@oi.net.br | C13: =VLOOKUP(A13,MTZ_Steakholders!$I$2:$K$123,3,0) -> Sistemas TI | D13: Ponto Focal | F13: N
A14: Alexandre Luiz Furtado Domingues | B14: alexandre.domingues@oi.net.br | C14: =VLOOKUP(A14,MTZ_Steakholders!$C$2:$K$123,9,0) -> Infra e Operações TI | D14: N2 | F14: S
A15: Altevo Carlos De Sa Volotao | B15: altevo.volotao@oi.net.br | C15: =VLOOKUP(A15,MTZ_Steakholders!$E$2:$K$123,7,0) -> Faturamento | D15: N3 | F15: S
A16: Ana Carolina Sarno De Mattos | B16: anamattos@oi.net.br | C16: =VLOOKUP(A16,MTZ_Steakholders!$E$2:$K$123,7,0) -> Infra e Operações TI | D16: N3 | F16: S
A17: Ana Cristina Guimaraes Murad | B17: anamurad@oi.net.br | C17: =VLOOKUP(A17,MTZ_Steakholders!$G$2:$K$123,5,0) -> Empresarial | D17: Gestor Imediato | F17: S
A18: Ana Kelly Da Silva Carneiro | B18: ana.carneiro@oi.net.br | C18: =VLOOKUP(A18,MTZ_Steakholders!$E$2:$K$123,7,0) -> CAP | D18: N3 | F18: S
A19: Ana Luiza Cunha E Silva Jorge | B19: ana.luiza@oi.net.br | C19: =VLOOKUP(A19,MTZ_Steakholders!$I$2:$K$123,3,0) -> Sistemas TI | D19: Ponto Focal | F19: N
A20: Ana Thereza Silva Miguelote | B20: ana.miguelote@oi.net.br | C20: =VLOOKUP(A20,MTZ_Steakholders!$C$2:$K$123,9,0) -> Energia | D20: N2 | F20: S
A21: Anderson Luis da Silva de Souza | B21: andersonlss@oi.net.br | C21: =VLOOKUP(A21,MTZ_Steakholders!$I$2:$K$123,3,0) -> Controladoria | D21: Ponto Focal | F21: N
A22: Anderson Luiz Fernandes Esteves | B22: anderson.esteves@oi.net.br | C22: =VLOOKUP(A22,MTZ_Steakholders!$G$2:$K$123,5,0) -> Empresarial | D22: Gestor Imediato | F22: S
A23: Andre Pereira Lopes | B23: andrelopes@oi.net.br | C23: =VLOOKUP(A23,MTZ_Steakholders!$I$2:$K$123,3,0) -> Fraude | D23: Ponto Focal | F23: N
A24: Andre Tavares Paradizi | B24: andre.paradizi@oi.net.br | C24: =VLOOKUP(A24,MTZ_Steakholders!$C$2:$K$123,9,0) -> Controladoria | D24: N2 | F24: S
A25: Antonio Carlos Da Silva Gomes | B25: antonio.silva.gomes@oi.net.br | C25: =VLOOKUP(A25,MTZ_Steakholders!$I$2:$K$123,3,0) -> Sistemas TI | D25: Ponto Focal | F25: N
A26: Ariane Fonseca Vieira | B26: ariane.vieira@oi.net.br | C26: =VLOOKUP(A26,MTZ_Steakholders!$C$2:$K$123,9,0) -> RH - Relac. Trab., Seg. | D26: N2 | F26: S
A27: Aroldo Candido Junior | B27: aroldo.junior@oi.net.br | C27: =VLOOKUP(A27,MTZ_Steakholders!$I$2:$K$123,3,0) -> Tributos/Fiscal | D27: Ponto Focal | F27: N
A28: Barbara Coelho Martinho | B28: barbara.martinho@oi.net.br | C28: =VLOOKUP(A28,MTZ_Steakholders!$G$2:$K$123,5,0) -> Comunicação | D28: Gestor Imediato | F28: S
A29: Barbara Erthal Pinheiro | B29: barbara.erthal@oi.net.br | C29: =VLOOKUP(A29,MTZ_Steakholders!$G$2:$K$123,5,0) -> Jur Societário | D29: Gestor Imediato | F29: S
A30: Bernardo Maturo Ieno | B30: bernardo.ieno@oi.net.br | C30: =VLOOKUP(A30,MTZ_Steakholders!$G$2:$K$123,5,0) -> Patrimonio | D30: Gestor Imediato | F30: S
A31: Bruno De Almeida Palombo | B31: bruno.palombo@oi.net.br | C31: =VLOOKUP(A31,MTZ_Steakholders!$G$2:$K$123,5,0) -> Data Analytics | D31: Gestor Imediato | F31: S
A32: Bruno de Sousa Oliveira | B32: bruno.sousa@oi.net.br | C32: =VLOOKUP(A32,MTZ_Steakholders!$I$2:$K$123,3,0) -> Cobrança | D32: Ponto Focal | F32: N
A33: Bruno Diehl | B33: bruno.diehl@oi.net.br | C33: =VLOOKUP(A33,MTZ_Steakholders!$C$2:$K$123,9,0) -> Sistemas TI | D33: N2 | F33: S
A34: Bruno Macedo Soares | B34: bmacedo@oi.net.br | C34: =VLOOKUP(A34,MTZ_Steakholders!$C$2:$K$123,9,0) -> PDD | D34: N2 | F34: S
A35: Caio Marcio Gusmon | B35: caio.gusmon@oi.net.br | C35: =VLOOKUP(A35,MTZ_Steakholders!$A$2:$K$123,11,0) -> Sistemas TI | D35: N1 | F35: S
A36: Camila Costa da Silva | B36: camilacosta@oi.net.br | C36: =VLOOKUP(A36,MTZ_Steakholders!$I$2:$K$123,3,0) -> Seguros | D36: Ponto Focal | F36: N
A37: Camilla Luciano Teixeira | B37: camilla.teixeira@oi.net.br | C37: =VLOOKUP(A37,MTZ_Steakholders!$I$2:$K$123,3,0) -> Contas a receber | D37: Ponto Focal | F37: N
A38: Carlos Alberto Sant Anna Lapa | B38: carlos.lapa@oi.net.br | C38: =VLOOKUP(A38,MTZ_Steakholders!$G$2:$K$123,5,0) -> Sistemas TI | D38: Gestor Imediato | F38: S
A39: Carlos Eduardo da Rocha Andrade | B39: carlos.andrade@oi.net.br> | C39: =VLOOKUP(A39,MTZ_Steakholders!$G$2:$K$123,5,0) -> RH - Remuneração, Planejamento e Gestão | D39: Gestor Imediato | F39: S
A40: Carlos Vasconcelos Galvão | B40: carlosgalvao@oi.net.br | C40: =VLOOKUP(A40,MTZ_Steakholders!$G$2:$K$123,5,0) -> Regulatório | D40: Gestor Imediato | F40: S
A41: Carolina Arlotta | B41: carolina.arlotta@oi.net.br | C41: =VLOOKUP(A41,MTZ_Steakholders!$G$2:$K$123,5,0) -> Energia | D41: Gestor Imediato | F41: S
A42: Carolina Darigo Kopschitz Facchinetti | B42: carolina.barros@oi.net.br | C42: =VLOOKUP(A42,MTZ_Steakholders!$G$2:$K$123,5,0) -> Sistemas TI | D42: Gestor Imediato | F42: S
A43: Carolina Gava | B43: carolina.gava@oi.net.br | C43: =VLOOKUP(A43,MTZ_Steakholders!$E$2:$K$123,7,0) -> Tesouraria | D43: N3 | F43: S
A44: Celiane Sousa Vieira | B44: celiane.vieira@oi.net.br | C44: =VLOOKUP(A44,MTZ_Steakholders!$I$2:$K$123,3,0) -> Contabilidade | D44: Ponto Focal | F44: N
A45: Cesar Augusto Bento Do Nascimento | B45: cesar.nascimento@oi.net.br | C45: =VLOOKUP(A45,MTZ_Steakholders!$C$2:$K$123,9,0) -> Arquitetura TI | D45: N2 | F45: S
A46: Charlene Santino da Silva | B46: charlene.silva@oi.net.br | C46: =VLOOKUP(A46,MTZ_Steakholders!$I$2:$K$123,3,0) -> M&A | D46: Ponto Focal | F46: N
A47: Christie Ramos Opytaciano Dos Santos | B47: christie.santos@oi.net.br | C47: =VLOOKUP(A47,MTZ_Steakholders!$I$2:$K$123,3,0) -> Tributos/Fiscal | D47: Ponto Focal | F47: N
A48: Cid Antunes Horta Junior | B48: cid.junior@oi.net.br | C48: =VLOOKUP(A48,MTZ_Steakholders!$G$2:$K$123,5,0) -> Infra e Operações TI | D48: Gestor Imediato | F48: S
A49: Cintia Zozimo Marques Rau | B49: cintia.rau@oi.net.br | C49: =VLOOKUP(A49,MTZ_Steakholders!$G$2:$K$123,5,0) -> RH - Relac. Trab., Seg. | D49: Gestor Imediato | F49: S
A50: Clarita Ferreira | B50: clarita.ferreira@oi.net.br | C50: =VLOOKUP(A50,MTZ_Steakholders!$G$2:$K$123,5,0) -> Logística | D50: Gestor Imediato | F50: S
A51: Cristiana Teixeira de Luna Freire | B51: cristiana.freire@oi.net.br | C51: =VLOOKUP(A51,MTZ_Steakholders!$I$2:$K$123,3,0) -> Tributos/Fiscal | D51: Ponto Focal | F51: N
A52: Cristiane Barretto Sales | B52: cristiane.barretto@oi.net.br | C52: =VLOOKUP(A52,MTZ_Steakholders!$A$2:$K$123,11,0) -> Controladoria | D52: N1 | F52: N
A53: Cristiane Dias E Alpoim Jacobson | B53: cristiane.jacobson@oi.net.br | C53: =VLOOKUP(A53,MTZ_Steakholders!$I$2:$K$123,3,0) -> Sistemas TI | D53: Ponto Focal | F53: N
A54: Daniel Cattete Sanguedo | B54: daniel.sanguedo@oi.net.br | C54: =VLOOKUP(A54,MTZ_Steakholders!$E$2:$K$123,7,0) -> Contas a receber | D54: N3 | F54: S
A55: Daniel Hermeto | B55: daniel.hermeto@oi.net.br | C55: =VLOOKUP(A55,MTZ_Steakholders!$A$2:$K$123,11,0) -> Patrimonio | D55: N1 | F55: N
A56: Daniel Nassur De Souza | B56: daniel.nassur@oi.net.br | C56: =VLOOKUP(A56,MTZ_Steakholders!$G$2:$K$123,5,0) -> Sistemas TI | D56: Gestor Imediato | F56: S
A57: Daniela Greco Guasti | B57: daniela.greco@oi.net.br | C57: =VLOOKUP(A57,MTZ_Steakholders!$G$2:$K$123,5,0) -> Varejo | D57: Gestor Imediato | F57: S
A58: Daniele Morais Silva Gouvea | B58: daniele.gouvea@oi.net.br | C58: =VLOOKUP(A58,MTZ_Steakholders!$I$2:$K$123,3,0) -> Tesouraria | D58: Ponto Focal | F58: N
A59: Daniella Geszikter Ventura | B59: daniella.ventura@oi.net.br | C59: =VLOOKUP(A59,MTZ_Steakholders!$C$2:$K$123,9,0) -> Jur Societário | D59: N2 | F59: S
A60: David Sodre Da Silva Ferreira | B60: david.sodre@oi.net.br | C60: =VLOOKUP(A60,MTZ_Steakholders!$I$2:$K$123,3,0) -> Sistemas TI | D60: Ponto Focal | F60: N
A61: Derick Ian Ferreira Machado De Assis | B61: derick.assis@oi.net.br | C61: =VLOOKUP(A61,MTZ_Steakholders!$I$2:$K$123,3,0) -> Jur Consumidor | D61: Ponto Focal | F61: N
A62: Diego de Avelar Ferreira | B62: diego.avelar@oi.net.br | C62: =VLOOKUP(A62,MTZ_Steakholders!$G$2:$K$123,5,0) -> Atendimento | D62: Gestor Imediato | F62: S
A63: Diogo Gomes Santos de Santana | B63: diogo.santana@oi.net.br | C63: =VLOOKUP(A63,MTZ_Steakholders!$I$2:$K$123,3,0) -> Tributos/Fiscal | D63: Ponto Focal | F63: N
A64: Douglas Tostes Coelho | B64: douglas.coelho@oi.net.br | C64: =VLOOKUP(A64,MTZ_Steakholders!$G$2:$K$123,5,0) -> Jur Trabalhista | D64: Gestor Imediato | F64: S
A65: Duhare Da Silveira Fernandes | B65: duhare.fernandes@oi.net.br | C65: =VLOOKUP(A65,MTZ_Steakholders!$I$2:$K$123,3,0) -> Logística | D65: Ponto Focal | F65: N
A66: Duilio De Novaes Alves | B66: duilio.alves@oi.net.br | C66: =VLOOKUP(A66,MTZ_Steakholders!$A$2:$K$123,11,0) -> Riscos/Controles | D66: N1 | F66: S
A67: Eduardo Damasceno | B67: eduardo.damasceno@oi.net.br | C67: =VLOOKUP(A67,MTZ_Steakholders!$I$2:$K$123,3,0) -> Sistemas TI | D67: Ponto Focal | F67: N
A68: Eduardo Levy Cardoso Moreira | B68: eduardo.levy@oi.net.br | C68: =VLOOKUP(A68,MTZ_Steakholders!$C$2:$K$123,9,0) -> Regulatório | D68: N2 | F68: S
A69: Eduardo Pedreira De Oliveira | B69: eduardo.oliveira@oi.net.br | C69: =VLOOKUP(A69,MTZ_Steakholders!$E$2:$K$123,7,0) -> Logística | D69: N3 | F69: S
A70: Eduardo Reis Beraldo | B70: eduardo.beraldo@oi.net.br | C70: =VLOOKUP(A70,MTZ_Steakholders!$G$2:$K$123,5,0) -> M&A | D70: Gestor Imediato | F70: S
A71: Eduardo Streit | B71: eduardo.streit@oi.net.br | C71: =VLOOKUP(A71,MTZ_Steakholders!$E$2:$K$123,7,0) -> Caixa | D71: N3 | F71: S
A72: Elaine Ortega Gonzo Funchal Camacho | B72: elaine.camacho@oi.net.br | C72: =VLOOKUP(A72,MTZ_Steakholders!$I$2:$K$123,3,0) -> Sistemas TI | D72: Ponto Focal | F72: N
A73: Elaine Vermil Lima Santiago | B73: elaine.santiago@oi.net.br | C73: =VLOOKUP(A73,MTZ_Steakholders!$I$2:$K$123,3,0) -> Tributos/Fiscal | D73: Ponto Focal | F73: N
A74: Elen Marques Souto La Croix | B74: elen.souto@oi.net.br | C74: =VLOOKUP(A74,MTZ_Steakholders!$C$2:$K$123,9,0) -> Jur Consumidor | D74: N2 | F74: S
A75: Elisabete de Sousa Ribeiro | B75: elisabete.ribeiro@oi.net.br | C75: =VLOOKUP(A75,MTZ_Steakholders!$I$2:$K$123,3,0) -> Tesouraria | D75: Ponto Focal | F75: N
A76: Elly Resende Silva | B76: elly.resende@oi.net.br | C76: =VLOOKUP(A76,MTZ_Steakholders!$C$2:$K$123,9,0) -> Transição | D76: N2 | F76: S
A77: Erika Braga | B77: erika.braga@oi.net.br | C77: =VLOOKUP(A77,MTZ_Steakholders!$G$2:$K$123,5,0) -> Tributos/Fiscal | D77: Gestor Imediato | F77: S
A78: Evandro Schimming Smith Angelo | B78: evandro.angelo@oi.net.br | C78: =VLOOKUP(A78,MTZ_Steakholders!$C$2:$K$123,9,0) -> Patrimonio | D78: N2 | F78: S
A79: Fabricio Bindi | B79: fabricio.bindi@oi.net.br | C79: =VLOOKUP(A79,MTZ_Steakholders!$A$2:$K$123,11,0) -> Varejo | D79: N1 | F79: S
A80: Fabricio Cardoso De Faria Martins | B80: fabricio.martins@oi.net.br | C80: =VLOOKUP(A80,MTZ_Steakholders!$G$2:$K$123,5,0) -> Jur Consumidor | D80: Gestor Imediato | F80: S
A81: Felicia Daquino Nonato Rosetti | B81: felicia@oi.net.br | C81: =VLOOKUP(A81,MTZ_Steakholders!$G$2:$K$123,5,0) -> Varejo | D81: Gestor Imediato | F81: S
A82: Fernanda Beserra De Almeida | B82: fernanda.almeida@oi.net.br | C82: =VLOOKUP(A82,MTZ_Steakholders!$I$2:$K$123,3,0) -> CAP | D82: Ponto Focal | F82: N
A83: Fernanda Cristina Lisboa Fischer | B83: fernanda.fischer@oi.net.br | C83: =VLOOKUP(A83,MTZ_Steakholders!$C$2:$K$123,9,0) -> Transformação | D83: N2 | F83: S
A84: Fernando Raposo Franco | B84: fernando.franco@oi.net.br | C84: =VLOOKUP(A84,MTZ_Steakholders!$C$2:$K$123,9,0) -> Jur Tributario | D84: N2 | F84: S
A85: Fernando Vairolatti Del Negro Fonseca | B85: fernando.fonseca@oi.net.br | C85: =VLOOKUP(A85,MTZ_Steakholders!$C$2:$K$123,9,0) -> Planejamento | D85: N2 | F85: S
A86: Flavia Sobreira Casali Lima Bastos | B86: flaviacasali@oi.net.br | C86: =VLOOKUP(A86,MTZ_Steakholders!$C$2:$K$123,9,0) -> Tributos/Fiscal | D86: N2 | F86: S
A87: Francis Valente De Souza | B87: francis.souza@oi.net.br | C87: =VLOOKUP(A87,MTZ_Steakholders!$I$2:$K$123,3,0) -> Sistemas TI | D87: Ponto Focal | F87: N
A88: Francisco Anderson Pereira De Paiva | B88: francisco.paiva@oi.net.br | C88: =VLOOKUP(A88,MTZ_Steakholders!$I$2:$K$123,3,0) -> M&A | D88: Ponto Focal | F88: N
A89: Francisco Anderson Pereira De Paiva | B89: francisco.paiva@oi.net.br | C89: =VLOOKUP(A89,MTZ_Steakholders!$I$2:$K$123,3,0) -> M&A | D89: Ponto Focal | F89: N
A90: Francisco Herio Rodrigues Freire | B90: francisco.freire@oi.net.br | C90: =VLOOKUP(A90,MTZ_Steakholders!$I$2:$K$123,3,0) -> Tributos/Fiscal | D90: Ponto Focal | F90: N
A91: Francisco Jose Thurler Tecles Junior | B91: francisco.tecles@oi.net.br | C91: =VLOOKUP(A91,MTZ_Steakholders!$C$2:$K$123,9,0) -> Varejo | D91: N2 | F91: S
A92: Francisco Paulo Macambira Haick | B92: francisco.haick@oi.net.br | C92: =VLOOKUP(A92,MTZ_Steakholders!$E$2:$K$123,7,0) -> Contabilidade | D92: N3 | F92: S
A93: Gabriel Vidal da Silva | B93: gabriel.vidal@oi.net.br | C93: =VLOOKUP(A93,MTZ_Steakholders!$I$2:$K$123,3,0) -> Sistemas TI | D93: Ponto Focal | F93: N
A94: Giovani Cristiano Da Silva | B94: giovani.silva@oi.net.br | C94: =VLOOKUP(A94,MTZ_Steakholders!$C$2:$K$123,9,0) -> Atendimento | D94: N2 | F94: S
A95: Guilherme Pinheiro Da Fonseca Pascoa | B95: guilherme.pascoa@oi.net.br | C95: =VLOOKUP(A95,MTZ_Steakholders!$I$2:$K$123,3,0) -> Sistemas TI | D95: Ponto Focal | F95: N
A96: Gustavo Medina Miranda Da Silva | B96: gustavo.medina@oi.net.br | C96: =VLOOKUP(A96,MTZ_Steakholders!$G$2:$K$123,5,0) -> Jur Trabalhista | D96: Gestor Imediato | F96: S
A97: Gustavo Queiroz Da Silva Pinto | B97: gustavo.queiroz@oi.net.br | C97: =VLOOKUP(A97,MTZ_Steakholders!$I$2:$K$123,3,0) -> Sistemas TI | D97: Ponto Focal | F97: N
A98: Gustavo Roberto Brambila | B98: gbrambila@oi.net.br | C98: =VLOOKUP(A98,MTZ_Steakholders!$A$2:$K$123,11,0) -> Operação de Rede e SI | D98: N1 | F98: S
A99: Herivelton Pereira | B99: herivelton.santo@oi.net.br | C99: =VLOOKUP(A99,MTZ_Steakholders!$I$2:$K$123,3,0) -> Data Analytics | D99: Ponto Focal | F99: N
A100: Hozana Guimarães de Sá Braga | B100: hozana.braga@oi.net.br | C100: =VLOOKUP(A100,MTZ_Steakholders!$G$2:$K$123,5,0) -> Tributos/Fiscal | D100: Gestor Imediato | F100: S
...

Sheet Agenda Reuniões
B2: Agenda de Reunião
A3: 1 | B3: Daily M&A | C3: 10hs
A4: 2 | B4: Weekly Executiva | C4: Qui 11hs
A5: 3 | B5: Quinzenal Executiva | C5: Qua 11hs
A6: 4 | B6: Mensal CDG
A9: Após a confirmação dos participantes, iremos propor a agenda das reuniões das frentes de trabalho.
