Workbook

Sheet Anexo A-TODOS OS SERVIÇOS (OLD)
B2: Resumo dos serviços descritos no TSA. | C2: Topicos | D2: Anexo A (MobileCo) | E2: Texto Anexo A (ClientCo) | F2: Área responsável pelo Report | G2: Pessoa responsável pelo Report | H2: Áreas impactadas | I2: Anotações | J2: Status Anexo A | K2: Nome da VP | L2: N1 | M2: N2 | N2: N3 | O2: N4/ Consultor
B3: Customer data and offer management​ | C3: Reajuste de Planos e Serviços ou ajustes de portfólio (inclusão, exclusão ou alterações) ​ | D3: Sob demanda, a Oi deverá desenvolver sistemicamente as inclusões, exclusões, ou alterações de preço (e não de dinâmica) das ofertas dentro das práticas e volumes atuais da Oi de forma a reenquadrar portfólio/clientes. Envolve implementar, testar e garantir a qualidade em toda cadeia (Front end, Fatura, contabilização, etc.) podendo ser acompanhado pelas Compradoras. Políticas comerciais, regras, valores e features serão solicitadas pelas Compradoras e serão avaliadas pela Oi quanto a viabilidade técnica, financeira, legal e regulatória. As alterações implantadas terão report para fins de acompanhamento do solicitante. Qualquer modificação que demande Capex, deverá ser reembolsada e não estará coberta pelo cap do Contrato. | E3: Sob demanda, a Oi deverá desenvolver sistemicamente as inclusões, exclusões, ou alterações de preço (e não de dinâmica) das ofertas dentro das práticas e volumes atuais da Oi de forma a reenquadrar portfólio/clientes. Envolve implementar, testar e garantir a qualidade em toda cadeia (Front end, Fatura, contabilização, etc.) podendo ser acompanhado pelas Compradoras. Políticas comerciais, regras, valores e features serão solicitadas pelas Compradoras e serão avaliadas pela Oi quanto a viabilidade técnica, financeira, legal e regulatória. As alterações implantadas terão report para fins de acompanhamento do solicitante. Qualquer modificação que demande Capex, deverá ser reembolsada e não estará coberta pelo cap do Contrato. | F3: Produtos | G3: Felícia | H3: Varejo e Empresarial; Faturamento | J3: EXCLUIR ESTE ITEM | K3: Oi Fibra | L3: Fabricio Bindi <fabricio.bindi@oi.net.br> | M3: Luis Filipe Meira <lfmeira@oi.net.br> | N3: Renato Elias <renato.elias@oi.net.br> | O3: Felicia Daquino Nonato Rosetti <felicia@oi.net.br>
B4: Customer data and offer management​ | C4: BI sendo prestado pela OI​ | D4: Garantir acesso as Compradoras das informações necessárias para tomada de decisões referente aos processos determinados pelo Contrato até a data de migração dos clientes de acordo com o SLA, meio, formato e tecnologia a ser definido entre as partes, respeitando as capacidades tecnológicas e regulações vigentes. | E4: A Oi se compromete a, sob demanda, compartilhar informações já disponíveis ou fornecer detalhamento de viabilidade técnica, prazo e custo incremental de novos desenvolvimentos, para apoio à tomada de decisões referentes aos processos determinados pelo Contrato durante o prazo de vigência do TSA, levando em consideração SLA, meio, formato e tecnologia a serem definidos entre as partes, respeitando as capacidades tecnológicas e regulações vigentes. | F4: DA | G4: Bruno Palombo | H4: Data Analytics | I4: Bruno Palombo: refinamento de escopo detalhando cenário de solicitação de novos desenvolvimentos com custo incremental | J4: CONCLUÍDO | K4: Tecnologia | L4: Caio Marcio Gusmon <caio.gusmon@oi.net.br> | M4: Ulisses Fonseca Alves <ulisses.alves@oi.net.br> | N4: Bruno Palombo <bruno.palombo@oi.net.br> | O4: -
B5: Customer data and offer management​ | C5: Consultoria tributária e atendimento à fiscalização | D5: A Oi se compromete a avaliar atendimento à novas demandas legais, fiscais e regulatórias, efetuadas posteriormente à assinatura do Contrato, avaliando viabilidade técnica, riscos, prazos legais/regulatórios e custo incremental. | E5: A Oi se compromete a avaliar novas demandas legais, fiscais e tributárias, criadas/instituídas posteriormente à assinatura do Contrato (durante o período do TSA), avaliando viabilidade técnica, riscos, prazos legais e custo incremental. O custo, pelos desenvolvimentos necessários, serão arcados e/ou reembolsamos pela compradora, a depender do que ficar combinado no contrato. Não há como prever, de antemão, quais seriam esses custos, já que não sabemos quais novas obrigações poderiam ser criadas. Ademais, especificamente ao atendimento à fiscalização tributária, a Oi se compromete em garantir a disposnibilidação da documentação suporte conforme AS IS para atendimento às notificações recebidas pelo Jurídico Tributário. | F5: Jurídico Tributário | G5: Julia Villares e Alessandra Lima | H5: Jur. Tributário | I5: Premissa utilizada pelo Jurídicotributário para elaboração do texto da ClientCo (Alessandra): Tendo em vista que nos foi dito em reunião que a Oi vai se comprometer com as ClientCo a avaliar e levantar os custos para o atendimento das novas demandas legais, relativas a temas fiscais e tributários, que venham a ser instituídas/criadas posteriormente à assinatura do Contrato (desde o closing e durante o período de vigência do TSA). | J5: CONCLUÍDO | K5: Jurídico | L5: Thalles Eduardo Silva Gracelacio Da Paixao <thalles.paixao@oi.net.br> | M5: Fernando Raposo Franco <fernando.franco@oi.net.br> | N5: Pedro Rique Nepomuceno <pedro.nepomuceno@oi.net.br> | O5: Julia Villares Torres <julia.torres@oi.net.br>
B6: Customer data and offer management​ | C6: Consultoria cível estratégico | D6: Novi item | E6: A Oi se compromete a prestar consultoria jurídica ou viabilizar a interface dos integrantes do grupo com a área jurídica impactada. | F6: Jurídico Cível Estratégico | G6: Luiz Felipe Vargas | J6: CONCLUÍDO | K6: Jurídico | L6: Thalles Eduardo Silva Gracelacio Da Paixao <thalles.paixao@oi.net.br> | M6: Fernando Raposo Franco <fernando.franco@oi.net.br> | N6: Luiz Felipe Neves Do Couto Vargas <luizf.vargas@oi.net.br>
B7: Customer data and offer management​ | C7: Ajustes sistêmicos para Regulatório | D7: A Oi se compromete a avaliar atendimento à novas demandas legais, fiscais e regulatórias, efetuadas posteriormente à assinatura do Contrato, avaliando viabilidade técnica, riscos, prazos legais/regulatórios e custo incremental. | E7: A Oi se compromete a avaliar atendimento à novas demandas legais, fiscais e regulatórias, efetuadas posteriormente à assinatura do Contrato, avaliando viabilidade técnica, riscos, prazos legais/regulatórios e custo incremental. | F7: Regulatório | G7: Carlos Galvão/ Dennis | H7: Regulatório | J7: CONCLUÍDO | K7: Regulatório e Institucional | L7: Adriana Da Cunha Costa <adriana.costa@oi.net.br> | M7: Adriana Da Cunha Costa <adriana.costa@oi.net.br> | N7: Carlos Vasconcelos Galvao <carlosgalvao@oi.net.br> | O7: -
B8: Admin personnel​ | C8: Payroll administration​ | D8: - Tratar os dados necessários para cálculo da folha de pagamento, calcular a folha de pagamento, pagar os respectivos impostos e demais deduções. - Quanto a migração das informações dos colaboradores a serem transferidos (FTEs) para a Claro, essa também considera a migração em duas fases - a primeira com os dados dos colaboradores e uma segunda fase para migração dos dados históricos. Dessa forma, a Claro ficará com todas as informações em compliance com as regulamentações. | E8: "- Tratar os dados necessários para cálculo da folha de pagamento, calcular a folha de pagamento, pagar os respectivos impostos e demais deduções. - Quanto a migração das informações dos colaboradores a serem transferidos (FTEs) para as compradoras, essa também considera a migração de todos os dados dos colaboradores e uma única fase. | F8: RH | G8: Ricardo | H8: RH | I8: O ponto focal do RH para auxiliar as áreas a mensurar os custos dos profissionais envolvidos no TSA será o Carlos Eduardo da Rocha | J8: EXCLUIR ESTE ITEM | K8: Pessoas & Cultura | L8: Marcos Aurelio Freire Mendes <marcos.mendes@oi.net.br> | M8: Ricardo Goulart <rgoulart@oi.net.br> | N8: Carlos Eduardo Da Rocha Andrade <carlos.andrade@oi.net.br>; Jussara Petra Rocha <jussara.rocha@oi.net.br>; Valeria Da Conceicao Braga <valeria.braga@oi.net.br> | O8: -
B9: Admin personnel​ | C9: Benefits administration​ | D9: - Manutenção da base e gestão dos benefícios (plano médico, plano odontológico, seguro de vida, vale transporte, previdência privada, auxílio creche, auxílio medicamentos e tíquete refeição/alimentação garantindo a disponibilidade e qualidade dos mesmos; - Faturar a utilização total dos benefícios, parcela da coparticipação (ainda não descontada) e utilização total (custo empresa) pós closing | E9: "- Manutenção da base e gestão dos benefícios (plano médico, plano odontológico, seguro de vida, vale transporte, previdência privada, auxílio creche, auxílio medicamentos e tíquete refeição/alimentação garantindo a disponibilidade e qualidade dos mesmos; - Faturar as compradoras toda a utilização de benefícios, parcela da coparticipação (ainda não descontada) e utilização total (custo empresa) pós closing, durante todo o período do TSA. | F9: RH | G9: Ricardo | H9: RH | I9: O ponto focal do RH para auxiliar as áreas a mensurar os custos dos profissionais envolvidos no TSA será o Carlos Eduardo da Rocha | J9: EXCLUIR ESTE ITEM | K9: Pessoas & Cultura | L9: Marcos Aurelio Freire Mendes <marcos.mendes@oi.net.br> | M9: Ricardo Goulart <rgoulart@oi.net.br> | N9: Carlos Eduardo Da Rocha Andrade <carlos.andrade@oi.net.br>; Jussara Petra Rocha <jussara.rocha@oi.net.br>; Valeria Da Conceicao Braga <valeria.braga@oi.net.br> | O9: -
B10: Bill-to-cash​ | C10: Execução de ciclos de Billings​ | D10: - A Oi deverá executar o processo de faturamento de terminais móveis, mantendo os sistemas, regras e processos atuais, até a migração total desses clientes. - Execução de todos os ciclos de billings (majoritários e minoritários) em todos os sistemas de faturamento existentes no parque de TI. - Execução dos ciclos de billing para processo de Cobilling junto as operadoras (Entrante e Sainte). - Resolução dos problemas encontrados durante o processamento. | E10: - A Oi deverá executar o processo de faturamento de terminais fibra, mantendo os sistemas, regras e processos atuais, até a migração total desses clientes. - Execução de todos os ciclos de billings (majoritários e minoritários) em todos os sistemas de faturamento existentes no parque de TI. - Resolução dos problemas encontrados durante o processamento. | F10: Faturamento | G10: Monica | H10: Faturamento | J10: CONCLUÍDO | K10: Finanças e Relações com investidores | L10: Cristiane Barretto Sales <cristiane.barretto@oi.net.br> | M10: Bruno Macedo Soares <bmacedo@oi.net.br> | N10: Monica Sant Anna Paetzoldt <monica.paetzoldt@oi.net.br> | O10: -
B11: Bill-to-cash​ | C11: Tarifação de chamadas, dados e eventos ​ | D11: A Oi irá executar o processo de tarifação de chamadas/ eventos/ SVAs/ consumo excedentes de terminais móveis, mantendo os sistemas, regras, processos e produtos e ofertas atuais, até a migração total desses clientes. - O tráfego do CSP das Compradoras continuará a ser tratado como Cobilling - Execução dos processos de tarifação em todos os sistemas de tarifação (chamadas, eventos e consumos de dados) realizados pelos clientes do segmento móvel. - Contemplar o processo de tarifação para chamadas de outras operadoras (Entrante e Sainte) e também Parcerias/CO faturamento “doações – SVAs”, garantindo o envio e recepção de chamadas. - Resolução dos problemas encontrados durante o processamento. | E11: - Realização do processo de Tarifação de Voz, SVA e 0500 mantendo os sistemas, regras, processos e produtos e ofertas atuais, até a migração total desses clientes. - Resolução dos problemas encontrados durante o processamento. | F11: Tráfego | G11: Marcus Vinícius | H11: Faturamento// Tarifação e Repasse | J11: CONCLUÍDO | K11: Finanças e Relações com investidores | L11: Cristiane Barretto Sales <cristiane.barretto@oi.net.br> | M11: Bruno Macedo Soares <bmacedo@oi.net.br> | N11: Altevo Carlos De Sa Volotao <altevo.volotao@oi.net.br> | O11: Marcus Vinicius Miguel De Oliveira <marcus.oliveira@oi.net.br>
B12: Bill-to-cash​ | C12: Emissão de termos de quitação​ | D12: - Emissão do termo de quitação referentes aos pagamentos das últimas faturas dos clientes móveis, a exceção de clientes corporativos e atacado onde a emissão será manual e sob demanda do cliente. - Resolução dos problemas encontrados durante o processamento. - Todas as pendências de emissão dos termos de quitação anteriores a data do fechamento do contrato deverão ser regularizadas. | E12: - Emissão do termo de quitação referentes aos pagamentos das últimas faturas dos clientes fibra. - Resolução dos problemas encontrados durante o processamento. - Todas as pendências de emissão dos termos de quitação anteriores a data do fechamento do contrato deverão ser regularizadas. | F12: Faturamento | G12: Monica | H12: Fatutamento/ Atendimento | J12: CONCLUÍDO | K12: Finanças e Relações com investidores | L12: Cristiane Barretto Sales <cristiane.barretto@oi.net.br> | M12: Bruno Macedo Soares <bmacedo@oi.net.br> | N12: Monica Sant Anna Paetzoldt <monica.paetzoldt@oi.net.br> | O12: -
B13: Bill-to-cash​ | C13: Validação do billings gerados - consistência, qualidade e confiabilidade ​ | D13: - A Oi irá executar o processo de validação prévia de faturas de terminais móveis, mantendo os sistemas, regras e processos atuais, até a migração total desses clientes. - Corrigir e reportar o tratamento adotado em caso de desvios identificados mantendo os sistemas, regras, processos e performance atuais, até a migração total desses clientes. -Executar as validações de consistência sobre o ciclo de billing executado. - Execução/geração dos processos de Contestação e Críticas das chamadas de cobilling e/ou Parcerias. | E13: - A Oi irá executar o processo de validação prévia de faturas de terminais fibra, mantendo os sistemas, regras e processos atuais, até a migração total desses clientes. - Corrigir e reportar o tratamento adotado em caso de desvios identificados mantendo os sistemas, regras, processos e performance atuais, até a migração total desses clientes. -Executar as validações de consistência sobre o ciclo de billing executado. | F13: Faturamento | G13: Monica | H13: Faturamento | J13: CONCLUÍDO | K13: Finanças e Relações com investidores | L13: Cristiane Barretto Sales <cristiane.barretto@oi.net.br> | M13: Bruno Macedo Soares <bmacedo@oi.net.br> | N13: Monica Sant Anna Paetzoldt <monica.paetzoldt@oi.net.br> | O13: -
B14: Bill-to-cash​ | C14: Disponibilização de faturas online e customizadas ​ | D14: - Oi irá disponibilizar as faturas de terminais móveis, mantendo os sistemas, regras e processos atuais, até a migração total desses clientes, nos formatos e layout atuais (online e customizadas) para clientes varejo, empresarial e corporativos. - Carga dos spools faturados nas ferramentas que disponibilizam online os documentos de faturamento. - Resolução dos problemas encontrados durante o processamento. - Eventuais necessidades de alterações deverão ser discutidas em relação à custo e prazo. | E14: - Oi irá disponibilizar as faturas de terminais fibra, mantendo os sistemas, regras e processos atuais, até a migração total desses clientes, nos formatos e layout atuais (online e customizadas) para clientes varejo e empresarial. - Carga dos spools faturados nas ferramentas que disponibilizam online os documentos de faturamento. - Resolução dos problemas encontrados durante o processamento. - Eventuais necessidades de alterações deverão ser discutidas em relação à custo e prazo. | F14: Faturamento | G14: Monica | H14: Fatutamento/ Atendimento | J14: CONCLUÍDO | K14: Finanças e Relações com investidores | L14: Cristiane Barretto Sales <cristiane.barretto@oi.net.br> | M14: Bruno Macedo Soares <bmacedo@oi.net.br> | N14: Monica Sant Anna Paetzoldt <monica.paetzoldt@oi.net.br> | O14: -
B15: Bill-to-cash​ | C15: Envio dos spools para as print centers ​ | D15: - Oi irá disponibilizar os spools de faturas de terminais móveis para as print centers atuais da Oi (e remunerar os print centers), mantendo os sistemas, regras e processos atuais, até a migração total desses clientes, nos formatos e layout atuais (online e customizadas) para clientes varejo, empresarial e corporativos. - Conferência do faturamento gerado e consistências cadastrais. - Disponibilização dos documentos para as empresas de postagem. | E15: - Oi irá disponibilizar os spools de faturas de terminais fibra para as print centers atuais da Oi (e remunerar os print centers), mantendo os sistemas, regras e processos atuais, até a migração total desses clientes, nos formatos e layout atuais (online e customizadas) para clientes varejo e empresarial. - Conferência do faturamento gerado e consistências cadastrais. - Disponibilização dos documentos para as empresas de postagem. | F15: Faturamento | G15: Monica | H15: Faturamento | J15: CONCLUÍDO | K15: Finanças e Relações com investidores | L15: Cristiane Barretto Sales <cristiane.barretto@oi.net.br> | M15: Bruno Macedo Soares <bmacedo@oi.net.br> | N15: Monica Sant Anna Paetzoldt <monica.paetzoldt@oi.net.br> | O15: -
B16: Bill-to-cash​ | C16: Postagem das faturas para os clientes ​ | D16: - Oi irá disponibilizar os documentos de faturamento de terminais móveis para as empresas de postagem, mantendo os sistemas, regras e processos atuais, até a migração total desses clientes, nos formatos e layout atuais (online e customizadas) para clientes varejo, empresarial e corporativos. | E16: - Oi irá disponibilizar os documentos de faturamento de terminais fibra para as empresas de postagem, mantendo os sistemas, regras e processos atuais, até a migração total desses clientes, nos formatos e layout atuais (online e customizadas) para clientes varejo e empresarial. - Os clientes digitais terão seu envio da forma que solicitaram, seja via email ou whatsapp | F16: Faturamento | G16: Monica | H16: Faturamento | J16: CONCLUÍDO | K16: Finanças e Relações com investidores | L16: Cristiane Barretto Sales <cristiane.barretto@oi.net.br> | M16: Bruno Macedo Soares <bmacedo@oi.net.br> | N16: Monica Sant Anna Paetzoldt <monica.paetzoldt@oi.net.br> | O16: -
B17: Bill-to-cash​ | C17: Execução dos processos de garantia da receita ​ | D17: - Execução mensal de certificações da receita de serviços de clientes pós-pagos dos segmentos varejo e empresarial nos processos de aprovisionamento, faturamento e cobrança para garantia de integridade do cliente entre essas etapas. - Execução mensal de certificações da receita de clientes pré-pago e controle nos processos de contabilização da receita, geração de nota fiscal e controle do saldo da plataforma (recarga - consumo x saldo). - Identificação, tratamento e report dos problemas encontrados mantendo os patamares de recuperação vigentes. - Geração dos reports executivos e operacionais mensais de casos e oportunidades de recuperação financeira. | E17: - Execução mensal de análise de variação da receita de serviços recorrentes dos segmentos varejo e empresarial nas principais alavancas (gross, churn, interrupções de faturamento, migrações, variações de clientes da base, etc) - Análise mensal das alavancas NTFGA (motivo de Terminais não Faturarem e Gerarem Assinatura) para serviços pós pagos. - Acompanhamento mensal da despesa de ITX e análise dos desvios (VOIP) | F17: RA/ Fraude | G17: Alessandro Varme | H17: RA/ Varme | J17: CONCLUÍDO | K17: Finanças e Relações com investidores | L17: Cristiane Barretto Sales <cristiane.barretto@oi.net.br> | M17: Bruno Macedo Soares <bmacedo@oi.net.br> | N17: Alessandro Luiz Varme Dias <alessandro.varme@oi.net.br> | O17: -
B18: Bill-to-cash​ | C18: Execução da cadeia de arrecadação​ | D18: - Execução dos processos de arrecadação bancária de acordo com processos, regras e sistemas atuais da Oi. - Troca de arquivos/informações com as instituições financeiras cadastradas. - Resolução de problemas encontrados durante o processamento | E18: - Execução dos processos de arrecadação bancária de acordo com processos, regras e sistemas atuais da Oi. - Troca de arquivos/informações com as instituições financeiras cadastradas. - Resolução de problemas encontrados durante o processamento | F18: Arrecadação e Cobrança | G18: Daniel Cattete | H18: Arrecadação/Cobrança/Daniel Cattete | J18: CONCLUÍDO | K18: Finanças e Relações com investidores | L18: Cristiane Barretto Sales <cristiane.barretto@oi.net.br> | M18: Bruno Macedo Soares <bmacedo@oi.net.br> | N18: Daniel Cattete Sanguedo <daniel.sanguedo@oi.net.br> | O18: -
B19: Bill-to-cash​ | C19: Execução da cadeia de débito automático ​ | D19: - Execução dos processos de débito automático de acordo com processos, regras e sistemas atuais da Oi. - Troca de arquivos/informações com as instituições cadastradas. - Resolução de problemas encontrados durante o processamento | E19: - Execução dos processos de débito automático de acordo com processos, regras e sistemas atuais da Oi. - Troca de arquivos/informações com as instituições cadastradas. - Resolução de problemas encontrados durante o processamento | F19: Arrecadação e Cobrança | G19: Daniel Cattete | H19: Arrecadação/Cobrança/Daniel Cattete | J19: CONCLUÍDO | K19: Finanças e Relações com investidores | L19: Cristiane Barretto Sales <cristiane.barretto@oi.net.br> | M19: Bruno Macedo Soares <bmacedo@oi.net.br> | N19: Daniel Cattete Sanguedo <daniel.sanguedo@oi.net.br> | O19: -
B20: Bill-to-cash​ | C20: Execução dos processos de fraude ​ | D20: - Execução dos processos de fraude técnica de acordo com as regras e modelos atuais da Oi. - Geração dos reports executivos e operacionais para estancar/reverter as perdas. - Resolução dos problemas encontrados durante o processamento. | E20: - Execução dos processos de fraude subscrição de acordo com as regras e modelos atuais da Oi no modelo preventivo, caso o processo de vendas fique a cargo da Oi. - Execução dos processos de fraude técnica de acordo com as regras e modelos atuais da Oi (spoofing, fishing, smishing, etc). - Tratamento de fraudes identificadas no modelo detectivo - pós instalação. (churn e contas a receber) - Tratamento de out layers de consumo (investigação, retirada e tratamento contábil) - Tratamento de reclamações de clientes com alegação de fraude, avaliando procedência / improcedência da contestação. | F20: RA/ Fraude | G20: Alessandro Varme | H20: Fraude | J20: CONCLUÍDO | K20: Finanças e Relações com investidores | L20: Cristiane Barretto Sales <cristiane.barretto@oi.net.br> | M20: Bruno Macedo Soares <bmacedo@oi.net.br> | N20: Alessandro Luiz Varme Dias <alessandro.varme@oi.net.br> | O20: -
B21: Bill-to-cash​ | C21: Execução da cadeia fiscal​ | D21: - Execução dos processos fiscais para as Compradoras de acordo com a legislação vigente respeitando as respectivas regras e modelos atuais da Oi. - Geração e envio das obrigações acessórias, apuração e pagamento da obrigação principal, de acordo com os sistemas e procedimentos atuais da Oi. - Consistência contábil, reports executivos e operacionais atualmente executados pela Oi. - Resolução dos problemas encontrados, referente ao processo de apuração durante a validação das obrigações acessórias e da obrigação principal. | E21: - Execução dos processos fiscais para as Compradoras de acordo com a legislação vigente respeitando as respectivas regras e modelos atuais da Oi. - Geração e envio das obrigações acessórias, apuração e pagamento da obrigação principal, de acordo com os sistemas e procedimentos atuais da Oi. - Consistência contábil, reports executivos e operacionais atualmente executados pela Oi. - Resolução dos problemas encontrados, referente ao processo de apuração durante a validação das obrigações acessórias e da obrigação principal. | F21: Tributos/Fiscal | G21: Erika Braga | H21: Tributos Indiretos/ Tribustos Diretos | I21: Seguindo as mesmas definições tributárias utilizadas para o TSA do MARS, tais como: utilização dos sistemas fiscais comply, ERP SAP; sem migração do saldo acumulado do CIAP; os mesmos relatórios fiscais para fins de informações gerenciais e analíticas, mesmas obrigações principais e acessórias entregues atualmente pela BTSA. | J21: CONCLUÍDO | K21: Finanças e Relações com investidores | L21: Cristiane Barretto Sales <cristiane.barretto@oi.net.br> | M21: Flavia Casali <flaviacasali@oi.net.br> | N21: Erika Braga <erika.braga@oi.net.br> | O21: -
B22: Bill-to-cash​ | C22: Execução da cadeia contábil​ | D22: - Execução das cadeias contábeis para as Compradoras de acordo com a legislação vigente respeitando as respectivas regras e modelos atuais da Oi- Carga dos arquivos no SAP da Oi. - Export dos dados para as Compradoras no formato acordado. - Envio dos arquivos dos convênios XXX, YYY e ZZZ para o fisco. - Confirmação de recebimento dos arquivos fiscais pelo Fisco- Resolução dos problemas encontrados durante o processamento. | E22: Execução das cadeias contábeis para as Compradoras de acordo com a legislação vigente respeitando as respectivas regras e modelos atuais da Oi- Carga dos arquivos no SAP da Oi, dos seguintes macro processos: 1- Receita, Descontos, ICMS e ISS, conforme ciclo dos Sistemas de Faturamento. 2- Arrecadação, Parcelamento de Fatura, Cancelamento e Contestação, conforme movimentos dos Sistema de Faturamento e Arrecadação. 3- Provisão p/ Créditos de Liquidação e Perdas, conforme movimentos dos Sistemas de Arrecadação. Export dos dados para as Compradoras no formato acordado. | F22: Contabilidade | G22: Marcelo Gomes | H22: Contabilidade | I22: Marcelo Gomes: o tópico foi alinhado com as áreas impacatdas, o ponto abaixo é apenas um detalhamento do que foi alinhado com as áreas impactadas. Deve ser avaliado pelos times de Tributos Diretos (Paulo Vidal) e Tributos Indiretos (Érika Braga): Envio dos arquivos dos convênios XXX, YYY e ZZZ para o fisco. Confirmação de recebimento dos arquivos fiscais pelo Fisco- Resolução dos problemas encontrados durante o processamento. Obs. O cálculo do PIS, COFINS, FUST e FUNTTEL é realizado pelo time de Tributos Diretos após a liberação/validação pela Contabilidade Operacional, conforme cronograma de fechamento. | J22: CONCLUÍDO | K22: Finanças e Relações com investidores | L22: Cristiane Barretto Sales <cristiane.barretto@oi.net.br> | M22: Andre Tavares Paradizi <andre.paradizi@oi.net.br> | N22: Francisco Paulo Macambira Haick <francisco.haick@oi.net.br> | O22: Marcelo Gomes <marcelo.gomes@oi.net.br>
B23: Bill-to-cash​ | C23: Execução da régua de cobrança - Classificação e reclassificação de status na régua ​ | D23: - Execução dos processos atuais da Oi associados à régua de cobrança para que os clientes evoluam dentro dos estágios existentes na régua. - Resolução dos problemas encontrados durante o processamento. | E23: - Execução dos processos atuais da Oi associados à régua de cobrança para que os clientes evoluam dentro dos estágios existentes na régua. - Resolução dos problemas encontrados durante o processamento. | F23: Arrecadação e Cobrança | G23: Daniel Cattete | H23: Arrecadação/Cobrança/Daniel Cattete | J23: CONCLUÍDO | K23: Finanças e Relações com investidores | L23: Cristiane Barretto Sales <cristiane.barretto@oi.net.br> | M23: Bruno Macedo Soares <bmacedo@oi.net.br> | N23: Daniel Cattete Sanguedo <daniel.sanguedo@oi.net.br> | O23: -
B24: Bill-to-cash​ | C24: Execução da régua de cobrança - Geração de notificação para clientes inadimplentes ​ | D24: - Execução dos processos atuais de comunicações/notificações da Oi conforme regras Regulatórias pertinentes à régua de cobrança. - Resolução dos problemas encontrados durante o processamento. | E24: - Execução dos processos atuais de comunicações/notificações da Oi conforme regras Regulatórias pertinentes à régua de cobrança. - Resolução dos problemas encontrados durante o processamento. | F24: Arrecadação e Cobrança | G24: Daniel Cattete | H24: Arrecadação/Cobrança/Daniel Cattete | J24: CONCLUÍDO | K24: Finanças e Relações com investidores | L24: Cristiane Barretto Sales <cristiane.barretto@oi.net.br> | M24: Bruno Macedo Soares <bmacedo@oi.net.br> | N24: Daniel Cattete Sanguedo <daniel.sanguedo@oi.net.br> | O24: -
B25: Bill-to-cash​ | C25: Mediação de bilhetes​ | D25: A Oi irá executar o processo de mediação de bilhetes de terminais móveis, mantendo os sistemas, regras e processos atuais, até a migração total desses clientes. - O tráfego dos CSPs das Compradoras continuarão a serem tratados como cobilling. - Análise de todo tipo de tráfego gerado (SMS, Dados, Voz, Cobilling) na entrada, saída e etapas intermediárias da Mediação. - Controle de críticas e descartes de bilhetes. - Resolução dos problemas encontrados durante o processamento da Mediação. - Recuperação e reprocessamento de bilhetes em casos necessários | E25: - A Oi irá executar o processo de mediação de bilhetes de terminais Voip da ClientCo, mantendo os sistemas, regras e processos atuais, até a migração total desses clientes. - Controle de críticas e descartes de bilhetes. - Resolução dos problemas encontrados durante o processamento da Mediação. - Recuperação e reprocessamento de bilhetes em casos necessários | F25: Tráfego | G25: Marcus Vinícius | H25: Tráfego/Marcus Vinícius | J25: CONCLUÍDO | K25: Finanças e Relações com investidores | L25: Cristiane Barretto Sales <cristiane.barretto@oi.net.br> | M25: Bruno Macedo Soares <bmacedo@oi.net.br> | N25: Altevo Carlos De Sa Volotao <altevo.volotao@oi.net.br> | O25: Marcus Vinicius Miguel De Oliveira <marcus.oliveira@oi.net.br>
B26: Bill-to-cash​ | C26: Recuperação de faturas​ | D26: - Oi deverá recuperar faturas antigas de terminais móveis, mediante solicitações judiciais, regulatórias ou obrigações tributárias, mantendo os sistemas, regras e processos atuais. | E26: - Oi deverá recuperar faturas antigas dos clientes da ClienteCo, mediante solicitações judiciais, regulatórias ou obrigações tributárias, mantendo os sistemas, regras e processos atuais. | F26: Jurídico Consumidor | G26: Anderson Nilson | H26: Jurídico Consumidor/ Regulatório/ Tributário | J26: CONCLUÍDO | K26: Jurídico | L26: Thalles Eduardo Silva Gracelacio Da Paixao <thalles.paixao@oi.net.br> | M26: Elen Marques Souto La Croix <elen.souto@oi.net.br> | N26: Adriana Velhote De Oliveira <adriana.velhote@oi.net.br> | O26: Anderson Nilson Rocha <anderson.rocha@oi.net.br>
B27: Bill-to-cash​ | C27: Recuperação de faturas​ | D27: - Oi deverá recuperar faturas antigas de terminais móveis, mediante solicitações judiciais, regulatórias ou obrigações tributárias, mantendo os sistemas, regras e processos atuais. | E27: Oi deverá recuperar faturas antigas , mediante solicitações judiciais, regulatórias ou obrigações tributárias, mantendo os sistemas, regras e processos atuais. | F27: Atendimento | G27: Giane Carla | H27: Atendimento/Giane Carla | I27: O tópico engloba o Atendimento e a Ouvidoria. | J27: EXCLUIR ESTE ITEM | K27: Oi Fibra | L27: Fabricio Bindi <fabricio.bindi@oi.net.br> | M27: Jomerson Da Silva Almeida <jomerson.almeida@oi.net.br> | N27: Giane Carla Varela <giane.varela@oi.net.br> | O27: -
B28: Bill-to-cash​ | C28: Parametrizações e Homologações​ | D28: - Oi deverá avaliar solicitações das Compradoras de parametrizações e/ ou projetos nos sistemas de billing quanto a viabilidade técnica, financeira, legal e regulatória. - As alterações implantadas deverão ser testadas e homologadas pela Oi e terão report para fins de acompanhamento do solicitante. | E28: - Oi deverá avaliar solicitações das Compradoras de parametrizações e/ ou projetos nos sistemas de billing quanto a viabilidade. - As alterações implantadas deverão ser testadas e homologadas pela Oi e terão report para fins de acompanhamento do solicitante. - Todas as alterações deverão ser únicas para todos os comprovadores, não podem haver divergencia de regra e pedido entre eles. financeira, legal e regulatória. | F28: Faturamento | G28: Iara | H28: Faturamento/Iara | J28: CONCLUÍDO | K28: Finanças e Relações com investidores | L28: Cristiane Barretto Sales <cristiane.barretto@oi.net.br> | M28: Bruno Macedo Soares <bmacedo@oi.net.br> | N28: Iara Kelli Da Cruz Braga <iara.braga@oi.net.br> | O28: -
B29: Bill-to-cash​ | C29: Criação dos dossiês de clientes inadimplentes para ajuizamento, cobrança extrajudicial e recuperação judicial ​ | D29: - Criação de dossiês com toda a documentação necessária e disponível para que o jurídico inicie os ajuizamentos. - Acompanhamento dos processos judiciais junto ao jurídico. | E29: - Criação de dossiês com toda a documentação necessária e disponível para que o jurídico inicie os ajuizamentos. | F29: Arrecadação e Cobrança | G29: Daniel Cattete | H29: Jur Consumidor/Fabrício | J29: CONCLUÍDO | K29: Finanças e Relações com investidores | L29: Cristiane Barretto Sales <cristiane.barretto@oi.net.br> | M29: Bruno Macedo Soares <bmacedo@oi.net.br> | N29: Daniel Cattete Sanguedo <daniel.sanguedo@oi.net.br> | O29: -
B30: Bill-to-cash​ | C30: Geração e distribuição de mailing e de relatórios de performance da operação ​ | D30: - Geração de mailings conforme regras atuais da Oi para a cobrança das assessorias. - Geração de relatórios de performance mensal atuais da Oi. | E30: - Geração de mailings conforme regras atuais da Oi para a cobrança das assessorias. - Geração de relatórios de performance mensal atuais da Oi. | F30: Arrecadação e Cobrança | G30: Daniel Cattete | H30: Faturamento// Contas a receber/ Cobrança | J30: CONCLUÍDO | K30: Finanças e Relações com investidores | L30: Cristiane Barretto Sales <cristiane.barretto@oi.net.br> | M30: Bruno Macedo Soares <bmacedo@oi.net.br> | N30: Daniel Cattete Sanguedo <daniel.sanguedo@oi.net.br> | O30: -
B31: Bill-to-cash​ | C31: Relatórios de CAR e PDD​ | D31: - Oi deverá gerar os relatórios gerenciais e analíticos de CAR e PDD com visão por segmento e por cliente de acordo com os prazos, formatos e capacidade tecnológica atuais. | E31: Oi deverá gerar os relatórios contábeis de CAR analítico por Unidade de Negócio, por Cliente e por Fatura, de acordo com os prazos. Oi deverá gerar os relatórios de PDD/PERDAS sintético por Unidade de Negócio, de acordo com os prazos. Oi deverá gerar o relatório de PDD Parcelamento analítico por Unidade de Negócio, por Cliente e por Fatura, de acordo com os prazos. | F31: Contabilidade | G31: Marcelo Gomes | H31: Contas a receber/Cobrança // Contabilidade | J31: CONCLUÍDO | K31: Finanças e Relações com investidores | L31: Cristiane Barretto Sales <cristiane.barretto@oi.net.br> | M31: Andre Tavares Paradizi <andre.paradizi@oi.net.br> | N31: Francisco Paulo Macambira Haick <francisco.haick@oi.net.br> | O31: Marcelo Gomes <marcelo.gomes@oi.net.br>
B32: Bill-to-cash​ | C32: Execução dos processos de Crédito​ | D32: - Oi deverá executar os processos de análise de crédito de acordo com as regras e modelos atuais, mantendo sistemas, políticas e níveis de serviços para as Compradoras tratando os problemas identificados e gerando os reports executivos e operacionais para acompanhamento do processo de aprovação de crédito. - A performance dessa operação será acompanhada em reports de aprovação e reports de performance de FPD nas visões e aberturas acompanhadas atualmente pela Oi, caso o processo de venda e aquisição ocorra nos CRM da Oi. - Este item não se refere a vendas, mas sim as movimentações na planta de clientes, p.ex., upgrades, downgrades, contratação de novas linhas móveis B2B, etc. | E32: Oi deverá executar os processos de análise de crédito de acordo com as regras e modelos atuais, mantendo sistemas, políticas e níveis de serviços para as Compradoras tratando os problemas identificados nos processos de aprovação de crédito. A performance dessa operação será acompanhada em reports de aprovação e reports de performance de FPD nas visões e aberturas acompanhadas atualmente pela Oi, caso o processo de venda e aquisição ocorra nos CRM da Oi. | F32: Crédito | G32: Bruno Simões | H32: Contas a receber/ Cobrança | I32: [Bruno Simões] - Descrição validada durante a reunião. | J32: CONCLUÍDO | K32: Finanças e Relações com investidores | L32: Cristiane Barretto Sales <cristiane.barretto@oi.net.br> | M32: Bruno Macedo Soares <bmacedo@oi.net.br> | N32: - | O32: Bruno Simoes <bruno.simoes@oi.net.br>
B33: Bill-to-cash​ | C33: Repasse da receita de Fibra das UPI´s ClientCo | D33: Novo tópico | E33: - Realização de repasse mensal da receita de Fibra, SVA, Oi Expert, Fibra X e Add on para as compradoras. - Resolução dos problemas encontrados durante apuração do repasse. | F33: Tráfego | G33: Marcus Vinícius | H33: Tráfego | J33: CONCLUÍDO | K33: Finanças e Relações com investidores | L33: Cristiane Barretto Sales <cristiane.barretto@oi.net.br> | M33: Bruno Macedo Soares <bmacedo@oi.net.br> | N33: Altevo Carlos De Sa Volotao <altevo.volotao@oi.net.br> | O33: Marcus Vinicius Miguel De Oliveira <marcus.oliveira@oi.net.br>
B34: Bill-to-cash​ | C34: Co-Billing Interno CSP´s de Outras Operadoras | D34: Novo tópico | E34: - A Oi S/A prestará o serviço de co-faturamento do CSP de Outras Operadoras originado por terminais Voip da ClientCo. | F34: Tráfego | G34: Marcus Vinícius | H34: Tráfego | J34: CONCLUÍDO | K34: Finanças e Relações com investidores | L34: Cristiane Barretto Sales <cristiane.barretto@oi.net.br> | M34: Bruno Macedo Soares <bmacedo@oi.net.br> | N34: Altevo Carlos De Sa Volotao <altevo.volotao@oi.net.br> | O34: Marcus Vinicius Miguel De Oliveira <marcus.oliveira@oi.net.br>
B35: Bill-to-cash​ | C35: Operação de Interconexão | D35: Novo tópico | E35: - A Oi irá executar o processo de apuração da Interconexão de bilhetes de terminais Voip da ClientCo, mantendo os sistemas, regras e processos atuais, até a migração total desses clientes. - Controle de críticas e descartes de bilhetes. - Resolução dos problemas encontrados durante o processamento da Interconexão. - Recuperação e reprocessamento de bilhetes em casos necessários | F35: Tráfego | G35: Marcus Vinícius | H35: Tráfego | J35: CONCLUÍDO | K35: Finanças e Relações com investidores | L35: Cristiane Barretto Sales <cristiane.barretto@oi.net.br> | M35: Bruno Macedo Soares <bmacedo@oi.net.br> | N35: Altevo Carlos De Sa Volotao <altevo.volotao@oi.net.br> | O35: Marcus Vinicius Miguel De Oliveira <marcus.oliveira@oi.net.br>
B36: Bill-to-cash​ | C36: Repasse de SVA/Terceiros/0500 | D36: Novo tópico | E36: - Realização da apuração periodica dos valores para repasse de parceiros de SVA/Terceiros/0500 mantendo os sistemas, regras e processos atuais, até a migração total desses clientes. - Resolução dos problemas encontrados durante apuração do repasse. | F36: Tráfego | G36: Marcus Vinícius | H36: Tráfego | J36: CONCLUÍDO | K36: Finanças e Relações com investidores | L36: Cristiane Barretto Sales <cristiane.barretto@oi.net.br> | M36: Bruno Macedo Soares <bmacedo@oi.net.br> | N36: Altevo Carlos De Sa Volotao <altevo.volotao@oi.net.br> | O36: Marcus Vinicius Miguel De Oliveira <marcus.oliveira@oi.net.br>
B37: Bill-to-cash​ | C37: Relacionamento Finaceiro com as Demais Operadoras | D37: Novo tópico | E37: - A Oi irá executar o processo de encontro de contas de Interconexão, mantendo os sistemas, regras e processos atuais, até a migração total desses clientes. - Resolução dos problemas encontrados durante apuração do repasse. | F37: Tráfego | G37: Marcus Vinícius | H37: Tráfego | J37: CONCLUÍDO | K37: Finanças e Relações com investidores | L37: Cristiane Barretto Sales <cristiane.barretto@oi.net.br> | M37: Bruno Macedo Soares <bmacedo@oi.net.br> | N37: Altevo Carlos De Sa Volotao <altevo.volotao@oi.net.br> | O37: Marcus Vinicius Miguel De Oliveira <marcus.oliveira@oi.net.br>
B38: Bill-to-cash​ | C38: Obrigação Fiscal (entrada NF/input SAP/retenções de impostos) - OPERAÇÃO BPO | D38: Novo tópico | E38: -A Oi deverá executar o processo de lançamentos das NF's de entrada no SAP, com as devidas retenções federais e municipais. - Execução dos controles internos conforme relação de controles existentes (SOX). - Devolutiva das criticas para as NF não lançadas pelo Posto Fiscal | F38: Tributos/Fiscal | G38: Hozana Guimarães | H38: Tributos/Fiscal | J38: CONCLUÍDO | K38: Finanças e Relações com investidores | L38: Cristiane Barretto Sales <cristiane.barretto@oi.net.br> | M38: Flavia Casali <flaviacasali@oi.net.br> | N38: Hozana Guimaraes De Sa Braga <hozana.braga@oi.net.br> | O38: -
B39: Bill-to-cash​ | C39: Criação de Requisições de compras e pedidos(célula adm) - OPERAÇÃO BPO | D39: Novo tópico | E39: - A Oi deverá criar os novos pedidos de compras conforme demandas de serviços e equipamentos que estiverem vinculados aos contratos e verba disponiveis para as ClientCO's | F39: Tributos/Fiscal | G39: Hozana Guimarães | H39: Diversas áreas | J39: CONCLUÍDO | K39: Finanças e Relações com investidores | L39: Cristiane Barretto Sales <cristiane.barretto@oi.net.br> | M39: Flavia Casali <flaviacasali@oi.net.br> | N39: Hozana Guimaraes De Sa Braga <hozana.braga@oi.net.br> | O39: -
B40: Bill-to-cash​ | C40: Criação e Manutenção dos cadastros de Fornecedores, Clientes, códigos de materiais e serviços | D40: Novo tópico | E40: - A Oi deverá executar o processo de cadastro no SAP para as demandas referentes a criação de novos fornecedores, clientes, codigos de materiais e serviços, manutenção dos cadastros ( atualização de dados bancários, ampliações de centros, paramentros de códigos para corretas contabilizações, ajustes de aliquotas, domicilio fiscal etc, conforme necessidade que surgirem no periodo após drop. -Extração de relatório com as demandas que forem solicitadas no periodo. | F40: Tributos/Fiscal | G40: Hozana Guimarães | H40: Diversas áreas | J40: CONCLUÍDO | K40: Finanças e Relações com investidores | L40: Cristiane Barretto Sales <cristiane.barretto@oi.net.br> | M40: Flavia Casali <flaviacasali@oi.net.br> | N40: Hozana Guimaraes De Sa Braga <hozana.braga@oi.net.br> | O40: -
B41: Bill-to-cash​ | C41: Portal de Notas (Sistema de acesso de fornecedores, gestores de aceite e usuários do Posto Fiscal) | D41: Novo tópico | E41: - A Oi deverá garantir o processo sistemico de cadastro, armazenamento das NF's de entrada no BRNOTAS, integração com sistemas SAP para escrituração fiscal no SAP. - Extração de relatórios das NF cadastrdas, com status de tratamento. - Consulta das NF emitidas contra as ClientC0's | F41: Tributos/Fiscal | G41: Hozana Guimarães | H41: Tributos/Fiscal | J41: CONCLUÍDO | K41: Finanças e Relações com investidores | L41: Cristiane Barretto Sales <cristiane.barretto@oi.net.br> | M41: Flavia Casali <flaviacasali@oi.net.br> | N41: Hozana Guimaraes De Sa Braga <hozana.braga@oi.net.br> | O41: -
B42: Customer care​ | C42: Portabilidade a outro operador​ | D42: - Atendimento do port out através dos canais atuais de atendimento da Oi. - Receber um relatório das solicitações para que as Compradoras possam fazer ofertas para este cliente. - Devem ser definidos por contrato os níveis de serviço atuais (manutenção dos SLA’s contratuais vigentes). | E42: - Atendimento do port out através dos canais atuais de atendimento da Oi. - Receber um relatório das solicitações para que as Compradoras possam fazer ofertas para este cliente. - Devem ser definidos por contrato os níveis de serviço atuais (manutenção dos SLA’s contratuais vigentes). | F42: Atendimento | G42: Giane Carla | H42: Varejo e Empresarial // Atendimento | I42: O tópico engloba o Atendimento e a Ouvidoria. | J42: EXCLUIR ESTE ITEM | K42: Oi Fibra | L42: Fabricio Bindi <fabricio.bindi@oi.net.br> | M42: Jomerson Da Silva Almeida <jomerson.almeida@oi.net.br> | N42: Giane Carla Varela <giane.varela@oi.net.br> | O42: -
B43: Customer care​ | C43: URA​ | D43: - Oi deverá manter toda infraestrutura e sistemas de URA para direcionamento dos clientes durante o período de transição. - Envolve a segmentação, marcação e verbalização de árvore de URA, processos e direcionamentos de chamadas conforme padrões e políticas atuais. | E43: - Oi deverá manter toda infraestrutura e sistemas de URA para direcionamento dos clientes durante o período de transição. - Envolve a segmentação, marcação e verbalização de árvore de URA, processos e direcionamentos de chamadas conforme padrões e políticas atuais. | F43: Ura | G43: Katia Rolim | H43: URA / Atendimento | J43: EXCLUIR ESTE ITEM | K43: Oi Fibra | L43: Fabricio Bindi <fabricio.bindi@oi.net.br> | M43: Jomerson Da Silva Almeida <jomerson.almeida@oi.net.br> | N43: Katia Rolim <katia.pessoa@oi.net.br> | O43: -
B44: Customer care​ | C44: Contestação de chamadas e/ou ​serviços​ | D44: - Atendimento através dos canais da Oi que realizam esse serviço atualmente (Lojas Próprias - discricionário à Oi decidir quais lojas irá manter, ou com os custos pagos pelas Compradoras. Um eventual decomissionamento de loja própria deve antes ser submetido antes às Compradoras que, caso queiram mantê-la, assumirão a responsabilidade pelo seu custo; Franquias Oi Atende, Atendimento e Ilha de antifraude). As Compradoras poderão restringir atuação em algum canal, conforme sua estratégia. - Devem ser mantidos os níveis de serviço atuais (Manutenção dos SLA vigentes). - Devem ser validadas com o atendimento as regras e SLAs dos contratos em lojas e call centers bem como o modelo de controle, alçadas e políticas dos mesmos. | E44: EXCLUIR ESTE ITEM | F44: Atendimento | G44: Giane Carla | H44: Atendimento | I44: [Atendimento] - Item duplicado o tema é contestação e já tem um chamado "contestação de faturas" | J44: EXCLUIR ESTE ITEM | K44: Oi Fibra | L44: Fabricio Bindi <fabricio.bindi@oi.net.br> | M44: Jomerson Da Silva Almeida <jomerson.almeida@oi.net.br> | N44: Giane Carla Varela <giane.varela@oi.net.br> | O44: -
B45: Customer care​ | C45: Solução de Problemas Técnicos ​ | D45: - Atendimento e realização de troubleshooting para solução de problemas através dos canais da Oi que realizam esse serviço atualmente (Lojas Próprias - discricionário à Oi decidir quais lojas irá manter, ou com os custos pagos pelas Compradoras. Um eventual decomissionamento de loja própria deve antes ser submetido antes às Compradoras que, caso queiram mantê-la, assumirão a responsabilidade pelo seu custo; Franquias Oi Atende e Atendimento). - Em caso de insucesso na identificação e correção da falha, abertura de ticket para tratamento offline por equipe especializada com SLA estabelecido para a correção e também para o prazo de resposta ao cliente. - Devem ser definidos por contrato os níveis de serviço atuais (Manutenção dos SLA vigentes). - Devem ser validadas com o atendimento as regras e SLAs dos contratos em lojas e call centers bem como o modelo de controle dos mesmos. | E45: - Atendimento dos Clientes através da URA e canais digitais e realização de troubleshooting para solução das falhas reclamadas pelos Clientes, sejam da Banda Larga e VOIP. - Em caso de insucesso da solução remota e em sendo pertinente, o Suporte Técnico abre um reparo para o campo para que a falha seja solucionada in loco. - Além da célula dos do Suporte Técnico que atende a grande maioria dos Clientes do FTTH, existem células especializadas para determinadas tratativas e Produtos. - Célula do Suporte Avançado que trata os casos específicos de VoIP e IPTV. - Célula Repetidor, para o Cliente que apresenta um determinada incidência de entrada no Suporte Técnico. - Célula Proactive Care: Célula especializada na tratativa do Cliente FibraX, sendo constituída de um atendimento receptivo e outro ativo que faz uma predição das falhas utilizando de ferramentas e plataformas específicas e entra em contato com o Cliente antecipadamente. - O Suporte técnico possui também uma célula OFF que faz a tratativa dos reparos preventivos. - Devem ser definidos por contrato os níveis de serviço atuais (Manutenção dos SLA vigentes). - Devem ser validadas com o atendimento as regras e SLAs dos contrato do suporte técnico bem como o modelo de controle destes. | F45: Suporte Técnico | G45: João Arlindo | H45: Suporte Técnico | J45: CONCLUÍDO | K45: Operações de Redes e SI | L45: Gustavo Roberto Brambila <gbrambila@oi.net.br> | M45: Rafael Freitas De Amorim <rafael.amorim@oi.net.br> | N45: Fabricio Ladislau <fabricio.ladislau@oi.net.br> | O45: Joao Arlindo Brito Junior <joao.brito@oi.net.br>
B46: Customer care​ | C46: Troca de número​ | D46: - Atendimento e realização de trocas de número de linha através dos canais da Oi que realizam esse serviço atualmente (Lojas Próprias - discricionário à Oi decidir quais lojas irá manter, ou com os custos pagos pelas Compradoras. Um eventual decomissionamento de loja própria deve antes ser submetido antes às Compradoras que, caso queiram mantê-la, assumirão a responsabilidade pelo seu custo; e Franquias Oi Atende). - Deverá manter todas as obrigações regulatórias e também todas as regras e controles vigentes para evitar fraudes. - Devem ser definidos por contrato os níveis - Devem ser definidos por Contrato os níveis de serviço atuais (Manutenção dos SLA vigentes). - Devem ser validadas com o atendimento as regras e SLAs dos contratos em lojas e call centers bem como o modelo de controle dos mesmos. | E46: - Atendimento e realização de trocas de número de linha através dos canais da Oi que realizam esse serviço atualmente (Atedimento call center) - Deverá manter todas as obrigações regulatórias e também todas as regras e controles vigentes para evitar fraudes. - Devem ser definidos por contrato os níveis - Devem ser definidos por Contrato os níveis de serviço atuais (Manutenção dos SLA vigentes). - Devem ser validadas com o atendimento as regras e SLAs dos contratos em lojas e call centers bem como o modelo de controle dos mesmos. | F46: Atendimento | G46: Giane Carla | H46: Atendimento | I46: O tópico engloba o Atendimento e a Ouvidoria. | J46: EXCLUIR ESTE ITEM | K46: Oi Fibra | L46: Fabricio Bindi <fabricio.bindi@oi.net.br> | M46: Jomerson Da Silva Almeida <jomerson.almeida@oi.net.br> | N46: Giane Carla Varela <giane.varela@oi.net.br> | O46: -
B47: Customer care​ | C47: Troca ou Ativação de SIM Card e eSIM ​ | D47: - Atendimento e realização de trocas e ativações de SIM card através dos canais da Oi que realizam esse serviço atualmente (Lojas Próprias - discricionário à Oi decidir quais lojas irá manter, ou com os custos pagos pelas Compradoras. Um eventual decomissionamento de loja própria deve antes ser submetido antes às Compradoras que, caso queiram mantê-la, assumirão a responsabilidade pelo seu custo; e Franquias Oi Atende). - Deverá manter todas as obrigações regulatórias e também todas as regras e controles vigentes para evitar fraudes. - Devem ser definidos por contrato os níveis. - Devem ser definidos por Contrato os níveis de serviço atuais (Manutenção dos SLA vigentes). - Devem ser validadas com o atendimento as regras e SLAs dos contratos em lojas e call centers bem como o modelo de controle dos mesmos. - A política de SIM Card deverá seguir estratégia e definições vigentes da Oi | E47: EXCLUIR ESTE ITEM | F47: Suporte Técnico | G47: João Arlindo | H47: Suporte Técnico | I47: [João] - Serviço exclusivo da Oi Móvel, não se aplica para Clientco. | J47: EXCLUIR ESTE ITEM | K47: Operações de Redes e SI | L47: Gustavo Roberto Brambila <gbrambila@oi.net.br> | M47: Rafael Freitas De Amorim <rafael.amorim@oi.net.br> | N47: Fabricio Ladislau <fabricio.ladislau@oi.net.br> | O47: Joao Arlindo Brito Junior <joao.brito@oi.net.br>
B48: Customer care​ | C48: Troca de Titularidade ​ | D48: - Atendimento e realização de trocas de titularidade através dos canais da Oi que realizam esse serviço atualmente (Lojas Próprias - discricionário à Oi decidir quais lojas irá manter, ou com os custos pagos pelas Compradoras. Um eventual decomissionamento de loja própria deve antes ser submetido antes às Compradoras que, caso queiram mantê-la, assumirão a responsabilidade pelo seu custo; Franquias Oi Atende e Atendimento). - Deverá manter todas as obrigações regulatórias e também todas as regras e controles vigentes para evitar fraudes. - Devem ser definidos por contrato os níveis de serviço atuais (Manutenção dos SLA vigentes). | E48: - Atendimento e realização de trocas de titularidade através dos canais da Oi que realizam esse serviço atualmente (Atendimento Call Center, Canais digitais). - Deverá manter todas as obrigações regulatórias e também todas as regras e controles vigentes para evitar fraudes. - Devem ser definidos por contrato os níveis de serviço atuais (Manutenção dos SLA vigentes). | F48: Atendimento | G48: Giane Carla | H48: Atendimento | I48: O tópico engloba o Atendimento e a Ouvidoria. | J48: EXCLUIR ESTE ITEM | K48: Oi Fibra | L48: Fabricio Bindi <fabricio.bindi@oi.net.br> | M48: Jomerson Da Silva Almeida <jomerson.almeida@oi.net.br> | N48: Giane Carla Varela <giane.varela@oi.net.br> | O48: -
B49: Customer care​ | C49: Execução da régua de cobrança - Geração de acordo de pagamento ​ | D49: - Para clientes ainda ativos deve-se manter o mesmo processo de atendimento e negociação de parcelamento atual da Oi. - Atendimento através dos canais da Oi que realizam esse serviço atualmente e conforme escopo atual de cada canal (Lojas Próprias - discricionário à Oi decidir quais lojas irá manter, ou com os custos pagos pelas Compradoras. Um eventual decomissionamento de loja própria deve antes ser submetido antes às Compradoras que, caso queiram mantê-la, assumirão a responsabilidade pelo seu custo; Franquias Oi Atende, Ecommerce, Atendimento e Cognitivos). - Garantir por contrato que os canais atuais sejam mantidos durante o período de transição. - Devem ser definidos por contrato os níveis de serviço atuais (Manutenção dos SLA vigentes). - Os processos de cobrança de terminais móveis pós-pagos inadimplentes serão realizados pela Oi até a data da migração dos clientes para as Compradoras, incluindo régua de cobrança, notificações, bloqueios, desbloqueios, termos de quitação, renegociação, descontos e parcelamento de dívidas, de acordo com os processos, canais, contratos, políticas e capacidades tecnológicas atuais. | E49: - Para clientes ainda ativos deve-se manter o mesmo processo de atendimento e negociação de parcelamento atual da Oi. - Atendimento através dos canais da Oi que realizam esse serviço atualmente e conforme escopo atual de cada canal (Atedimento call center, canais digitais e URA). - Garantir por contrato que os canais atuais sejam mantidos durante o período de transição. - Devem ser definidos por contrato os níveis de serviço atuais (Manutenção dos SLA vigentes). - Os processos de cobrança de terminais móveis pós-pagos inadimplentes serão realizados pela Oi até a data da migração dos clientes para as Compradoras, incluindo régua de cobrança, notificações, bloqueios, desbloqueios, termos de quitação, renegociação, descontos e parcelamento de dívidas, de acordo com os processos, canais, contratos, políticas e capacidades tecnológicas atuais. | F49: Atendimento | G49: Giane Carla | H49: Contas a receber/ Cobrança/ Atendimento | I49: O tópico engloba o Atendimento e a Ouvidoria. | J49: EXCLUIR ESTE ITEM | K49: Oi Fibra | L49: Fabricio Bindi <fabricio.bindi@oi.net.br> | M49: Jomerson Da Silva Almeida <jomerson.almeida@oi.net.br> | N49: Giane Carla Varela <giane.varela@oi.net.br> | O49: -
B50: Customer care​ | C50: Emissão de segunda via de conta​ | D50: - Atendimento aos pedidos de emissão de 2a via de conta através dos canais da Oi que atualmente realiza esse serviço (Lojas próprias, Franquia Oi Atende, App, Ecommerce, Atendimento, Cognitivos, etc.). - Garantir por contrato que os canais atuais sejam mantidos durante o período de transição. - Devem ser definidos por contrato os níveis de serviço atuais (Manutenção dos SLA vigentes). - Devem ser validadas com o atendimento as regras e SLAs dos contratos em lojas e call centers bem como o modelo de controle dos mesmos. | E50: - Atendimento aos pedidos de emissão de 2a via de conta através dos canais da Oi que atualmente realiza esse serviço (Atedimento call center, canais digitais e URA). - Garantir por contrato que os canais atuais sejam mantidos durante o período de transição. - Devem ser definidos por contrato os níveis de serviço atuais (Manutenção dos SLA vigentes). - Devem ser validadas com o atendimento as regras e SLAs dos contratos em lojas e call centers bem como o modelo de controle dos mesmos. | F50: Atendimento | G50: Giane Carla | H50: URA / Atendimento/ Joice/ Minha Oi/ Oi_e | I50: O tópico engloba o Atendimento e a Ouvidoria. | J50: EXCLUIR ESTE ITEM | K50: Oi Fibra | L50: Fabricio Bindi <fabricio.bindi@oi.net.br> | M50: Jomerson Da Silva Almeida <jomerson.almeida@oi.net.br> | N50: Giane Carla Varela <giane.varela@oi.net.br> | O50: -
B51: Customer care​ | C51: Cadastramento em débito automático​ | D51: - Atendimento aos pedidos de cadastramento de débito automático através dos canais da Oi que realizam esse serviço atualmente (Lojas Próprias - discricionário à Oi decidir quais lojas irá manter, ou com os custos pagos pelas Compradoras. Um eventual decomissionamento de loja própria deve antes ser submetido antes às Compradoras que, caso queiram mantê-la, assumirão a responsabilidade pelo seu custo; Franquias Oi Atende, Bancos, Ecommerce, App, Atendimento, URA e Cognitivos). - Garantir por contrato que os canais atuais sejam mantidos durante o período de transição. - Devem ser definidos por contrato os níveis de serviço atuais (Manutenção dos SLA vigentes). - Devem ser validadas com o atendimento as regras e SLAs dos contratos em lojas e call centers bem como o modelo de controle dos mesmos. | E51: EXCLUIR ESTE ITEM | F51: Vendas (var/ Emp) | G51: Emanuelle | H51: URA / Atendimento/ Joice/ Minha Oi/ Oi_e/ E-commerce | I51: [Emanuelle] - Devemos excluir o item porque não temos mais lojas próprias. Todo atendimento deve ser através do SAC e seus canais digitais. | J51: EXCLUIR ESTE ITEM | K51: Oi Fibra | L51: Fabricio Bindi <fabricio.bindi@oi.net.br> | M51: Fernando Vairolatti Del Negro Fonseca <fernando.fonseca@oi.net.br> | N51: Emanuelle Rocha <emanuelle.rocha@oi.net.br> | O51: -
B52: Customer care​ | C52: Conversão de conta para digital (E-Billing)​ | D52: - Atendimento aos pedidos de conversão de conta digital (E-billing) através dos canais da Oi que realizam esse serviço atualmente (Lojas Próprias - discricionário à Oi decidir quais lojas irá manter, ou com os custos pagos pelas Compradoras. Um eventual decomissionamento de loja própria deve antes ser submetido antes às Compradoras que, caso queiram mantê-la, assumirão a responsabilidade pelo seu custo; Franquias Oi Atende, Ecommerce, App, Atendimento, URA e Cognitivos). - Garantir por contrato que os canais atuais sejam mantidos durante o período de transição. - Devem ser definidos por contrato os níveis de serviço atuais (Manutenção dos SLA vigentes). - Devem ser validadas com o atendimento as regras e SLAs dos contratos em lojas e call centers bem como o modelo de controle dos mesmos. | E52: - Atendimento aos pedidos de conversão de conta digital (E-billing) através dos canais da Oi que realizam esse serviço atualmente . - Garantir por contrato que os canais atuais sejam mantidos durante o período de transição. - Devem ser definidos por contrato os níveis de serviço atuais (Manutenção dos SLA vigentes). - Devem ser validadas com o atendimento as regras e SLAs dos contratos em lojas e call centers bem como o modelo de controle dos mesmos. | F52: Atendimento | G52: Giane Carla | H52: Arrecadação | I52: O tópico engloba o Atendimento e a Ouvidoria. | J52: EXCLUIR ESTE ITEM | K52: Oi Fibra | L52: Fabricio Bindi <fabricio.bindi@oi.net.br> | M52: Jomerson Da Silva Almeida <jomerson.almeida@oi.net.br> | N52: Giane Carla Varela <giane.varela@oi.net.br> | O52: -
B53: Customer care​ | C53: Alteração de dados cadastrais/ método de pagamento/data de vencimento ​ | D53: - Atendimento aos pedidos de alteração de dados cadastrais / método de pagamento / data de vencimento através dos canais da Oi que realizam esse serviço atualmente e conforme escopo atual de cada canal (Lojas Próprias - discricionário à Oi decidir quais lojas irá manter, ou com os custos pagos pelas Compradoras. Um eventual decomissionamento de loja própria deve antes ser submetido antes às Compradoras que, caso queiram mantê-la, assumirão a responsabilidade pelo seu custo; Franquias Oi Atende, Ecommerce, App e Atendimento). - Garantir por contrato que os canais atuais sejam mantidos durante o período de transição. - Devem ser definidos por contrato os níveis de serviço atuais (Manutenção dos SLA vigentes). - Devem ser validadas com o atendimento as regras e SLAs dos contratos em lojas e call centers bem como o modelo de controle dos mesmos. | E53: - Atendimento aos pedidos de alteração de dados cadastrais / método de pagamento / data de vencimento através dos canais da Oi que realizam esse serviço atualmente e conforme escopo atual de cada canal .(Atedimento call center, canais digitais e URA). - Garantir por contrato que os canais atuais sejam mantidos durante o período de transição. - Devem ser definidos por contrato os níveis de serviço atuais (Manutenção dos SLA vigentes). - Devem ser validadas com o atendimento as regras e SLAs dos contratos em lojas e call centers bem como o modelo de controle dos mesmos. | F53: Atendimento | G53: Giane Carla | H53: Atendimento | I53: O tópico engloba o Atendimento e a Ouvidoria. | J53: EXCLUIR ESTE ITEM | K53: Oi Fibra | L53: Fabricio Bindi <fabricio.bindi@oi.net.br> | M53: Jomerson Da Silva Almeida <jomerson.almeida@oi.net.br> | N53: Giane Carla Varela <giane.varela@oi.net.br> | O53: -
B54: Customer care​ | C54: Bloqueio e desbloqueio do serviço de forma temporária | D54: - Atendimento aos pedidos de Bloqueio e desbloqueio de linha e aparelhos (perda ou roubo) através dos canais da Oi que realizam esse serviço atualmente e conforme escopo atual de cada canal (Lojas Próprias - discricionário à Oi decidir quais lojas irá manter, ou com os custos pagos pelas Compradoras. Um eventual decomissionamento de loja própria deve antes ser submetido antes às Compradoras que, caso queiram mantê-la, assumirão a responsabilidade pelo seu custo; Franquia Oi Atende, Ecommerce, Atendimento e URA). - Manter o procedimento atual de bloqueio / desbloqueio de IMEIS conforme diretrizes da ANATEL até a data de migração dos clientes. - Compartilhar, periodicamente, o controle de movimentações de suspensões e bloqueios. - Garantir por contrato que os canais atuais sejam mantidos durante o período de transição. - Devem ser definidos por contrato os níveis de serviço atuais (Manutenção dos SLA vigentes). - Devem ser validadas com o atendimento as regras e SLAs dos contratos em lojas e call centers bem como o modelo de controle dos mesmos. Obs.: deve-se avaliar a possibilidade técnica de buscar uma solução de desbloqueio que já considere uma migração para base da entidade compradora. | E54: - Manter o procedimento atual de bloqueio / desbloqueio conforme diretrizes da ANATEL até a data de migração dos clientes, através dos canais da Oi que realizam esse serviço atualmente e conforme escopo atual de cada canal (Atedimento call center, canais digitais e URA). - Compartilhar, periodicamente, o controle de movimentações de suspensões e bloqueios. - Garantir por contrato que os canais atuais sejam mantidos durante o período de transição. - Devem ser definidos por contrato os níveis de serviço atuais (Manutenção dos SLA vigentes). - Devem ser validadas com o atendimento as regras e SLAs dos contratos em lojas e call centers bem como o modelo de controle dos mesmos. Obs.: deve-se avaliar a possibilidade técnica de buscar uma solução de desbloqueio que já considere uma migração para base da entidade compradora. | F54: Atendimento | G54: Giane Carla | H54: Atendimento | I54: Texto ajustado para bloqueio temporário | J54: EXCLUIR ESTE ITEM | K54: Oi Fibra | L54: Fabricio Bindi <fabricio.bindi@oi.net.br> | M54: Jomerson Da Silva Almeida <jomerson.almeida@oi.net.br> | N54: Giane Carla Varela <giane.varela@oi.net.br> | O54: -
B55: Customer care​ | C55: Solicitação de acessos a outros canais (senhas de app e portal) ​ | D55: - Atendimento aos pedidos de acessos a outros canais (senhas de app e portal) através dos canais da Oi que realizam esse serviço atualmente (Ecommerce e App). - Garantir por contrato que os canais atuais sejam mantidos durante o período de transição. - Devem ser definidos por contrato os níveis de serviço atuais (Manutenção dos SLA vigentes). - Devem ser validadas com o atendimento as regras e SLAs dos contratos em lojas e call centers bem como o modelo de controle dos mesmos. | E55: - Atendimento aos pedidos de acessos a outros canais (senhas de app e portal) através dos canais da Oi que realizam esse serviço atualmente (Ecommerce e App). - Garantir por contrato que os canais atuais sejam mantidos durante o período de transição. - Devem ser definidos por contrato os níveis de serviço atuais (Manutenção dos SLA vigentes). - Devem ser validadas com o atendimento as regras e SLAs dos contratos em lojas e call centers bem como o modelo de controle dos mesmos. | F55: Atendimento | G55: Giane Carla | H55: Atendimento | I55: O tópico engloba o Atendimento e a Ouvidoria. | J55: EXCLUIR ESTE ITEM | K55: Oi Fibra | L55: Fabricio Bindi <fabricio.bindi@oi.net.br> | M55: Jomerson Da Silva Almeida <jomerson.almeida@oi.net.br> | N55: Giane Carla Varela <giane.varela@oi.net.br> | O55: -
B56: Customer care​ | C56: Interação com Tribunais de Justiça, Órgãos e entidades de Relacionamento com consumidores: PROCON, Ouvidoria ANATEL e Consumidor.gov ​ | D56: - Atendimento pelos canais exigidos e pré-acordados com as instâncias externas para recepção de contatos e reclamações dos Procons Estaduais e o site Consumidor.gov bem como os canais regulados de resposta com a Anatel e Ouvidoria Anatel. - Os SLAs também já são os estabelecidos e acordados pelos mesmos. | E56: - Internalização e definição para tratamento de demandas judiciais e administrativas dos consumidores - Atendimento pelos canais exigidos e pré-acordados com as instâncias externas para recepção de contatos e reclamações prevenientes dos Tribunais de Justiça, Procons, site Consumidor.Gov, bem como, canais regulados de respostas com a Anatel e Ouvidoria Anatel. - Os SLAs também já são os estabelecidos e acordados pelos mesmos. | F56: Jurídico Consumidor | G56: Anderson Nilson | H56: Jur Consumidor/ Ouvidoria/ Anatel | J56: CONCLUÍDO | K56: Jurídico | L56: Thalles Eduardo Silva Gracelacio Da Paixao <thalles.paixao@oi.net.br> | M56: Elen Marques Souto La Croix <elen.souto@oi.net.br> | N56: Adriana Velhote De Oliveira <adriana.velhote@oi.net.br> | O56: Anderson Nilson Rocha <anderson.rocha@oi.net.br>
B57: Customer care​ | C57: Solicitação de bloqueio Judicial ​de ações criminais | D57: - Atendimento e execução aos pedidos de bloqueio judicial de linhas, de acordo com os processos vigentes nos canais de BackOffice da Oi, mediante solicitação da operadora responsável pelo terminal, enquanto a adquirente não tiver acesso à rede para programar os bloqueios. | E57: EXCLUIR ESTE ITEM | F57: Ações restritas | G57: Walbert | H57: VTAL | I57: [Walbert] - Não existe demanda para bloqueio judicial fibra/voip. | J57: EXCLUIR ESTE ITEM | K57: Suporte ao Negócio | L57: Daniel Junqueira Pinto Hermeto <daniel.hermeto@oi.net.br> | M57: Evandro Schimming Smith Angelo <evandro.angelo@oi.net.br> | N57: Adriano Andrey Israel <adriano.israel@oi.net.br> | O57: Walbert De Almeida Bueno <walbert.bueno@oi.net.br>
B58: Customer care​ | C58: Bloqueio Judicial/ Anatel | D58: - Atendimento e execução aos pedidos de bloqueio judicial de linhas, de acordo com os processos vigentes nos canais de BackOffice da Oi, mediante solicitação da operadora responsável pelo terminal, enquanto a adquirente não tiver acesso à rede para programar os bloqueios. | E58: EXCLUIR ESTE ITEM | F58: Regulatório | G58: Carlos Galvão/ Dennis | H58: Operação Rafael Amorim | I58: [ Luiz Conha]: Tema excluído porque já está contemplado no tópico "Interceptação judicial ​/ Quebra de Sigilo" | J58: EXCLUIR ESTE ITEM | K58: Regulatório e Institucional | L58: Adriana Da Cunha Costa <adriana.costa@oi.net.br> | M58: Adriana Da Cunha Costa <adriana.costa@oi.net.br> | N58: Carlos Vasconcelos Galvao <carlosgalvao@oi.net.br> | O58: -
B59: Customer care​ | C59: Interceptação Judicial de chamadas e dados ​ | D59: Execução de interceptação de chamadas e dados e outros serviços de quebra de sigilo, deverá ser realizada pela Oi, mediante solicitação da operadora responsável pelo terminal, devidamente acompanhada do ofício que a requereu, enquanto a adquirente não tiver acesso à rede para programar as interceptações | E59: Execução de interceptação de chamadas e dados e outros serviços de quebra de sigilo, deverá ser realizada pela Oi, mediante solicitação da operadora responsável pelo terminal, devidamente acompanhada do ofício que a requereu, enquanto a adquirente não tiver acesso à rede e a obtenção do dados de CDR, para realizar a programação dos terminais e forncimento de extratos de chamadas e dados de conexões a internet. | F59: Ações restritas | G59: Walbert | H59: VTAL | J59: CONCLUÍDO | K59: Suporte ao Negócio | L59: Daniel Junqueira Pinto Hermeto <daniel.hermeto@oi.net.br> | M59: Evandro Schimming Smith Angelo <evandro.angelo@oi.net.br> | N59: Adriano Andrey Israel <adriano.israel@oi.net.br> | O59: Walbert De Almeida Bueno <walbert.bueno@oi.net.br>
B60: Customer care​ | C60: Atendimento presencial | D60: Novo tópico | E60: EXCLUIR ESTE ITEM | F60: Vendas (var/ Emp) | G60: Emanuelle | H60: Atendimento | I60: [Emanuelle] - Apesar do Atendimento ter solicitado a criação desse tópico, foi confirmado pela Emanuelle que o mesmo deve ser excluído porque não temos mais atendimento presencial. | J60: EXCLUIR ESTE ITEM | K60: Oi Fibra | L60: Fabricio Bindi <fabricio.bindi@oi.net.br> | M60: Fernando Vairolatti Del Negro Fonseca <fernando.fonseca@oi.net.br> | N60: Emanuelle Rocha <emanuelle.rocha@oi.net.br> | O60: -
B61: Core network O&M​ | C61: Configuração em elementos de pré-pago e IN​ | D61: De acordo com as regras e parâmetros atuais, utilizando os recursos, sistemas, plataformas atuais, a Oi deverá: - Executar serviços de configuração, parametrização e roteamente em elementos de rede para serviços de pré-pago e IN, de acordo com as necessidades das Compradoras. | E61: Depende da área Oi | F61: Operações de Rede e SI | G61: Priscila Falco | H61: Operações de Rede e SI | I61: Tópicos foram substituídos por outros, enviados pela Priscilla Falco | J61: EXCLUIR ESTE ITEM | K61: Operações de Redes e SI | L61: Gustavo Roberto Brambila <gbrambila@oi.net.br> | M61: Thiago Vasconcelos <thiago.vasconcelos@oi.net.br> | N61: Priscila Falco Tonidandel <priscila@oi.net.br> | O61: -
B62: Core network O&M​ | C62: Integração de elementos de pré-pago e IN​ | D62: De acordo com as regras e parâmetros atuais, utilizando os recursos, sistemas, plataformas atuais, a Oi deverá: - Executar serviços de integração para elementos de rede para serviços de pré-pago e IN, de acordo com as necessidades das Compradoras. | E62: Depende da área Oi | F62: Operações de Rede e SI | G62: Priscila Falco | H62: Operações de Rede e SI | I62: Tópicos foram substituídos por outros, enviados pela Priscilla Falco | J62: EXCLUIR ESTE ITEM | K62: Operações de Redes e SI | L62: Gustavo Roberto Brambila <gbrambila@oi.net.br> | M62: Thiago Vasconcelos <thiago.vasconcelos@oi.net.br> | N62: Priscila Falco Tonidandel <priscila@oi.net.br> | O62: -
B63: Core network O&M​ | C63: Campanha OTA​ | D63: De acordo com as regras e parâmetros atuais, utilizando os recursos, sistemas, plataformas atuais, a Oi deverá: - Manter links e conectividade para permitir execução de campanha OTA para atualização de diferentes EFs, tais como PPLMN, HPLMN, IMSI, SMSCAddr, FPLMN, CSP, SPN, pelas Compradoras | E63: Depende da área Oi | F63: Operações de Rede e SI | G63: Priscila Falco | H63: Operações de Rede e SI | I63: Tópicos foram substituídos por outros, enviados pela Priscilla Falco | J63: EXCLUIR ESTE ITEM | K63: Operações de Redes e SI | L63: Gustavo Roberto Brambila <gbrambila@oi.net.br> | M63: Thiago Vasconcelos <thiago.vasconcelos@oi.net.br> | N63: Priscila Falco Tonidandel <priscila@oi.net.br> | O63: -
B64: Core network O&M​ | C64: Campanha Device Manager​ | E64: Depende da área Oi | F64: Operações de Rede e SI | G64: Priscila Falco | H64: Operações de Rede e SI | I64: Tópicos foram substituídos por outros, enviados pela Priscilla Falco | J64: EXCLUIR ESTE ITEM | K64: Operações de Redes e SI | L64: Gustavo Roberto Brambila <gbrambila@oi.net.br> | M64: Thiago Vasconcelos <thiago.vasconcelos@oi.net.br> | N64: Priscila Falco Tonidandel <priscila@oi.net.br> | O64: -
B65: Core network O&M​ | C65: Integração DRA/DEA​ | D65: De acordo com as regras e parâmetros atuais, utilizando os recursos, sistemas, plataformas atuais, a Oi deverá: - Implantar e manter integração entre DEA e STP Oi com elementos equivalentes das Compradoras. | E65: Depende da área Oi | F65: Operações de Rede e SI | G65: Priscila Falco | H65: Operações de Rede e SI | I65: Tópicos foram substituídos por outros, enviados pela Priscilla Falco | J65: EXCLUIR ESTE ITEM | K65: Operações de Redes e SI | L65: Gustavo Roberto Brambila <gbrambila@oi.net.br> | M65: Thiago Vasconcelos <thiago.vasconcelos@oi.net.br> | N65: Priscila Falco Tonidandel <priscila@oi.net.br> | O65: -
B66: Core network O&M​ | C66: Ativação roaming ​ | D66: De acordo com as regras e parâmetros atuais, utilizando os recursos, sistemas, plataformas atuais, a Oi deverá: - Habilitar e manter o roaming de usuários Oi nas redes das Compradoras. | E66: EXCLUIR ESTE ITEM | F66: Sistemas TI | G66: Bruno Diehl | H66: TI | I66: [Bruno Diehl] - Não se aplica para ClientCo | J66: EXCLUIR ESTE ITEM | K66: Tecnologia | L66: Caio Marcio Gusmon <caio.gusmon@oi.net.br> | M66: Bruno Diehl <bruno.diehl@oi.net.br> | N66: - | O66: -
B67: Core network O&M​ | C67: Envio de bases de dados de clientes​ | D67: De acordo com as regras e parâmetros atuais, utilizando os recursos, sistemas, plataformas atuais, a Oi deverá: - Extrair e enviar dados de todos os clientes no AuC, HLR e HSS usando o ETL da Oi, de acordo com regras das Compradoras para conversão de serviços e campos específicos, de acordo com as necessidades das Compradoras. | E67: A Oi se disponibilizará a prover dados dos clientes da base adquirida na negociação, com prazos à serem acordados. | F67: Sistemas TI | G67: Bruno Diehl | H67: Sistemas TI | J67: CONCLUÍDO | K67: Tecnologia | L67: Caio Marcio Gusmon <caio.gusmon@oi.net.br> | M67: Bruno Diehl <bruno.diehl@oi.net.br> | N67: - | O67: -
B68: Core network O&M​ | C68: Suporte de plataformas​ | D68: De acordo com as regras e parâmetros atuais, utilizando os recursos, sistemas, plataformas atuais, a Oi deverá: - Suportar plataformas de rede e TI da Oi, integradas a plataformas correspondentes nas Compradoras. | E68: A Oi terá responsabilidade de manutenção das plataformas e suas apliçaões, mantendo os serviços, atendendo aos chamados de incidentes, possibilitando à operação e entrega de serviços. | F68: Sistemas TI | G68: Bruno Diehl | H68: Sistemas de TI | I68: Verificar impacto VTAL | J68: CONCLUÍDO | K68: Tecnologia | L68: Caio Marcio Gusmon <caio.gusmon@oi.net.br> | M68: Bruno Diehl <bruno.diehl@oi.net.br> | N68: - | O68: -
B69: Core network O&M​ | C69: Envio de chaves de segurança​ | D69: De acordo com as regras e parâmetros atuais, utilizando os recursos, sistemas, plataformas atuais, a Oi deverá: - Migrar chaves utilizadas para criptografar essas bases de dados (HSS/HLR/AuC), e das chaves OTA | E69: Depende da área Oi | F69: Operações de Rede e SI | G69: Priscila Falco | H69: Operações de Rede e SI// Infra e Operações de TI | I69: Tópicos foram substituídos por outros, enviados pela Priscilla Falco | J69: EXCLUIR ESTE ITEM | K69: Operações de Redes e SI | L69: Gustavo Roberto Brambila <gbrambila@oi.net.br> | M69: Thiago Vasconcelos <thiago.vasconcelos@oi.net.br> | N69: Priscila Falco Tonidandel <priscila@oi.net.br> | O69: -
B70: Core network O&M​ | C70: Envio de templates de perfis de SIM cards​ | D70: De acordo com as regras e parâmetros atuais, utilizando os recursos, sistemas, plataformas atuais, a Oi deverá: - Migrar templates dos perfis da Oi para a plataforma OTA das Compradoras. | E70: Depende da área Oi | F70: Operações de Rede e SI | G70: Priscila Falco | H70: N/A | I70: Tópicos foram substituídos por outros, enviados pela Priscilla Falco | J70: EXCLUIR ESTE ITEM | K70: Operações de Redes e SI | L70: Gustavo Roberto Brambila <gbrambila@oi.net.br> | M70: Thiago Vasconcelos <thiago.vasconcelos@oi.net.br> | N70: Priscila Falco Tonidandel <priscila@oi.net.br> | O70: -
B71: Core network O&M​ | C71: Acesso a sistemas para provisionamento​ | D71: De acordo com as regras e parâmetros atuais, utilizando os recursos, sistemas, plataformas atuais, a Oi deverá: - Viabilizar o acesso de sistemas das Compradoras ao provisionamento Oi para desativação de clientes nas bases (HSS+HLR+AuC), e a sistema de portabilidade (FNR) para registro de números portados para as Compradoras. | E71: EXCLUIR ESTE ITEM | F71: Sistemas TI | G71: Bruno Diehl | H71: Sistemas TI | I71: [Bruno Diehl] - O tópico foi excluído porque o tema está contemplado em outros tópicos: Gestão de Problemas, Gerenciamento de mudanças (GMUD´s) e Gestão de Capacidade e ativos | J71: EXCLUIR ESTE ITEM | K71: Tecnologia | L71: Caio Marcio Gusmon <caio.gusmon@oi.net.br> | M71: Bruno Diehl <bruno.diehl@oi.net.br> | N71: - | O71: -
B72: Core network O&M​ | C72: Suporte, acesso e integração de plataformas de rede e TI​ | D72: De acordo com as regras e parâmetros atuais, utilizando os recursos, sistemas, plataformas atuais, a Oi deverá: - Suportar, prover acesso remoto e realizar atividades de integração entre plataformas de rede e TI da Oi e das Compradoras: - HSS, HLR, AuC, MME, eDNS, DRA (SLF), DEA, STP (FNR), S/P-GW, S/GGSN, OTA, FDA, USSD, MMS, SMSC, Anti-Spam, PCRF, CTF, Plataforma de BigData, Device Manager, Service Manager, WAP, EIR, GMLC/SMLC, Voice Mail, IVR, Ring Back Tone, SIM Browsing, Provisioning, Inter-AS, IN. | E72: Depende da área Oi | F72: Operações de Rede e SI | G72: Priscila Falco | H72: Operações de Rede e SI// Infra e Operações de TI// Sistemas TI// Arquitetura TI | I72: Tópicos foram substituídos por outros, enviados pela Priscilla Falco | J72: EXCLUIR ESTE ITEM | K72: Operações de Redes e SI | L72: Gustavo Roberto Brambila <gbrambila@oi.net.br> | M72: Thiago Vasconcelos <thiago.vasconcelos@oi.net.br> | N72: Priscila Falco Tonidandel <priscila@oi.net.br> | O72: -
B73: Core network O&M​ | C73: Configuração de dialling plan, B-number, tradutor de dígitos, etc.​ | D73: De acordo com as regras e parâmetros atuais, utilizando os recursos, sistemas, plataformas atuais, a Oi deverá: - Configurar árvore de análise de dígitos para definição de encaminhamento para cenários de chamadas de voz. | E73: Depende da área Oi | F73: Operações de Rede e SI | G73: Priscila Falco | H73: Operações de Rede e SI// Infra e Operações de TI// Sistemas TI | I73: Tópicos foram substituídos por outros, enviados pela Priscilla Falco | J73: EXCLUIR ESTE ITEM | K73: Operações de Redes e SI | L73: Gustavo Roberto Brambila <gbrambila@oi.net.br> | M73: Thiago Vasconcelos <thiago.vasconcelos@oi.net.br> | N73: Priscila Falco Tonidandel <priscila@oi.net.br> | O73: -
B74: Core network O&M​ | C74: Configuração de roteamento de sinalização de rede (ex. SS7, Diamenter, SIP, etc.)​ | D74: De acordo com as regras e parâmetros atuais, utilizando os recursos, sistemas, plataformas atuais, a Oi deverá: - Executar serviços de configuração para roteamento de sinalização de rede (ex. SS7, Diamenter, SIP, etc.), de acordo com as necessidades das Compradoras. | E74: Depende da área Oi | F74: Operações de Rede e SI | G74: Priscila Falco | H74: Operações de Rede e SI | I74: Tópicos foram substituídos por outros, enviados pela Priscilla Falco | J74: EXCLUIR ESTE ITEM | K74: Operações de Redes e SI | L74: Gustavo Roberto Brambila <gbrambila@oi.net.br> | M74: Thiago Vasconcelos <thiago.vasconcelos@oi.net.br> | N74: Priscila Falco Tonidandel <priscila@oi.net.br> | O74: -
B75: Core network O&M​ | C75: Configuração de links e associações para sinalização​ | D75: De acordo com as regras e parâmetros atuais, utilizando os recursos, sistemas, plataformas atuais, a Oi deverá: - Executar serviços de configuração de links e associações necessárias para sinalização SS7, Diameter, etc, de acordo com as necessidades das Compradoras. | E75: Depende da área Oi | F75: Operações de Rede e SI | G75: Priscila Falco | H75: Operações de Rede e SI | I75: Tópicos foram substituídos por outros, enviados pela Priscilla Falco | J75: EXCLUIR ESTE ITEM | K75: Operações de Redes e SI | L75: Gustavo Roberto Brambila <gbrambila@oi.net.br> | M75: Thiago Vasconcelos <thiago.vasconcelos@oi.net.br> | N75: Priscila Falco Tonidandel <priscila@oi.net.br> | O75: -
B76: Core network O&M​ | C76: Rotas de voz (ex. TDM, SIP, etc.)​ | D76: De acordo com as regras e parâmetros atuais, utilizando os recursos, sistemas, plataformas atuais, a Oi deverá: - Executar serviços de configuração de rotas de voz (ex. TDM, SIP, etc.), de acordo com as necessidades das Compradoras. | E76: Depende da área Oi | F76: Operações de Rede e SI | G76: Priscila Falco | H76: Operações de Rede e SI | I76: Tópicos foram substituídos por outros, enviados pela Priscilla Falco | J76: EXCLUIR ESTE ITEM | K76: Operações de Redes e SI | L76: Gustavo Roberto Brambila <gbrambila@oi.net.br> | M76: Thiago Vasconcelos <thiago.vasconcelos@oi.net.br> | N76: Priscila Falco Tonidandel <priscila@oi.net.br> | O76: -
B77: Core network O&M​ | C77: Definição profile de usuário para as redes 4G, 3G e 2G.​ | D77: De acordo com as regras e parâmetros atuais, utilizando os recursos, sistemas, plataformas atuais, a Oi deverá: - Executar serviços de configuração de profile de usuário para as redes 4G, 3G e 2G (ex. HLR, HSS, PCRF, etc.), de acordo com as necessidades das Compradoras. | E77: Depende da área Oi | F77: Operações de Rede e SI | G77: Priscila Falco | H77: Operações de Rede e SI | I77: Tópicos foram substituídos por outros, enviados pela Priscilla Falco | J77: EXCLUIR ESTE ITEM | K77: Operações de Redes e SI | L77: Gustavo Roberto Brambila <gbrambila@oi.net.br> | M77: Thiago Vasconcelos <thiago.vasconcelos@oi.net.br> | N77: Priscila Falco Tonidandel <priscila@oi.net.br> | O77: -
B78: Core network O&M​ | C78: Serviços de configuração de parâmetros e serviços suplementares em base de dados de usuário (HLR, HSS, etc.)​ | D78: De acordo com as regras e parâmetros atuais, utilizando os recursos, sistemas, plataformas atuais, a Oi deverá: - Executar serviços de configuração de parâmetros e serviços suplementares em base de dados de usuário (HLR, HSS, etc.), de acordo com as necessidades das Compradoras. | E78: Depende da área Oi | F78: Operações de Rede e SI | G78: Priscila Falco | H78: Operações de Rede e SI | I78: Tópicos foram substituídos por outros, enviados pela Priscilla Falco | J78: EXCLUIR ESTE ITEM | K78: Operações de Redes e SI | L78: Gustavo Roberto Brambila <gbrambila@oi.net.br> | M78: Thiago Vasconcelos <thiago.vasconcelos@oi.net.br> | N78: Priscila Falco Tonidandel <priscila@oi.net.br> | O78: -
B79: Core network O&M​ | C79: Parametrização e serviços suplementares​ | D79: De acordo com as regras e parâmetros atuais, utilizando os recursos, sistemas, plataformas atuais, a Oi deverá: Executar serviços de configuração de parâmetros e serviços suplementares em servidores de aplicação (ex. MMTel) e base de dados de usuários (ex. HLR, HSS, etc.), de acordo com as necessidades das Compradoras. | E79: Depende da área Oi | F79: Operações de Rede e SI | G79: Priscila Falco | H79: Operações de Rede e SI | I79: Tópicos foram substituídos por outros, enviados pela Priscilla Falco | J79: EXCLUIR ESTE ITEM | K79: Operações de Redes e SI | L79: Gustavo Roberto Brambila <gbrambila@oi.net.br> | M79: Thiago Vasconcelos <thiago.vasconcelos@oi.net.br> | N79: Priscila Falco Tonidandel <priscila@oi.net.br> | O79: -
B80: Core network O&M​ | C80: Configuração ENUM/DNS​ | E80: Depende da área Oi | F80: Operações de Rede e SI | G80: Priscila Falco | H80: Operações de Rede e SI | I80: Tópicos foram substituídos por outros, enviados pela Priscilla Falco | J80: EXCLUIR ESTE ITEM | K80: Operações de Redes e SI | L80: Gustavo Roberto Brambila <gbrambila@oi.net.br> | M80: Thiago Vasconcelos <thiago.vasconcelos@oi.net.br> | N80: Priscila Falco Tonidandel <priscila@oi.net.br> | O80: -
B81: Core network O&M​ | C81: Roaming​ | D81: De acordo com as regras e parâmetros atuais, utilizando os recursos, sistemas, plataformas atuais, a Oi deverá: - Executar serviços de configuração em elementos de core de voz (CS e IMS) para roaming, de acordo com as necessidades das Compradoras. | E81: EXCLUIR ESTE ITEM | F81: Sistemas TI | G81: Bruno Diehl | H81: TI | I81: [Bruno Diehl] - Não se aplica para ClientCo | J81: EXCLUIR ESTE ITEM | K81: Tecnologia | L81: Caio Marcio Gusmon <caio.gusmon@oi.net.br> | M81: Bruno Diehl <bruno.diehl@oi.net.br> | N81: - | O81: -
B82: Core network O&M​ | C82: Integração de sinalização​ | D82: De acordo com as regras e parâmetros atuais, utilizando os recursos, sistemas, plataformas atuais, a Oi deverá: - Executar serviços de integração para rede SS7/Sigtran, Diameter, etc, de acordo com as necessidades das Compradoras. | E82: Depende da área Oi | F82: Operações de Rede e SI | G82: Priscila Falco | H82: Operações de Rede e SI | I82: Tópicos foram substituídos por outros, enviados pela Priscilla Falco | J82: EXCLUIR ESTE ITEM | K82: Operações de Redes e SI | L82: Gustavo Roberto Brambila <gbrambila@oi.net.br> | M82: Thiago Vasconcelos <thiago.vasconcelos@oi.net.br> | N82: Priscila Falco Tonidandel <priscila@oi.net.br> | O82: -
B83: Core network O&M​ | C83: Integração de rotas de voz​ | D83: De acordo com as regras e parâmetros atuais, utilizando os recursos, sistemas, plataformas atuais, a Oi deverá: - Executar serviços de integração para rotas de voz baseadas em ISUP, BICC, SIP, etc, de acordo com as necessidades das Compradoras. | E83: Depende da área Oi | F83: Operações de Rede e SI | G83: Priscila Falco | H83: Operações de Rede e SI | I83: Tópicos foram substituídos por outros, enviados pela Priscilla Falco | J83: EXCLUIR ESTE ITEM | K83: Operações de Redes e SI | L83: Gustavo Roberto Brambila <gbrambila@oi.net.br> | M83: Thiago Vasconcelos <thiago.vasconcelos@oi.net.br> | N83: Priscila Falco Tonidandel <priscila@oi.net.br> | O83: -
B84: Core network O&M​ | C84: Integração de elementos de rede do core de voz.​ | D84: De acordo com as regras e parâmetros atuais, utilizando os recursos, sistemas, plataformas atuais, a Oi deverá: - Executar serviços de integração entre elementos de rede do core de voz, de acordo com as necessidades das Compradoras. | E84: Depende da área Oi | F84: Operações de Rede e SI | G84: Priscila Falco | H84: Operações de Rede e SI | I84: Tópicos foram substituídos por outros, enviados pela Priscilla Falco | J84: EXCLUIR ESTE ITEM | K84: Operações de Redes e SI | L84: Gustavo Roberto Brambila <gbrambila@oi.net.br> | M84: Thiago Vasconcelos <thiago.vasconcelos@oi.net.br> | N84: Priscila Falco Tonidandel <priscila@oi.net.br> | O84: -
B85: Core network O&M​ | C85: Homologação de sinalização​ | D85: De acordo com as regras e parâmetros atuais, utilizando os recursos, sistemas, plataformas atuais, a Oi deverá: - Executar serviços de homologação e testes para cenários envolvendo sinalização SS7, SIP, Diamenter, etc., de acordo com as necessidades das Compradoras. | E85: Depende da área Oi | F85: Operações de Rede e SI | G85: Priscila Falco | H85: Operações de Rede e SI | I85: Tópicos foram substituídos por outros, enviados pela Priscilla Falco | J85: EXCLUIR ESTE ITEM | K85: Operações de Redes e SI | L85: Gustavo Roberto Brambila <gbrambila@oi.net.br> | M85: Thiago Vasconcelos <thiago.vasconcelos@oi.net.br> | N85: Priscila Falco Tonidandel <priscila@oi.net.br> | O85: -
B86: Core network O&M​ | C86: Homologação de roaming​ | D86: De acordo com as regras e parâmetros atuais, utilizando os recursos, sistemas, plataformas atuais, a Oi deverá: - Executar serviços de homologação e testes para validação de novos acordos de roaming e troubleshooting, de acordo com as necessidades das Compradoras. | E86: EXCLUIR ESTE ITEM | F86: Sistemas TI | G86: Bruno Diehl | H86: TI | I86: [Bruno Diehl] - Não se aplica para ClientCo | J86: EXCLUIR ESTE ITEM | K86: Tecnologia | L86: Caio Marcio Gusmon <caio.gusmon@oi.net.br> | M86: Bruno Diehl <bruno.diehl@oi.net.br> | N86: - | O86: -
B87: Core network O&M​ | C87: Integração dos elementos​ | D87: De acordo com as regras e parâmetros atuais, utilizando os recursos, sistemas, plataformas atuais, a Oi deverá: - Integrar todos os elementos do Core de Voz, Dados, Sinalização e Plataformas SVA da OI com os elementos Core de Voz, Dados e Plataformas de SVA das Compradoras, de acordo com as necessidades das Compradoras. | E87: Depende da área Oi | F87: Operações de Rede e SI | G87: Priscila Falco | H87: Operações de Rede e SI | I87: Tópicos foram substituídos por outros, enviados pela Priscilla Falco | J87: EXCLUIR ESTE ITEM | K87: Operações de Redes e SI | L87: Gustavo Roberto Brambila <gbrambila@oi.net.br> | M87: Thiago Vasconcelos <thiago.vasconcelos@oi.net.br> | N87: Priscila Falco Tonidandel <priscila@oi.net.br> | O87: -
B88: Core network O&M​ | C88: Configuração dos elementos​ | D88: De acordo com as regras e parâmetros atuais, utilizando os recursos, sistemas, plataformas atuais, a Oi deverá: - Configurar todos os elementos do Core de Voz, Dados, Sinalização e Plataformas SVA da OI para permitir o registro dos clientes “OI” na Rede das Compradoras, de acordo com as necessidades das Compradoras. | E88: Depende da área Oi | F88: Operações de Rede e SI | G88: Priscila Falco | H88: Operações de Rede e SI | I88: Tópicos foram substituídos por outros, enviados pela Priscilla Falco | J88: EXCLUIR ESTE ITEM | K88: Operações de Redes e SI | L88: Gustavo Roberto Brambila <gbrambila@oi.net.br> | M88: Thiago Vasconcelos <thiago.vasconcelos@oi.net.br> | N88: Priscila Falco Tonidandel <priscila@oi.net.br> | O88: -
B89: Core network O&M​ | C89: Configuração dos elementos​ | D89: De acordo com as regras e parâmetros atuais, utilizando os recursos, sistemas, plataformas atuais, a Oi deverá: - Configurar todos os elementos do Core de Voz, Dados, Sinalização e Plataformas SVA da OI para permitir o registro dos clientes da(s) compradoras na Rede da OI, de acordo com as necessidades das Compradoras. | E89: Depende da área Oi | F89: Operações de Rede e SI | G89: Priscila Falco | H89: Operações de Rede e SI | I89: Tópicos foram substituídos por outros, enviados pela Priscilla Falco | J89: EXCLUIR ESTE ITEM | K89: Operações de Redes e SI | L89: Gustavo Roberto Brambila <gbrambila@oi.net.br> | M89: Thiago Vasconcelos <thiago.vasconcelos@oi.net.br> | N89: Priscila Falco Tonidandel <priscila@oi.net.br> | O89: -
B90: Core network O&M​ | C90: Transferência Base de Dados​ | D90: De acordo com as regras e parâmetros atuais, utilizando os recursos, sistemas, plataformas atuais, a Oi deverá: - Transferir todos os dados armazenados nas Base de Dados da OI para as Base de Dados das Compradoras, de acordo com as necessidades das Compradoras. | E90: Depende da área Oi | F90: Operações de Rede e SI | G90: Priscila Falco | H90: Operações de Rede e SI | I90: Tópicos foram substituídos por outros, enviados pela Priscilla Falco | J90: EXCLUIR ESTE ITEM | K90: Operações de Redes e SI | L90: Gustavo Roberto Brambila <gbrambila@oi.net.br> | M90: Thiago Vasconcelos <thiago.vasconcelos@oi.net.br> | N90: Priscila Falco Tonidandel <priscila@oi.net.br> | O90: -
B91: Core network O&M​ | C91: Suporte durante a migração​ | D91: De acordo com as regras e parâmetros atuais, utilizando os recursos, sistemas, plataformas atuais, a Oi deverá: - Prover suporte N1, N2 e N3 durante toda fase de migração, integração e capacitação dos elementos do Core de Voz, Dados e Plataformas SVA, de acordo com as necessidades das Compradoras | E91: Depende da área Oi | F91: Operações de Rede e SI | G91: Priscila Falco | H91: Operações de Rede e SI// Infra e Operações de TI// Sistemas TI | I91: Tópicos foram substituídos por outros, enviados pela Priscilla Falco | J91: EXCLUIR ESTE ITEM | K91: Operações de Redes e SI | L91: Gustavo Roberto Brambila <gbrambila@oi.net.br> | M91: Thiago Vasconcelos <thiago.vasconcelos@oi.net.br> | N91: Priscila Falco Tonidandel <priscila@oi.net.br> | O91: -
B92: Core network O&M​ | C92: Campanhas de atualização​ | D92: De acordo com as regras e parâmetros atuais, utilizando os recursos, sistemas, plataformas atuais, a Oi deverá: - Realizar campanhas de atualização dos Simcards (via Over-the-Air) até que toda base de clientes esteja atualizada, de acordo com as necessidades das Compradoras. | E92: Depende da área Oi | F92: Operações de Rede e SI | G92: Priscila Falco | H92: Operações de Rede e SI | I92: Tópicos foram substituídos por outros, enviados pela Priscilla Falco | J92: EXCLUIR ESTE ITEM | K92: Operações de Redes e SI | L92: Gustavo Roberto Brambila <gbrambila@oi.net.br> | M92: Thiago Vasconcelos <thiago.vasconcelos@oi.net.br> | N92: Priscila Falco Tonidandel <priscila@oi.net.br> | O92: -
... B128: Access network O&M​ | C128: Suporte durante a migração​ | D128: -Equipe com profundo conhecimento técnico nos elementos de acesso móvel, que deve trabalhar de forma dedicada e exclusiva durante toda fase de migração, de acordo com as necessidades das Compradoras (incluindo FTEs do perímetro e aqueles fora do perímetro que sejam responsáveis pelo suporte a plataformas compartilhadas com demais empresas do Grupo Oi). | E128: A Oi se disponibilizará junto aos compradores, na construção da estratatégia e suporte à migração da base de clientes. | F128: Sistemas TI | G128: Bruno Diehl | H128: Operações de Rede e SI// Infra e Operações de TI// Sistemas TI | I128: Verificar impacto VTAL | J128: CONCLUÍDO | K128: Tecnologia | L128: Caio Marcio Gusmon <caio.gusmon@oi.net.br> | M128: Bruno Diehl <bruno.diehl@oi.net.br> | N128: - | O128: -
B129: Access network O&M​ | C129: Operação e Manutenção​ | E129: A Oi manterá o processo de manutenção dos sistemas, tratamento de bugs, incidentes, garantindo o funcionamento dos produtos e serviços. | F129: Sistemas TI | G129: Bruno Diehl | I129: No Tsa da móvel só tinhamos a parte de operações de Redes, dupliquei para incluir a parte de TI. | J129: CONCLUÍDO | K129: Tecnologia | L129: Caio Marcio Gusmon <caio.gusmon@oi.net.br> | M129: Bruno Diehl <bruno.diehl@oi.net.br> | N129: - | O129: -
B130: Access network O&M​ | C130: Operação e Manutenção​ | D130: De acordo com as regras e parâmetros atuais, utilizando os recursos, sistemas, plataformas atuais, a Oi deverá: - Operar e realizar manutenção corretiva para a Rede de Acesso Móvel em eventos especiais; - Suportar, direcionar e orientar as equipes de manutenção de campo (FLM) nas situações de manutenção corretiva e preventiva; - Apoiar as equipes de Supervisão de Rede, analisando falhas críticas ou complexas, verificando possíveis correlações com outras ocorrências; - Avaliar as topologias existentes, analisando possíveis melhorias com foco na melhoria da performance da Rede de Acesso Móvel; - Mapear e identificar possíveis problemas de Rede que necessitem de ampliações de conexões, evitando limitações ou lentidão nos serviços prestados; - Realizar serviço de Suporte N3 relacionado aos elementos da Rede de Acesso Móvel (ERB), BSC, RNC em âmbito Nacional em regime 24x7; - Gerar reports diários relacionados aos problemas e indicadores de serviço que envolvam os elementos da Rede de Acesso Móvel; - Garantir (através do Contrato) HC suficientes para a Operação e Manutenção da Rede de Acesso Móvel em regime 24x7. Estes HCs devem ser alterados conforme ocorrerem as migrações das ERB, bem como clientes para a base das Compradoras. - Analisar, controlar, liberar e negociar as atividades programadas (GMUD) nos elementos concentradores da Rede de Acesso Móvel, de acordo com as afetações envolvidas, junto às áreas fornecedoras (interna e externas); - Acompanhar e validar a atualização de correção de produto (software) e aplicação de updates e correções nos elementos concentradores da Rede de Acesso Móvel; - Gerenciar os contratos da área (suporte e recursos), bem como qualificar, mensurar e avaliar os serviços fornecidos; - Acompanhar a validação em laboratório das soluções de falhas a serem implementadas nos elementos da Rede de Acesso Móvel em produção; - Realizar a tratativas e gestão fim a fim para os eventos com impacto de serviço ao cliente, e também a cobrança de prazo as áreas responsáveis; - Realizar anualmente testes de contingência, a fim de garantir a integridade da rede, e proteção de serviço; - Garantir triagem e diagnóstico assertivo, buscar sempre que possível a solução remota, sempre realizar a retenção de eventos quando uma causa raiz já estiver em tratativas pelas equipes de campo; e - Acompanhar os casos reincidentes, e garantir que sejam tratados com solução em definitivo na primeira tratativa. | E130: Depende da área Oi | F130: Operações de Rede e SI | G130: Priscila Falco | H130: Operações de Rede e SI// Infra e Operações de TI | I130: Tópicos foram substituídos por outros, enviados pela Priscilla Falco | J130: EXCLUIR ESTE ITEM | K130: Operações de Redes e SI | L130: Gustavo Roberto Brambila <gbrambila@oi.net.br> | M130: Thiago Vasconcelos <thiago.vasconcelos@oi.net.br> | N130: Priscila Falco Tonidandel <priscila@oi.net.br> | O130: -
B131: Application and data management​ | C131: Gestão da portabilidade (interna e externa) ​ | D131: De acordo com as regras e parâmetros atuais, utilizando os recursos, sistemas, plataformas atuais, a Oi deverá: - Direcionar para as mesas de retenção; - Executar todas as atividades para disponibilizar e efetivar os port ins e port outs; e - Resolver os problemas encontrados durante o processamento. | E131: De acordo com as regras e parâmetros atuais, utilizando os recursos, sistemas, plataformas atuais, a Oi deverá: - Direcionar para as mesas de retenção; - Executar todas as atividades para disponibilizar e efetivar os port ins e port outs; e - Resolver os problemas encontrados durante o processamento. | F131: Sistemas TI | G131: Bruno Diehl | H131: Infra e Operações de TI | J131: CONCLUÍDO | K131: Tecnologia | L131: Caio Marcio Gusmon <caio.gusmon@oi.net.br> | M131: Bruno Diehl <bruno.diehl@oi.net.br> | N131: - | O131: -
B132: Application and data management​ | C132: Disponibilidade de sistemas​ | D132: De acordo com as regras e parâmetros atuais, utilizando os recursos, sistemas, plataformas atuais, a Oi deverá: - Através das atividades de monitoramento, gestão de incidentes, gestão de problemas, gestão de mudanças, gestão de capacidade, gestão de vulnerabilidades e gestão de continuidade, manter o nível de disponibilidade dos sistemas de TI na taxa de sucesso definida; e - Gerar os reports executivos e operacionais associados | E132: EXCLUIR ESTE ITEM | F132: Sistemas TI | G132: Bruno Diehl | H132: Infra e Operações de TI | I132: [Bruno Diehl] - Tema excluído porque está contemplado no tópico "Gestão de Problemas". | J132: EXCLUIR ESTE ITEM | K132: Tecnologia | L132: Caio Marcio Gusmon <caio.gusmon@oi.net.br> | M132: Bruno Diehl <bruno.diehl@oi.net.br> | N132: - | O132: -
B133: Application and data management​ | C133: Gestão de incidentes​ | D133: De acordo com as regras e parâmetros atuais, utilizando os recursos, sistemas, plataformas atuais, a Oi deverá: - Restaurar o serviço o mais rápido possível e minimizar o impacto negativo sobre as operações de negócios, garantindo os níveis acordados de qualidade dos serviços. - Monitorar, identificar, registrar e comunicar incidentes. - Solucionar e fechar o incidente | E133: De acordo com as regras e parâmetros atuais, utilizando os recursos, sistemas, plataformas atuais, a Oi deverá: - Restaurar o serviço o mais rápido possível e minimizar o impacto negativo sobre as operações de negócios, garantindo os níveis acordados de qualidade dos serviços. - Monitorar, identificar, registrar e comunicar incidentes. - Solucionar e fechar o incidente | F133: Sistemas TI | G133: Bruno Diehl | H133: Infra e Operações de TI | J133: CONCLUÍDO | K133: Tecnologia | L133: Caio Marcio Gusmon <caio.gusmon@oi.net.br> | M133: Bruno Diehl <bruno.diehl@oi.net.br> | N133: - | O133: -
B134: Application and data management​ | C134: Gestão de problemas​ | D134: De acordo com as regras e parâmetros atuais, utilizando os recursos, sistemas, plataformas atuais, a Oi deverá: - Acompanhar o ciclo de vida de todos os problemas: - Investigação e diagnóstico da causa raiz do problema: - Resposta a demanda dos problemas - Execução de análise N1 - Direcionamento do problema para níveis mais detalhados de análise (N2 e N3). | E134: De acordo com as regras e parâmetros atuais, utilizando os recursos, sistemas, plataformas atuais, a Oi deverá: - Acompanhar o ciclo de vida de todos os problemas: - Investigação e diagnóstico da causa raiz do problema: - Resposta a demanda dos problemas - Execução de análise N1 - Direcionamento do problema para níveis mais detalhados de análise (N2 e N3). | F134: Sistemas TI | G134: Bruno Diehl | H134: Infra e Operações de TI | J134: CONCLUÍDO | K134: Tecnologia | L134: Caio Marcio Gusmon <caio.gusmon@oi.net.br> | M134: Bruno Diehl <bruno.diehl@oi.net.br> | N134: - | O134: -
B135: Application and data management​ | C135: Gerenciamento de mudanças (GMUD´s) ​ | D135: De acordo com as regras e parâmetros atuais, utilizando os recursos, sistemas, plataformas atuais, a Oi deverá: - Executar as mudanças em ambiente produtivo com o mínimo de riscos e interrupção para os serviços de TI. - Registrar, Agendar e Planejar Mudança. - Validar Planejamento da Mudança. - Autorizar Implantação da Mudança - Implantar Mudança - Realizar Revisão Pós Mudança - Gerenciar Mudança Emergencial - Gerenciar Mudança Padrão | E135: De acordo com as regras e parâmetros atuais, utilizando os recursos, sistemas, plataformas atuais, a Oi deverá: - Executar as mudanças em ambiente produtivo com o mínimo de riscos e interrupção para os serviços de TI. - Registrar, Agendar e Planejar Mudança. - Validar Planejamento da Mudança. - Autorizar Implantação da Mudança - Implantar Mudança - Realizar Revisão Pós Mudança - Gerenciar Mudança Emergencial - Gerenciar Mudança Padrão | F135: Sistemas TI | G135: Bruno Diehl | H135: Infra e Operações de TI | J135: CONCLUÍDO | K135: Tecnologia | L135: Caio Marcio Gusmon <caio.gusmon@oi.net.br> | M135: Bruno Diehl <bruno.diehl@oi.net.br> | N135: - | O135: -
B136: Application and data management​ | C136: Gestão de capacidade e manutenção de ativos​ de TI | D136: De acordo com as regras e parâmetros atuais, utilizando os recursos, sistemas, plataformas atuais, a Oi deverá: - Executar ajustes de hardware e reposições necessárias (manutenção pró-ativa e reativa) para se manter os níveis de disponibilidade e desempenho acordados. - Gerir contratos e licenciamentos existentes no parque de TI - Compliance de ativos | E136: De acordo com as regras e parâmetros atuais, utilizando os recursos, sistemas, plataformas atuais, a Oi deverá: - Executar ajustes de hardware e reposições necessárias (manutenção pró-ativa e reativa) para se manter os níveis de disponibilidade e desempenho acordados. - Gerir contratos e licenciamentos existentes no parque de TI - Compliance de ativos | F136: Sistemas TI | G136: Bruno Diehl | H136: Infra e Operações de TI | J136: CONCLUÍDO | K136: Tecnologia | L136: Caio Marcio Gusmon <caio.gusmon@oi.net.br> | M136: Bruno Diehl <bruno.diehl@oi.net.br> | N136: - | O136: -
...

Sheet Anexo A - TODOS OS SERVIÇOS
B2: Nome da VP | C2: Resumo dos serviços descritos no TSA. | D2: Topicos | E2: Texto Anexo A (ClientCo) | F2: Área responsável pelo Report | G2: Pessoa responsável pelo Report | H2: Áreas impactadas | I2: Anotações | J2: Status Anexo A | K2: N1 | L2: N2 | M2: N3 | N2: N4/ Consultor
B3: Auditoria e GRC | C3: Bill-to-cash​ | D3: Riscos e Controles | E3: - Revisão, atualização e teste de controles do Ambiente de Controles Internos da Companhia que permeiam todos os processos; - Gestão das Alçadas da Companhia que permeiam as principais atividades de aprovação; - Avaliação de Riscos conforme demanda das áreas; - Gestão dos Riscos Corporativos; - Gestão dos documentos da Companhia; - GCN que podem envolver incidentes/crises que impactam o serviço da Fibra. | F3: Controles Internos | G3: Kamila de Vasconcelos | J3: CONCLUÍDO | K3: Duilio De Novaes Alves <duilio.alves@oi.net.br> | L3: Duilio De Novaes Alves <duilio.alves@oi.net.br> | M3: Kamila De Vasconcelos Vieira <kamila.vieira@oi.net.br> | N3: -
B4: Auditoria e GRC | C4: Bill-to-cash​ | D4: Conformidade e Sustentabilidade | E4: - Gestão do canal e atendimento às solicitações de direitos previstos na LGPD por parte de titulares de dados pessoais; - Avaliação e adequação de contratos e editais, sob o aspecto de privacidade e proteção de dados pessoais, com fornecedores, parceiros e clientes (empresariais); - Manutenção do registro de operações de tratamento de dados pessoais, na forma do art. 37 da LGPD; - Identificação e registro de transferências internacionais de dados pessoais na forma do art. 33 da LGPD; - Identificação, avaliação e tratamento de riscos de privacidade em processos e projetos da Companhia; - Gestão, tratamento e comunicação - sob demanda - de eventuais incidentes de segurança que envolvam dados pessoais; - Resposta à ofícios e requerimentos de autoridades públicas, relacionados à privacidade; - Gestão do canal de denúncias e apuração de relatos; - Avaliação e adequação da cláusula de Compliance em contratos e editais; - Realização de análise de integridade de terceiros e colaboradores; - Realização de testes detectivos de conflitos de interesse; pagamentos à agentes públicos; doações; Brindes e Presentes e etc; - Resposta à Due Diligence de Terceiros, Parceiros; Investidores e Clientes; - Realização de processos de Partes Relacionadas; Acompanhamento de relacionamento com países em lista de sanções internacionais. | F4: Controles Internos | G4: Kamila de Vasconcelos | J4: CONCLUÍDO | K4: Duilio De Novaes Alves <duilio.alves@oi.net.br> | L4: Duilio De Novaes Alves <duilio.alves@oi.net.br> | M4: Kamila De Vasconcelos Vieira <kamila.vieira@oi.net.br> | N4: -
B5: Auditoria e GRC | C5: Bill-to-cash​ | D5: Auditoria Interna | E5: - Apuração de casos fraude; - Auditoria de sistemas e processos que permeiam toda a Cia de acordo com o plano aprovado; - Acompanhamento e “reteste” de ações corretivas; - Monitoramento de fraude em processos críticos. | F5: Controles Internos | G5: Kamila de Vasconcelos | J5: CONCLUÍDO | K5: Duilio De Novaes Alves <duilio.alves@oi.net.br> | L5: Duilio De Novaes Alves <duilio.alves@oi.net.br> | M5: Kamila De Vasconcelos Vieira <kamila.vieira@oi.net.br> | N5: -
B6: Finanças e Relações com investidores | C6: Bill-to-cash​ | D6: Execução de ciclos de Billings​ | E6: - A Oi deverá executar o processo de faturamento de terminais fibra, mantendo os sistemas, regras e processos atuais, até a migração total desses clientes. - Execução de todos os ciclos de billings (majoritários e minoritários) em todos os sistemas de faturamento existentes no parque de TI. - Resolução dos problemas encontrados durante o processamento. | F6: Faturamento | G6: Monica | H6: Faturamento | J6: CONCLUÍDO | K6: Cristiane Barretto Sales <cristiane.barretto@oi.net.br> | L6: Bruno Macedo Soares <bmacedo@oi.net.br> | M6: Monica Sant Anna Paetzoldt <monica.paetzoldt@oi.net.br> | N6: -
B7: Finanças e Relações com investidores | C7: Bill-to-cash​ | D7: Tarifação de chamadas, dados e eventos ​ | E7: - Realização do processo de Tarifação de Voz, SVA e 0500 mantendo os sistemas, regras, processos e produtos e ofertas atuais, até a migração total desses clientes. - Resolução dos problemas encontrados durante o processamento. | F7: Tráfego | G7: Marcus Vinícius | H7: Faturamento// Tarifação e Repasse | J7: CONCLUÍDO | K7: Cristiane Barretto Sales <cristiane.barretto@oi.net.br> | L7: Bruno Macedo Soares <bmacedo@oi.net.br> | M7: Altevo Carlos De Sa Volotao <altevo.volotao@oi.net.br> | N7: Marcus Vinicius Miguel De Oliveira <marcus.oliveira@oi.net.br>
B8: Finanças e Relações com investidores | C8: Bill-to-cash​ | D8: Emissão de termos de quitação​ | E8: - Emissão do termo de quitação referentes aos pagamentos das últimas faturas dos clientes fibra. - Resolução dos problemas encontrados durante o processamento. - Todas as pendências de emissão dos termos de quitação anteriores a data do fechamento do contrato deverão ser regularizadas. | F8: Faturamento | G8: Monica | H8: Fatutamento/ Atendimento | J8: CONCLUÍDO | K8: Cristiane Barretto Sales <cristiane.barretto@oi.net.br> | L8: Bruno Macedo Soares <bmacedo@oi.net.br> | M8: Monica Sant Anna Paetzoldt <monica.paetzoldt@oi.net.br> | N8: -
B9: Finanças e Relações com investidores | C9: Bill-to-cash​ | D9: Validação do billings gerados - consistência, qualidade e confiabilidade ​ | E9: - A Oi irá executar o processo de validação prévia de faturas de terminais fibra, mantendo os sistemas, regras e processos atuais, até a migração total desses clientes. - Corrigir e reportar o tratamento adotado em caso de desvios identificados mantendo os sistemas, regras, processos e performance atuais, até a migração total desses clientes. -Executar as validações de consistência sobre o ciclo de billing executado. | F9: Faturamento | G9: Monica | H9: Faturamento | J9: CONCLUÍDO | K9: Cristiane Barretto Sales <cristiane.barretto@oi.net.br> | L9: Bruno Macedo Soares <bmacedo@oi.net.br> | M9: Monica Sant Anna Paetzoldt <monica.paetzoldt@oi.net.br> | N9: -
B10: Finanças e Relações com investidores | C10: Bill-to-cash​ | D10: Disponibilização de faturas online e customizadas ​ | E10: - Oi irá disponibilizar as faturas de terminais fibra, mantendo os sistemas, regras e processos atuais, até a migração total desses clientes, nos formatos e layout atuais (online e customizadas) para clientes varejo e empresarial. - Carga dos spools faturados nas ferramentas que disponibilizam online os documentos de faturamento. - Resolução dos problemas encontrados durante o processamento. - Eventuais necessidades de alterações deverão ser discutidas em relação à custo e prazo. | F10: Faturamento | G10: Monica | H10: Fatutamento/ Atendimento | J10: CONCLUÍDO | K10: Cristiane Barretto Sales <cristiane.barretto@oi.net.br> | L10: Bruno Macedo Soares <bmacedo@oi.net.br> | M10: Monica Sant Anna Paetzoldt <monica.paetzoldt@oi.net.br> | N10: -
B11: Finanças e Relações com investidores | C11: Bill-to-cash​ | D11: Envio dos spools para as print centers ​ | E11: - Oi irá disponibilizar os spools de faturas de terminais fibra para as print centers atuais da Oi (e remunerar os print centers), mantendo os sistemas, regras e processos atuais, até a migração total desses clientes, nos formatos e layout atuais (online e customizadas) para clientes varejo e empresarial. - Conferência do faturamento gerado e consistências cadastrais. - Disponibilização dos documentos para as empresas de postagem. | F11: Faturamento | G11: Monica | H11: Faturamento | J11: CONCLUÍDO | K11: Cristiane Barretto Sales <cristiane.barretto@oi.net.br> | L11: Bruno Macedo Soares <bmacedo@oi.net.br> | M11: Monica Sant Anna Paetzoldt <monica.paetzoldt@oi.net.br> | N11: -
B12: Finanças e Relações com investidores | C12: Bill-to-cash​ | D12: Postagem das faturas para os clientes ​ | E12: - Oi irá disponibilizar os documentos de faturamento de terminais fibra para as empresas de postagem, mantendo os sistemas, regras e processos atuais, até a migração total desses clientes, nos formatos e layout atuais (online e customizadas) para clientes varejo e empresarial. - Os clientes digitais terão seu envio da forma que solicitaram, seja via email ou whatsapp | F12: Faturamento | G12: Monica | H12: Faturamento | J12: CONCLUÍDO | K12: Cristiane Barretto Sales <cristiane.barretto@oi.net.br> | L12: Bruno Macedo Soares <bmacedo@oi.net.br> | M12: Monica Sant Anna Paetzoldt <monica.paetzoldt@oi.net.br> | N12: -
B13: Finanças e Relações com investidores | C13: Bill-to-cash​ | D13: Execução dos processos de garantia da receita ​ | E13: - Execução mensal de análise de variação da receita de serviços recorrentes dos segmentos varejo e empresarial nas principais alavancas (gross, churn, interrupções de faturamento, migrações, variações de clientes da base, etc) - Análise mensal das alavancas NTFGA (motivo de Terminais não Faturarem e Gerarem Assinatura) para serviços pós pagos. - Acompanhamento mensal da despesa de ITX e análise dos desvios (VOIP) | F13: RA/ Fraude | G13: Alessandro Varme | H13: RA/ Varme | J13: CONCLUÍDO | K13: Cristiane Barretto Sales <cristiane.barretto@oi.net.br> | L13: Bruno Macedo Soares <bmacedo@oi.net.br> | M13: Alessandro Luiz Varme Dias <alessandro.varme@oi.net.br> | N13: -
B14: Finanças e Relações com investidores | C14: Bill-to-cash​ | D14: Execução da cadeia de arrecadação​ | E14: - Execução dos processos de arrecadação bancária de acordo com processos, regras e sistemas atuais da Oi. - Troca de arquivos/informações com as instituições financeiras cadastradas. - Resolução de problemas encontrados durante o processamento | F14: Arrecadação e Cobrança | G14: Daniel Cattete | H14: Arrecadação/Cobrança/Daniel Cattete | J14: CONCLUÍDO | K14: Cristiane Barretto Sales <cristiane.barretto@oi.net.br> | L14: Bruno Macedo Soares <bmacedo@oi.net.br> | M14: Daniel Cattete Sanguedo <daniel.sanguedo@oi.net.br> | N14: -
B15: Finanças e Relações com investidores | C15: Bill-to-cash​ | D15: Execução da cadeia de débito automático ​ | E15: - Execução dos processos de débito automático de acordo com processos, regras e sistemas atuais da Oi. - Troca de arquivos/informações com as instituições cadastradas. - Resolução de problemas encontrados durante o processamento | F15: Arrecadação e Cobrança | G15: Daniel Cattete | H15: Arrecadação/Cobrança/Daniel Cattete | J15: CONCLUÍDO | K15: Cristiane Barretto Sales <cristiane.barretto@oi.net.br> | L15: Bruno Macedo Soares <bmacedo@oi.net.br> | M15: Daniel Cattete Sanguedo <daniel.sanguedo@oi.net.br> | N15: -
B16: Finanças e Relações com investidores | C16: Bill-to-cash​ | D16: Execução dos processos de fraude ​ | E16: - Execução dos processos de fraude subscrição de acordo com as regras e modelos atuais da Oi no modelo preventivo, caso o processo de vendas fique a cargo da Oi. - Execução dos processos de fraude técnica de acordo com as regras e modelos atuais da Oi (spoofing, fishing, smishing, etc). - Tratamento de fraudes identificadas no modelo detectivo - pós instalação. (churn e contas a receber) - Tratamento de out layers de consumo (investigação, retirada e tratamento contábil) - Tratamento de reclamações de clientes com alegação de fraude, avaliando procedência / improcedência da contestação. | F16: RA/ Fraude | G16: Alessandro Varme | H16: Fraude | J16: CONCLUÍDO | K16: Cristiane Barretto Sales <cristiane.barretto@oi.net.br> | L16: Bruno Macedo Soares <bmacedo@oi.net.br> | M16: Alessandro Luiz Varme Dias <alessandro.varme@oi.net.br> | N16: -
B17: Finanças e Relações com investidores | C17: Bill-to-cash​ | D17: Execução da cadeia fiscal​ | E17: - Execução dos processos fiscais para as Compradoras de acordo com a legislação vigente respeitando as respectivas regras e modelos atuais da Oi. - Geração e envio das obrigações acessórias, apuração e pagamento da obrigação principal, de acordo com os sistemas e procedimentos atuais da Oi. - Consistência contábil, reports executivos e operacionais atualmente executados pela Oi. - Resolução dos problemas encontrados, referente ao processo de apuração durante a validação das obrigações acessórias e da obrigação principal. | F17: Tributos/Fiscal | G17: Erika Braga | H17: Tributos Indiretos/ Tribustos Diretos | I17: Seguindo as mesmas definições tributárias utilizadas para o TSA do MARS, tais como: utilização dos sistemas fiscais comply, ERP SAP; sem migração do saldo acumulado do CIAP; os mesmos relatórios fiscais para fins de informações gerenciais e analíticas, mesmas obrigações principais e acessórias entregues atualmente pela BTSA. | J17: CONCLUÍDO | K17: Cristiane Barretto Sales <cristiane.barretto@oi.net.br> | L17: Flavia Casali <flaviacasali@oi.net.br> | M17: Erika Braga <erika.braga@oi.net.br> | N17: -
B18: Finanças e Relações com investidores | C18: Bill-to-cash​ | D18: Execução da cadeia contábil​ | E18: Execução das cadeias contábeis para as Compradoras de acordo com a legislação vigente respeitando as respectivas regras e modelos atuais da Oi- Carga dos arquivos no SAP da Oi, dos seguintes macro processos: 1- Receita, Descontos, ICMS e ISS, conforme ciclo dos Sistemas de Faturamento. 2- Arrecadação, Parcelamento de Fatura, Cancelamento e Contestação, conforme movimentos dos Sistema de Faturamento e Arrecadação. 3- Provisão p/ Créditos de Liquidação e Perdas, conforme movimentos dos Sistemas de Arrecadação. Export dos dados para as Compradoras no formato acordado. | F18: Contabilidade | G18: Marcelo Gomes | H18: Contabilidade | I18: Marcelo Gomes: o tópico foi alinhado com as áreas impacatdas, o ponto abaixo é apenas um detalhamento do que foi alinhado com as áreas impactadas. Deve ser avaliado pelos times de Tributos Diretos (Paulo Vidal) e Tributos Indiretos (Érika Braga): Envio dos arquivos dos convênios XXX, YYY e ZZZ para o fisco. Confirmação de recebimento dos arquivos fiscais pelo Fisco- Resolução dos problemas encontrados durante o processamento. Obs. O cálculo do PIS, COFINS, FUST e FUNTTEL é realizado pelo time de Tributos Diretos após a liberação/validação pela Contabilidade Operacional, conforme cronograma de fechamento. | J18: CONCLUÍDO | K18: Cristiane Barretto Sales <cristiane.barretto@oi.net.br> | L18: Andre Tavares Paradizi <andre.paradizi@oi.net.br> | M18: Francisco Paulo Macambira Haick <francisco.haick@oi.net.br> | N18: Marcelo Gomes <marcelo.gomes@oi.net.br>
B19: Finanças e Relações com investidores | C19: Bill-to-cash​ | D19: Execução da régua de cobrança - Classificação e reclassificação de status na régua ​ | E19: - Execução dos processos atuais da Oi associados à régua de cobrança para que os clientes evoluam dentro dos estágios existentes na régua. - Resolução dos problemas encontrados durante o processamento. | F19: Arrecadação e Cobrança | G19: Daniel Cattete | H19: Arrecadação/Cobrança/Daniel Cattete | J19: CONCLUÍDO | K19: Cristiane Barretto Sales <cristiane.barretto@oi.net.br> | L19: Bruno Macedo Soares <bmacedo@oi.net.br> | M19: Daniel Cattete Sanguedo <daniel.sanguedo@oi.net.br> | N19: -
B20: Finanças e Relações com investidores | C20: Bill-to-cash​ | D20: Execução da régua de cobrança - Geração de notificação para clientes inadimplentes ​ | E20: - Execução dos processos atuais de comunicações/notificações da Oi conforme regras Regulatórias pertinentes à régua de cobrança. - Resolução dos problemas encontrados durante o processamento. | F20: Arrecadação e Cobrança | G20: Daniel Cattete | H20: Arrecadação/Cobrança/Daniel Cattete | J20: CONCLUÍDO | K20: Cristiane Barretto Sales <cristiane.barretto@oi.net.br> | L20: Bruno Macedo Soares <bmacedo@oi.net.br> | M20: Daniel Cattete Sanguedo <daniel.sanguedo@oi.net.br> | N20: -
B21: Finanças e Relações com investidores | C21: Bill-to-cash​ | D21: Mediação de bilhetes​ | E21: - A Oi irá executar o processo de mediação de bilhetes de terminais Voip da ClientCo, mantendo os sistemas, regras e processos atuais, até a migração total desses clientes. - Controle de críticas e descartes de bilhetes. - Resolução dos problemas encontrados durante o processamento da Mediação. - Recuperação e reprocessamento de bilhetes em casos necessários | F21: Tráfego | G21: Marcus Vinícius | H21: Tráfego/Marcus Vinícius | J21: CONCLUÍDO | K21: Cristiane Barretto Sales <cristiane.barretto@oi.net.br> | L21: Bruno Macedo Soares <bmacedo@oi.net.br> | M21: Altevo Carlos De Sa Volotao <altevo.volotao@oi.net.br> | N21: Marcus Vinicius Miguel De Oliveira <marcus.oliveira@oi.net.br>
B22: Finanças e Relações com investidores | C22: Bill-to-cash​ | D22: Parametrizações e Homologações​ | E22: - Oi deverá avaliar solicitações das Compradoras de parametrizações e/ ou projetos nos sistemas de billing quanto a viabilidade. - As alterações implantadas deverão ser testadas e homologadas pela Oi e terão report para fins de acompanhamento do solicitante. - Todas as alterações deverão ser únicas para todos os comprovadores, não podem haver divergencia de regra e pedido entre eles. financeira, legal e regulatória. | F22: Faturamento | G22: Iara | H22: Faturamento/Iara | J22: CONCLUÍDO | K22: Cristiane Barretto Sales <cristiane.barretto@oi.net.br> | L22: Bruno Macedo Soares <bmacedo@oi.net.br> | M22: Iara Kelli Da Cruz Braga <iara.braga@oi.net.br> | N22: -
B23: Finanças e Relações com investidores | C23: Bill-to-cash​ | D23: Criação dos dossiês de clientes inadimplentes para ajuizamento, cobrança extrajudicial e recuperação judicial ​ | E23: - Criação de dossiês com toda a documentação necessária e disponível para que o jurídico inicie os ajuizamentos. | F23: Arrecadação e Cobrança | G23: Daniel Cattete | H23: Jur Consumidor/Fabrício | J23: CONCLUÍDO | K23: Cristiane Barretto Sales <cristiane.barretto@oi.net.br> | L23: Bruno Macedo Soares <bmacedo@oi.net.br> | M23: Daniel Cattete Sanguedo <daniel.sanguedo@oi.net.br> | N23: -
B24: Finanças e Relações com investidores | C24: Bill-to-cash​ | D24: Geração e distribuição de mailing e de relatórios de performance da operação ​ | E24: - Geração de mailings conforme regras atuais da Oi para a cobrança das assessorias. - Geração de relatórios de performance mensal atuais da Oi. | F24: Arrecadação e Cobrança | G24: Daniel Cattete | H24: Faturamento// Contas a receber/ Cobrança | J24: CONCLUÍDO | K24: Cristiane Barretto Sales <cristiane.barretto@oi.net.br> | L24: Bruno Macedo Soares <bmacedo@oi.net.br> | M24: Daniel Cattete Sanguedo <daniel.sanguedo@oi.net.br> | N24: -
B25: Finanças e Relações com investidores | C25: Bill-to-cash​ | D25: Relatórios de CAR e PDD​ | E25: Oi deverá gerar os relatórios contábeis de CAR analítico por Unidade de Negócio, por Cliente e por Fatura, de acordo com os prazos. Oi deverá gerar os relatórios de PDD/PERDAS sintético por Unidade de Negócio, de acordo com os prazos. Oi deverá gerar o relatório de PDD Parcelamento analítico por Unidade de Negócio, por Cliente e por Fatura, de acordo com os prazos. | F25: Contabilidade | G25: Marcelo Gomes | H25: Contas a receber/Cobrança // Contabilidade | J25: CONCLUÍDO | K25: Cristiane Barretto Sales <cristiane.barretto@oi.net.br> | L25: Andre Tavares Paradizi <andre.paradizi@oi.net.br> | M25: Francisco Paulo Macambira Haick <francisco.haick@oi.net.br> | N25: Marcelo Gomes <marcelo.gomes@oi.net.br>
B26: Finanças e Relações com investidores | C26: Bill-to-cash​ | D26: Execução dos processos de Crédito​ | E26: Oi deverá executar os processos de análise de crédito de acordo com as regras e modelos atuais, mantendo sistemas, políticas e níveis de serviços para as Compradoras tratando os problemas identificados nos processos de aprovação de crédito. A performance dessa operação será acompanhada em reports de aprovação e reports de performance de FPD nas visões e aberturas acompanhadas atualmente pela Oi, caso o processo de venda e aquisição ocorra nos CRM da Oi. | F26: Crédito | G26: Bruno Simões | H26: Contas a receber/ Cobrança | I26: [Bruno Simões] - Descrição validada durante a reunião. | J26: CONCLUÍDO | K26: Cristiane Barretto Sales <cristiane.barretto@oi.net.br> | L26: Bruno Macedo Soares <bmacedo@oi.net.br> | M26: - | N26: Bruno Simoes <bruno.simoes@oi.net.br>
B27: Finanças e Relações com investidores | C27: Bill-to-cash​ | D27: Repasse da receita de Fibra das UPI´s ClientCo | E27: - Realização de repasse mensal da receita de Fibra, SVA, Oi Expert, Fibra X e Add on para as compradoras. - Resolução dos problemas encontrados durante apuração do repasse. | F27: Tráfego | G27: Marcus Vinícius | H27: Tráfego | J27: CONCLUÍDO | K27: Cristiane Barretto Sales <cristiane.barretto@oi.net.br> | L27: Bruno Macedo Soares <bmacedo@oi.net.br> | M27: Altevo Carlos De Sa Volotao <altevo.volotao@oi.net.br> | N27: Marcus Vinicius Miguel De Oliveira <marcus.oliveira@oi.net.br>
B28: Finanças e Relações com investidores | C28: Bill-to-cash​ | D28: Co-Billing Interno CSP´s de Outras Operadoras | E28: - A Oi S/A prestará o serviço de co-faturamento do CSP de Outras Operadoras originado por terminais Voip da ClientCo. | F28: Tráfego | G28: Marcus Vinícius | H28: Tráfego | J28: CONCLUÍDO | K28: Cristiane Barretto Sales <cristiane.barretto@oi.net.br> | L28: Bruno Macedo Soares <bmacedo@oi.net.br> | M28: Altevo Carlos De Sa Volotao <altevo.volotao@oi.net.br> | N28: Marcus Vinicius Miguel De Oliveira <marcus.oliveira@oi.net.br>
B29: Finanças e Relações com investidores | C29: Bill-to-cash​ | D29: Operação de Interconexão | E29: - A Oi irá executar o processo de apuração da Interconexão de bilhetes de terminais Voip da ClientCo, mantendo os sistemas, regras e processos atuais, até a migração total desses clientes. - Controle de críticas e descartes de bilhetes. - Resolução dos problemas encontrados durante o processamento da Interconexão. - Recuperação e reprocessamento de bilhetes em casos necessários | F29: Tráfego | G29: Marcus Vinícius | H29: Tráfego | J29: CONCLUÍDO | K29: Cristiane Barretto Sales <cristiane.barretto@oi.net.br> | L29: Bruno Macedo Soares <bmacedo@oi.net.br> | M29: Altevo Carlos De Sa Volotao <altevo.volotao@oi.net.br> | N29: Marcus Vinicius Miguel De Oliveira <marcus.oliveira@oi.net.br>
B30: Finanças e Relações com investidores | C30: Bill-to-cash​ | D30: Repasse de SVA/Terceiros/0500 | E30: - Realização da apuração periodica dos valores para repasse de parceiros de SVA/Terceiros/0500 mantendo os sistemas, regras e processos atuais, até a migração total desses clientes. - Resolução dos problemas encontrados durante apuração do repasse. | F30: Tráfego | G30: Marcus Vinícius | H30: Tráfego | J30: CONCLUÍDO | K30: Cristiane Barretto Sales <cristiane.barretto@oi.net.br> | L30: Bruno Macedo Soares <bmacedo@oi.net.br> | M30: Altevo Carlos De Sa Volotao <altevo.volotao@oi.net.br> | N30: Marcus Vinicius Miguel De Oliveira <marcus.oliveira@oi.net.br>
B31: Finanças e Relações com investidores | C31: Bill-to-cash​ | D31: Relacionamento Finaceiro com as Demais Operadoras | E31: - A Oi irá executar o processo de encontro de contas de Interconexão, mantendo os sistemas, regras e processos atuais, até a migração total desses clientes. - Resolução dos problemas encontrados durante apuração do repasse. | F31: Tráfego | G31: Marcus Vinícius | H31: Tráfego | J31: CONCLUÍDO | K31: Cristiane Barretto Sales <cristiane.barretto@oi.net.br> | L31: Bruno Macedo Soares <bmacedo@oi.net.br> | M31: Altevo Carlos De Sa Volotao <altevo.volotao@oi.net.br> | N31: Marcus Vinicius Miguel De Oliveira <marcus.oliveira@oi.net.br>
B32: Finanças e Relações com investidores | C32: Bill-to-cash​ | D32: Obrigação Fiscal (entrada NF/input SAP/retenções de impostos) - OPERAÇÃO BPO | E32: -A Oi deverá executar o processo de lançamentos das NF's de entrada no SAP, com as devidas retenções federais e municipais. - Execução dos controles internos conforme relação de controles existentes (SOX). - Devolutiva das criticas para as NF não lançadas pelo Posto Fiscal | F32: Tributos/Fiscal | G32: Hozana Guimarães | H32: Tributos/Fiscal | J32: CONCLUÍDO | K32: Cristiane Barretto Sales <cristiane.barretto@oi.net.br> | L32: Flavia Casali <flaviacasali@oi.net.br> | M32: Hozana Guimaraes De Sa Braga <hozana.braga@oi.net.br> | N32: -
B33: Finanças e Relações com investidores | C33: Bill-to-cash​ | D33: Criação de Requisições de compras e pedidos(célula adm) - OPERAÇÃO BPO | E33: - A Oi deverá criar os novos pedidos de compras conforme demandas de serviços e equipamentos que estiverem vinculados aos contratos e verba disponiveis para as ClientCO's | F33: Tributos/Fiscal | G33: Hozana Guimarães | H33: Diversas áreas | J33: CONCLUÍDO | K33: Cristiane Barretto Sales <cristiane.barretto@oi.net.br> | L33: Flavia Casali <flaviacasali@oi.net.br> | M33: Hozana Guimaraes De Sa Braga <hozana.braga@oi.net.br> | N33: -
B34: Finanças e Relações com investidores | C34: Bill-to-cash​ | D34: Criação e Manutenção dos cadastros de Fornecedores, Clientes, códigos de materiais e serviços | E34: - A Oi deverá executar o processo de cadastro no SAP para as demandas referentes a criação de novos fornecedores, clientes, codigos de materiais e serviços, manutenção dos cadastros ( atualização de dados bancários, ampliações de centros, paramentros de códigos para corretas contabilizações, ajustes de aliquotas, domicilio fiscal etc, conforme necessidade que surgirem no periodo após drop. -Extração de relatório com as demandas que forem solicitadas no periodo. | F34: Tributos/Fiscal | G34: Hozana Guimarães | H34: Diversas áreas | J34: CONCLUÍDO | K34: Cristiane Barretto Sales <cristiane.barretto@oi.net.br> | L34: Flavia Casali <flaviacasali@oi.net.br> | M34: Hozana Guimaraes De Sa Braga <hozana.braga@oi.net.br> | N34: -
B35: Finanças e Relações com investidores | C35: Bill-to-cash​ | D35: Portal de Notas (Sistema de acesso de fornecedores, gestores de aceite e usuários do Posto Fiscal) | E35: - A Oi deverá garantir o processo sistemico de cadastro, armazenamento das NF's de entrada no BRNOTAS, integração com sistemas SAP para escrituração fiscal no SAP. - Extração de relatórios das NF cadastrdas, com status de tratamento. - Consulta das NF emitidas contra as ClientC0's | F35: Tributos/Fiscal | G35: Hozana Guimarães | H35: Tributos/Fiscal | J35: CONCLUÍDO | K35: Cristiane Barretto Sales <cristiane.barretto@oi.net.br> | L35: Flavia Casali <flaviacasali@oi.net.br> | M35: Hozana Guimaraes De Sa Braga <hozana.braga@oi.net.br> | N35: -
B36: Finanças e Relações com investidores | C36: Bill-to-cash​ | D36: Gestão dos print centers​ | E36: - Manter e divulgar para as Compradoras os indicadores e SLAs de gestão das print centers, alinhados como KPIs - A Oi irá divulgar os indicadores e SLAs, mantendo os sistemas, regras e processos atuais, até a migração total desses clientes, nos formatos e layout atuais (online e customizadas) para clientes varejo e empresarial | F36: Faturamento | G36: Monica | H36: Faturamento | I36: Levar para Bill to cash? Faturamento vai avaliar. | J36: CONCLUÍDO | K36: Cristiane Barretto Sales <cristiane.barretto@oi.net.br> | L36: Bruno Macedo Soares <bmacedo@oi.net.br> | M36: Monica Sant Anna Paetzoldt <monica.paetzoldt@oi.net.br> | N36: -
B37: Finanças e Relações com investidores | C37: Application and data management​ | D37: Tratamento de inadimplência anterior à migração ​ | E37: De acordo com as regras e parâmetros atuais, utilizando os recursos, sistemas, plataformas atuais, a Oi deverá: - Tratar nos sistemas Oi o processo de inadimplência dos clientes anteriores a migração para as Compradoras. | F37: Arrecadação e Cobrança | G37: Daniel Cattete | H37: Contas a receber/ Cobrança | I37: Atendimento: Direcionar o item para Contas a Receber/Cobrança. Não tem ação de atendimento, no entanto a ação de efetuar parcelamento está contida no item regua de cobrança | J37: CONCLUÍDO | K37: Cristiane Barretto Sales <cristiane.barretto@oi.net.br> | L37: Bruno Macedo Soares <bmacedo@oi.net.br> | M37: Daniel Cattete Sanguedo <daniel.sanguedo@oi.net.br> | N37: -
B38: Finanças e Relações com investidores | C38: Application and data management​ | D38: Cobilling​ | E38: - Executar o faturamento do CSP 31 e 14 até a migração do terminal para compradora, mantendo os sistemas, regras e processos atuais. | F38: Tráfego | G38: Marcus Vinícius | H38: Tarifação e repasse | J38: CONCLUÍDO | K38: Cristiane Barretto Sales <cristiane.barretto@oi.net.br> | L38: Bruno Macedo Soares <bmacedo@oi.net.br> | M38: Altevo Carlos De Sa Volotao <altevo.volotao@oi.net.br> | N38: Marcus Vinicius Miguel De Oliveira <marcus.oliveira@oi.net.br>
B39: Finanças e Relações com investidores | C39: Bill-to-cash​ | D39: Extração, elaboração e envio dos reports para forncedores de Conteúdo | E39: Principais Atividades: - Extração das bases dos CRMs (SINN, SIEBEL, DW) - Carga das exportações no Banco de Dados - Validação dos volumes de clientes (check de sanidade) - Formatação e preenchimento dos reports nos formatos acordados com cada fornecedor - Envio dos reports e eventuais correções | F39: Parceiro de Negócio | G39: Maurício | J39: CONCLUÍDO | K39: Cristiane Barretto Sales <cristiane.barretto@oi.net.br> | L39: Andre Tavares Paradizi <andre.paradizi@oi.net.br> | M39: Mauricio Fernandes <mauricio.cardoso@oi.net.br>
B40: Finanças e Relações com investidores | C40: Bill-to-cash​ | D40: Cálculo dos valores de fauramento | E40: Calcular os valores a serem pagos aos Fornecedores, como base nos report gerando racional de faturamentode acordo com as condições contratuais | F40: Parceiro de Negócio | G40: Maurício | J40: CONCLUÍDO | K40: Cristiane Barretto Sales <cristiane.barretto@oi.net.br> | L40: Andre Tavares Paradizi <andre.paradizi@oi.net.br> | M40: Mauricio Fernandes <mauricio.cardoso@oi.net.br>
B41: Finanças e Relações com investidores | C41: Bill-to-cash​ | D41: Criação e gestão dos pedidos de compra | E41: Principais Atividades: - Interface com setor administrativo para solicitação de criação de Pedido de Compras e RC (requisição de compras) e checks dos documentos criados; - Envio dos pedidos para os fornecdores. - Solicitação da aprovação dos pedidos SAP aos gestores responsáveis. | F41: Parceiro de Negócio | G41: Maurício | J41: CONCLUÍDO | K41: Cristiane Barretto Sales <cristiane.barretto@oi.net.br> | L41: Andre Tavares Paradizi <andre.paradizi@oi.net.br> | M41: Mauricio Fernandes <mauricio.cardoso@oi.net.br>
B42: Finanças e Relações com investidores | C42: Bill-to-cash​ | D42: Cálculos, Lançamentos e Justificativas de Provisão e Reclassificaçõs | E42: Principais Atividades: -Calculos e análises do valor disponível (EP, WE e PV) - Cálculos, atualização e análises de repasse, provisão e resultado por programadora, segmento de negocios, UNs e UPIs - real frente ao orçado e forecast´s - Acompanhando NFs no GED e SAP - Calculos e análises de simulações para resultado do pcte e estimativa gasto e uso verba para os próximo meses (cenários) | F42: Parceiro de Negócio | G42: Maurício | J42: CONCLUÍDO | K42: Cristiane Barretto Sales <cristiane.barretto@oi.net.br> | L42: Andre Tavares Paradizi <andre.paradizi@oi.net.br> | M42: Mauricio Fernandes <mauricio.cardoso@oi.net.br>
B43: Finanças e Relações com investidores | C43: Bill-to-cash​ | D43: Emissão de Nota Fiscal e Input da Receita de PagSeguro | E43: - geração de nota fiscal no SISRED para parceiros B2B (PagSeguro e Safira); - Após a geração da nota fiscal, encaminhar ao parceiro para que efetue o pagamento e ao time de Faturamento; - Acompanhamento da baixa do pagamento pelo SISRAF; | F43: Parceiro de Negócio | G43: Maurício | J43: CONCLUÍDO | K43: Cristiane Barretto Sales <cristiane.barretto@oi.net.br> | L43: Andre Tavares Paradizi <andre.paradizi@oi.net.br> | M43: Mauricio Fernandes <mauricio.cardoso@oi.net.br>
B44: Finanças e Relações com investidores | C44: Bill-to-cash​ | D44: Comissões de Vendas - Validação das politicas comerciais | E44: Garantir a aplicabilidade das regras de comissionamento elaboradas pelos diversos canais de vendas | F44: Parceiro de Negócio | G44: Maurício | J44: CONCLUÍDO | K44: Cristiane Barretto Sales <cristiane.barretto@oi.net.br> | L44: Andre Tavares Paradizi <andre.paradizi@oi.net.br> | M44: Mauricio Fernandes <mauricio.cardoso@oi.net.br>
B45: Finanças e Relações com investidores | C45: Bill-to-cash​ | D45: Comissões de Vendas - Cálculos de Comissionamento | E45: Extração das bases de Vendas (BOV); Aplicação das Políticas Comerciais; Aplicação das PADAs de Campanha; Sign Off dos valores para garantir que as não haja variações injustificadas; Divulgação dos valores para Regionais e Canais | F45: Parceiro de Negócio | G45: Maurício | J45: CONCLUÍDO | K45: Cristiane Barretto Sales <cristiane.barretto@oi.net.br> | L45: Andre Tavares Paradizi <andre.paradizi@oi.net.br> | M45: Mauricio Fernandes <mauricio.cardoso@oi.net.br>
B46: Finanças e Relações com investidores | C46: Bill-to-cash​ | D46: Comissões de Vendas - Cálculo de IQ | E46: Extração das bases de Vendas; Acompanhamento do Churn e Inadimplência; Divulgação do índice para Regionais e Canais | F46: Parceiro de Negócio | G46: Maurício | J46: CONCLUÍDO | K46: Cristiane Barretto Sales <cristiane.barretto@oi.net.br> | L46: Andre Tavares Paradizi <andre.paradizi@oi.net.br> | M46: Mauricio Fernandes <mauricio.cardoso@oi.net.br>
B47: Finanças e Relações com investidores | C47: Admin personnel​ | D47: Programação, BackOffice, Planejamento e Conciliação dos pagamentos | E47: - Tratamento e analise dos documentos - Criação de proposta de pagamento - Aprovação da proposta de pagamento - Previa dos pagamentos e solicitação do recurso financeiros por CNPJ - Confecção dos borderôs - Aprovação do Pagamento no banco - Emissão de comprovantes de pagamento - Registro dos comprovantes de pagamento no sistema - Importação dos arquivos retorno e dos extratos - Conciliação contábil das contas bancárias de contas a pagar | F47: Tesouraria e Análise de Desempenho | G47: Streit | J47: CONCLUÍDO | K47: Cristiane Barretto Sales <cristiane.barretto@oi.net.br> | L47: Pedro Andrade Franca <pedro.franca@oi.net.br> | M47: Ana Kelly Da Silva Carneiro <ana.carneiro@oi.net.br> | N47: Manuela Barros De Sa Grande <manuela.grande@oi.net.br>
B48: Finanças e Relações com investidores | C48: Admin personnel​ | D48: Projeção do Fluxo de Caixa e acompanhamento do realizado | E48: - Projeção do FCD/FCI da(s) SPE(s) de curto e médio prazos - Previsão diária dos Recebimentos/Pagamentos para controle do Caixa da(s) SPE(s) - Acompanhamento e report do realizado mensal do Caixa, analisando as principais variações frente a projeção | F48: Tesouraria e Análise de Desempenho | G48: Streit | J48: CONCLUÍDO | K48: Cristiane Barretto Sales <cristiane.barretto@oi.net.br> | L48: Pedro Andrade Franca <pedro.franca@oi.net.br> | M48: Eduardo Streit <eduardo.streit@oi.net.br> | N48: Fabiana Fares Dib <fabiana.dib@oi.net.br>
B49: Finanças e Relações com investidores | C49: Admin personnel​ | D49: Relacionamento com Bancos | E49: - Realizar a implantação operacional da estrutura de acesso aos novos usuários: abertura de conta corrente, criação de acessos, cadastro das empresas, implementação de convênios (folha e CAP) | F49: Tesouraria e Análise de Desempenho | G49: Streit | J49: CONCLUÍDO | K49: Cristiane Barretto Sales <cristiane.barretto@oi.net.br> | L49: Pedro Andrade Franca <pedro.franca@oi.net.br> | M49: Carolina Gava <carolina.gava@oi.net.br> | N49: Janaina Carvalho Martins <janaina.martins@oi.net.br>
B50: Finanças e Relações com investidores | C50: Admin personnel​ | D50: Relacionamento com Bancos | E50: - Realizar a implantação de convênios de arrecadação nos bancos em que hoje os clientes migrados já possuem relacionamento. Para os casos em que os clientes não tenham débito automático, garantir a implementação da estrutura de boletos / PIX. Em um cenário co-billing, realizar pós closing. | F50: Tesouraria e Análise de Desempenho | G50: Streit | J50: CONCLUÍDO | K50: Cristiane Barretto Sales <cristiane.barretto@oi.net.br> | L50: Pedro Andrade Franca <pedro.franca@oi.net.br> | M50: Carolina Gava <carolina.gava@oi.net.br> | N50: Janaina Carvalho Martins <janaina.martins@oi.net.br>
B51: Finanças e Relações com investidores | C51: Admin personnel​ | D51: Gestão e Fechamento do Caixa | E51: - Em um cenário de co-billing e, em havendo datas pontuais de repasses no mês, realizar o cálculo do float a ser transferido aos compradores. Em um cenário de faturamento direto pelas SPEs, fazer manualmente as transferências diárias onde os bancos não tenham centralização automática | F51: Tesouraria e Análise de Desempenho | G51: Streit | J51: CONCLUÍDO | K51: Cristiane Barretto Sales <cristiane.barretto@oi.net.br> | L51: Pedro Andrade Franca <pedro.franca@oi.net.br> | M51: Carolina Gava <carolina.gava@oi.net.br> | N51: Janaina Carvalho Martins <janaina.martins@oi.net.br>
B52: Finanças e Relações com investidores | C52: Admin personnel​ | D52: Gestão e Fechamento do Caixa | E52: - Realizar a rotina operacional de disponibilização de recursos para os pagamentos diários | F52: Tesouraria e Análise de Desempenho | G52: Streit | J52: CONCLUÍDO | K52: Cristiane Barretto Sales <cristiane.barretto@oi.net.br> | L52: Pedro Andrade Franca <pedro.franca@oi.net.br> | M52: Carolina Gava <carolina.gava@oi.net.br> | N52: Janaina Carvalho Martins <janaina.martins@oi.net.br>
B53: Finanças e Relações com investidores | C53: Admin personnel​ | D53: Fechamento de Câmbio | E53: - Cadastro das empresas nos bancos que operacionalizam câmbio | F53: Tesouraria e Análise de Desempenho | G53: Carolina Gava | J53: CONCLUÍDO | K53: Cristiane Barretto Sales <cristiane.barretto@oi.net.br> | L53: Pedro Andrade Franca <pedro.franca@oi.net.br> | M53: Carolina Gava <carolina.gava@oi.net.br> | N53: Janaina Carvalho Martins <janaina.martins@oi.net.br>
B54: Finanças e Relações com investidores | C54: Admin personnel​ | D54: Fechamento de Câmbio | E54: - Fechamento de câmbio para pagamento a fornecedores internacionais | F54: Tesouraria e Análise de Desempenho | G54: Carolina Gava | J54: CONCLUÍDO | K54: Cristiane Barretto Sales <cristiane.barretto@oi.net.br> | L54: Pedro Andrade Franca <pedro.franca@oi.net.br> | M54: Carolina Gava <carolina.gava@oi.net.br> | N54: Janaina Carvalho Martins <janaina.martins@oi.net.br>
B55: Finanças e Relações com investidores | C55: Admin personnel​ | D55: Projeção e Relatórios de Caixa | E55: - Confeccionar os relatórios gerenciais de caixa para a construção do fluxo de caixa diário pelo time de FP&A | F55: Tesouraria e Análise de Desempenho | G55: Streit | J55: CONCLUÍDO | K55: Cristiane Barretto Sales <cristiane.barretto@oi.net.br> | L55: Pedro Andrade Franca <pedro.franca@oi.net.br> | M55: Carolina Gava <carolina.gava@oi.net.br> | N55: Janaina Carvalho Martins <janaina.martins@oi.net.br>
B56: Finanças e Relações com investidores | C56: Admin personnel​ | D56: Conciliação Bancária das operações de Tesouraria no SAP | E56: - Executar a conciliação bancária de operações de Tesouraria (Saldo conta contábil x Extrato) | F56: Tesouraria e Análise de Desempenho | G56: Streit | J56: CONCLUÍDO | K56: Cristiane Barretto Sales <cristiane.barretto@oi.net.br> | L56: Pedro Andrade Franca <pedro.franca@oi.net.br> | M56: Philippe Reis Brasil <philippe.carmo@oi.net.br> | N56: Elisabete Ribeiro <elisabete.ribeiro@oi.net.br>
B57: Finanças e Relações com investidores | C57: Admin personnel​ | D57: Contabilização das operações de Tesouraria no SAP | E57: - Executar a contabilização das operações de Tesouraria (Aplicação, Resgate, Rendimentos e Tributação e câmbio). A compradora deve enviar quinzenalmente um controle de excel para carga no SAP (a ser disponibilizado pela Oi), identificando, entre outros, as contas contábeis, debitos e créditos, data de lançamento. | F57: Tesouraria e Análise de Desempenho | G57: Streit | J57: CONCLUÍDO | K57: Cristiane Barretto Sales <cristiane.barretto@oi.net.br> | L57: Pedro Andrade Franca <pedro.franca@oi.net.br> | M57: Philippe Reis Brasil <philippe.carmo@oi.net.br> | N57: Elisabete Ribeiro <elisabete.ribeiro@oi.net.br>
B58: Finanças e Relações com investidores | C58: Admin personnel​ | D58: Controle de Ativo Imobilizado e Intangível | E58: Execução e Conciliação das Rotinas do Ativo Fixo (Imobilizado/Intangível). | F58: Contabilidade | G58: Marcelo Gomes | I58: [Leandro] - Informação enviada no dia 05/06/24, ou seja, após o disparo oficial do Draft. Retificado para os executivos no dia 05/06 | J58: CONCLUÍDO | K58: Cristiane Barretto Sales <cristiane.barretto@oi.net.br> | L58: Andre Tavares Paradizi <andre.paradizi@oi.net.br> | M58: Francisco Paulo Macambira Haick <francisco.haick@oi.net.br> | N58: Marcelo Gomes <marcelo.gomes@oi.net.br>
B59: Finanças e Relações com investidores | C59: Admin personnel​ | D59: Controle de Despesas e Obrigações Contábeis | E59: Execução e Conciliação das Despesas, parametrizações contábeis e Obrigações junto à Receita Federal. | F59: Contabilidade | G59: Marcelo Gomes | I59: [Leandro] - Informação enviada no dia 05/06/24, ou seja, após o disparo oficial do Draft. Retificado para os executivos no dia 05/06 | J59: CONCLUÍDO | K59: Cristiane Barretto Sales <cristiane.barretto@oi.net.br> | L59: Andre Tavares Paradizi <andre.paradizi@oi.net.br> | M59: Francisco Paulo Macambira Haick <francisco.haick@oi.net.br> | N59: Marcelo Gomes <marcelo.gomes@oi.net.br>
B60: Finanças e Relações com investidores | C60: Admin personnel​ | D60: Informações contábeis necessárias para elaboração das Demonstrações Financeiras | E60: Elaboração de determinados quadros das Notas Explicativas das Demonstrações Financeiras. | F60: Contabilidade | G60: Marcelo Gomes | I60: [Leandro] - Informação enviada no dia 05/06/24, ou seja, após o disparo oficial do Draft. Retificado para os executivos no dia 05/06 | J60: CONCLUÍDO | K60: Cristiane Barretto Sales <cristiane.barretto@oi.net.br> | L60: Andre Tavares Paradizi <andre.paradizi@oi.net.br> | M60: Francisco Paulo Macambira Haick <francisco.haick@oi.net.br> | N60: Patricia Ann Necyk <pan@oi.net.br>
B61: Jurídico | C61: Customer data and offer management​ | D61: Consultoria tributária e atendimento à fiscalização | E61: A Oi se compromete a avaliar novas demandas legais, fiscais e tributárias, criadas/instituídas posteriormente à assinatura do Contrato (durante o período do TSA), avaliando viabilidade técnica, riscos, prazos legais e custo incremental. O custo, pelos desenvolvimentos necessários, serão arcados e/ou reembolsamos pela compradora, a depender do que ficar combinado no contrato. Não há como prever, de antemão, quais seriam esses custos, já que não sabemos quais novas obrigações poderiam ser criadas. Ademais, especificamente ao atendimento à fiscalização tributária, a Oi se compromete em garantir a disposnibilidação da documentação suporte conforme AS IS para atendimento às notificações recebidas pelo Jurídico Tributário. | F61: Jurídico Tributário | G61: Julia Villares e Alessandra Lima | H61: Jur. Tributário | I61: Premissa utilizada pelo Jurídicotributário para elaboração do texto da ClientCo (Alessandra): Tendo em vista que nos foi dito em reunião que a Oi vai se comprometer com as ClientCo a avaliar e levantar os custos para o atendimento das novas demandas legais, relativas a temas fiscais e tributários, que venham a ser instituídas/criadas posteriormente à assinatura do Contrato (desde o closing e durante o período de vigência do TSA). | J61: CONCLUÍDO | K61: Thalles Eduardo Silva Gracelacio Da Paixao <thalles.paixao@oi.net.br> | L61: Fernando Raposo Franco <fernando.franco@oi.net.br> | M61: Pedro Rique Nepomuceno <pedro.nepomuceno@oi.net.br> | N61: Julia Villares Torres <julia.torres@oi.net.br>
B62: Jurídico | C62: Customer data and offer management​ | D62: Consultoria cível estratégico | E62: A Oi se compromete a prestar consultoria jurídica ou viabilizar a interface dos integrantes do grupo com a área jurídica impactada. | F62: Jurídico Cível Estratégico | G62: Luiz Felipe Vargas | J62: CONCLUÍDO | K62: Thalles Eduardo Silva Gracelacio Da Paixao <thalles.paixao@oi.net.br> | L62: Fernando Raposo Franco <fernando.franco@oi.net.br> | M62: Luiz Felipe Neves Do Couto Vargas <luizf.vargas@oi.net.br>
B63: Jurídico | C63: Bill-to-cash​ | D63: Recuperação de faturas​ | E63: - Oi deverá recuperar faturas antigas dos clientes da ClienteCo, mediante solicitações judiciais, regulatórias ou obrigações tributárias, mantendo os sistemas, regras e processos atuais. | F63: Jurídico Consumidor | G63: Anderson Nilson | H63: Jurídico Consumidor/ Regulatório/ Tributário | J63: CONCLUÍDO | K63: Thalles Eduardo Silva Gracelacio Da Paixao <thalles.paixao@oi.net.br> | L63: Elen Marques Souto La Croix <elen.souto@oi.net.br> | M63: Adriana Velhote De Oliveira <adriana.velhote@oi.net.br> | N63: Anderson Nilson Rocha <anderson.rocha@oi.net.br>
B64: Jurídico | C64: Customer care​ | D64: Interação com Tribunais de Justiça, Órgãos e entidades de Relacionamento com consumidores: PROCON, Ouvidoria ANATEL e Consumidor.gov ​ | E64: - Internalização e definição para tratamento de demandas judiciais e administrativas dos consumidores - Atendimento pelos canais exigidos e pré-acordados com as instâncias externas para recepção de contatos e reclamações prevenientes dos Tribunais de Justiça, Procons, site Consumidor.Gov, bem como, canais regulados de respostas com a Anatel e Ouvidoria Anatel. - Os SLAs também já são os estabelecidos e acordados pelos mesmos. | F64: Jurídico Consumidor | G64: Anderson Nilson | H64: Jur Consumidor/ Ouvidoria/ Anatel | J64: CONCLUÍDO | K64: Thalles Eduardo Silva Gracelacio Da Paixao <thalles.paixao@oi.net.br> | L64: Elen Marques Souto La Croix <elen.souto@oi.net.br> | M64: Adriana Velhote De Oliveira <adriana.velhote@oi.net.br> | N64: Anderson Nilson Rocha <anderson.rocha@oi.net.br>
B65: Jurídico | C65: Application and data management​ | D65: Dados históricos anteriores à migração (informações necessárias para tratar eventuais ações e processos judiciais e administrativos PROCON e CONSUMIDOR.GOV.BR)​ | E65: De acordo com as regras e parâmetros atuais, utilizando os recursos, sistemas, plataformas atuais, a Oi deverá: - Tratar em seus sistemas legados, cumprir determinações judiciais consumeristas, ou disponibilizar as informações necessárias para tratar eventuais ações e processos judiciais ou administrativos, de clientes com datas anteriores à migração massiva ou voluntária realizada para as bases da Compradora. | F65: Jurídico Consumidor | G65: Anderson Nilson | H65: Jurídico Consumidor/ Jurídico Cível Estratégico | I65: Texto foi validado pelo time Jurídico consumidor. TI contempla o tema dentro do tema "Dados históricos anteriores à migração (chamados de clientes que demandem informações históricas)​". Obs.: Retiramos a palavra "Fiscal" do tópico. | J65: CONCLUÍDO | K65: Thalles Eduardo Silva Gracelacio Da Paixao <thalles.paixao@oi.net.br> | L65: Elen Marques Souto La Croix <elen.souto@oi.net.br> | M65: Adriana Velhote De Oliveira <adriana.velhote@oi.net.br> | N65: Anderson Nilson Rocha <anderson.rocha@oi.net.br>
B66: Jurídico | C66: Customer care​ | D66: Gestão de solicitações Consumeristas (JEC, VARA CÍVEL, PROCON e CONSUMIDOR.GOV.BR) | E66: De acordo com as regras e parâmetros atuais, utilizando os recursos, sistemas, plataformas atuais, a Oi deverá: - Controlar as demandas Judiciais e Administrativas do Juridico Consumidor, recebidas via e-mail ou sistemas a serem definidos, distribuir para tratamento operacional e controlar resposta para as compradoras. | F66: Jurídico Consumidor | G66: Anderson Nilson | H66: Jurídico Consumidor/Anderson Rocha / Fabricio Martins | J66: CONCLUÍDO | K66: Thalles Eduardo Silva Gracelacio Da Paixao <thalles.paixao@oi.net.br> | L66: Elen Marques Souto La Croix <elen.souto@oi.net.br> | M66: Adriana Velhote De Oliveira <adriana.velhote@oi.net.br> | N66: Anderson Nilson Rocha <anderson.rocha@oi.net.br>
B67: Jurídico | C67: Customer care​ | D67: Análise Jurídica Consumerista e avaliação de ingresso no polo | E67: Recebimento da notificação de demanda de terceiro, analise jurídica, encaminhamento ou tratamento dos processos judiciais consumeristas com avaliação de ingresso no polo. | F67: Jurídico Consumidor | G67: Anderson Nilson | H67: Jurídico Consumidor/Anderson Rocha / Fabricio Martins | J67: CONCLUÍDO | K67: Thalles Eduardo Silva Gracelacio Da Paixao <thalles.paixao@oi.net.br> | L67: Elen Marques Souto La Croix <elen.souto@oi.net.br> | M67: Fabricio Cardoso De Faria Martins <fabricio.martins@oi.net.br>
B68: Jurídico | C68: Application and data management​ | D68: Dados históricos anteriores à migração (informações necessárias para tratar eventuais ações e processos judiciais)​ | E68: De acordo com as regras e parâmetros atuais, utilizando os recursos, sistemas, plataformas atuais, a Oi deverá: - Tratar em seus sistemas, ou disponibilizar as informações necessárias para tratar eventuais ações e processos judiciais de ex-colaboradores com datas anteriores à migração massiva.. | F68: Serviços Jurídicos e Tralhista | G68: Douglas Tostes | H68: Serviços Jurídicos Regionais | I68: [Douglas Tostes] - Informou que da Diretoria da Williams, só terá atividade na diretoria "Serviços Jurídicos Regionais". | J68: CONCLUÍDO | K68: Thalles Eduardo Silva Gracelacio Da Paixao <thalles.paixao@oi.net.br> | L68: Williams Pereira Junior <williams.pereira@oi.net.br> | M68: Douglas Tostes Coelho <douglas.coelho@oi.net.br> | N68: Viviane Lima Marques <viviane.marques@oi.net.br>
B69: Oi Fibra | C69: Customer data and offer management​ | D69: Construção de proposta de valor | E69: 1. Definição e revisão contínua da Estratégia de atuação de marketing da Oi Fibra seguindo diretrizes de negócio bem como premissas financeiras, entre outros. 2. Responsável por detalhar a entrega de valor para o cliente da Oi Fibra na visão fim a fim (ciclo de vida do cliente), em nível de detalhe e aprofundamento. 3. Mapeamento do tipo de cliente (perfil, caracteristicas, segmentação, persona) para desenvolver soluções da Oi Fibra | F69: Oi Fibra | G69: Fernanda Fischer | J69: CONCLUÍDO | K69: Fabricio Bindi <fabricio.bindi@oi.net.br> | L69: Luis Filipe Meira <lfmeira@oi.net.br> | M69: Renato Elias <renato.elias@oi.net.br>
B70: Oi Fibra | C70: Customer data and offer management​ | D70: Estratégia de Aquisição | E70: 1. Responsável por todas as estratégias de aquisiçãode clientes da Oi Fibra. 2. Responsável por Definir a estratégia de Produtos ofertas e serviços. 3. Define e coordena a Estratégia de venda e atendimento do cliente (Omnicanalidade) | F70: Oi Fibra | G70: Fernanda Fischer | J70: CONCLUÍDO | K70: Fabricio Bindi <fabricio.bindi@oi.net.br> | L70: Luis Filipe Meira <lfmeira@oi.net.br> | M70: Renato Elias <renato.elias@oi.net.br>
B71: Oi Fibra | C71: Customer data and offer management​ | D71: Estratégia de Gestão de Base de Clientes | E71: 1. Responsável por todas as estratégias de Gestão da Base de cliente da Oi Fibra, considerando: a) ações de rentabilização, retenção e blindagem e fidelização de clientes b) ações para a gestão e redução do churn voluntário e involuntário de clientes 2. Responsável pelo acompanhamento da experiência do cliente propondo, em conjunto com a área de CX, ações de comunicação e relacionamento com a base | F71: Oi Fibra | G71: Fernanda Fischer | J71: CONCLUÍDO | K71: Fabricio Bindi <fabricio.bindi@oi.net.br> | L71: Luis Filipe Meira <lfmeira@oi.net.br> | M71: Francisco Tecles <francisco.tecles@oi.net.br>
B72: Oi Fibra | C72: Customer data and offer management​ | D72: Jornadas e Experiência do Cliente | E72: 1. Definir as jornadas propostas para o cliente Oi Fibra com uma visao da sua experiência em um cadeia de valor fim a fim. 2. Definir as principais métricas e Kpis para estas jornadas de modo a acompanhar a satisfação e experiência do cliente ao longo do seu ciclo de vida com a Oi. 3. Propor ajustes contínuos de melhoria desta jornada a partir dos dados analisados, minimizando pontos de atrito com o cliente e maximizando valor. 4. Co-construir com time de Estratégia e Proposição de Valor as jornadas garantindo que estas sejam viáveis economicamente para a Oi.* 5. Mapear e propor, em conjunto com as áreas, melhorias nos processos que impactam as jornadas dos clientes 6. Responsável pela estratégia e gestão das pesquisas de experiência e satisfação do cliente (NPS, CSAT e outras), co-construindo ações com as áreas responsáveis, que impacte na melhoria da satisfação dos clientes em cada uma das etapas da jornada. | F72: Oi Fibra | G72: Fernanda Fischer | J72: CONCLUÍDO | K72: Fabricio Bindi <fabricio.bindi@oi.net.br> | L72: Fernanda Cristina Lisboa Fischer <fernanda.fischer@oi.net.br> | M72: Thais Rodrigues Goncalves <thais.goncalves@oi.net.br>
B73: Oi Fibra | C73: Customer data and offer management​ | D73: Estratégia de Portfólio (produto, pricing e ofertas) | E73: 1. Definição da estratégia do Portfolio Oi Fibra, incluindo ofertas, serviços de valor agregado e produtos (SVA) para aquisição e base 2. Definição da estratégiado de Go to Market, incluindo estratégia de pricing (produto/sva/tributação) 3. Definição do publico alvo a partir clusterização de clientes prospect (através do mapeamento da concorrência) ou Base Pre definida para a Oi Fibra. 4. Qual o canal ou praça este produto, serviço e oferta será disponibilizado ao cliente da Oi Fibra. | F73: Oi Fibra | G73: Fernanda Fischer | J73: CONCLUÍDO | K73: Fabricio Bindi <fabricio.bindi@oi.net.br> | L73: Luis Filipe Meira <lfmeira@oi.net.br> | M73: Renato Elias <renato.elias@oi.net.br>
B74: Oi Fibra | C74: Customer data and offer management​ | D74: Desenvolvimento de negócios e produtos | E74: 1. Viabilizar e coordenar a implantação de produtos e serviços através das plataformas existentes ou a partir de novas soluções, viabilizando a comercialização do portfólio estratégicos da companhia: 2. Definir e alinhar priorização de requisitos (MVP) 3. Elaborar projeto e cronograma de implantação 4. Coordenar o processo de Business Simulation, homologando as entregas funcionais 5. Gestão da Mudança (rollout) junto as áreas impactadas 6. Gestão de backlog e orçamento de projeto | F74: Oi Fibra | G74: Fernanda Fischer | J74: CONCLUÍDO | K74: Fabricio Bindi <fabricio.bindi@oi.net.br> | L74: Luis Filipe Meira <lfmeira@oi.net.br> | M74: Renato Elias <renato.elias@oi.net.br>
B75: Oi Fibra | C75: Customer data and offer management​ | D75: Estratégia de Devices / ONT | E75: 1. Avaliação das características técnicas dos devices que compoem o produto Oi Fibra 2. Avaliação de custos de devices 3. Avaliação de performance de devices 4. Mapeamento da concorrência – benchmarking 5. Implementar as diretrizes de comunicação na ONT 6. Definição de direcionadores para aquisição de equipamentos, incluindo total cost para a Oi | F75: Oi Fibra | G75: Fernanda Fischer | J75: CONCLUÍDO | K75: Fabricio Bindi <fabricio.bindi@oi.net.br> | L75: Luis Filipe Meira <lfmeira@oi.net.br> | M75: Renato Elias <renato.elias@oi.net.br>
B76: Oi Fibra | C76: Customer data and offer management​ | D76: Comunicação Institucional | E76: 1. Responsável pela Estratégia, gestão e relacionamento com imprensa para fomentar as ambições de negocio da Nova Oi e seus clientes. 2. Responsável pela gestão e elaboração dos releases de negócio / regionais para imprensa relacionados ao negócio da Oi Fibra. 3. Responsável pela co-construção de realeases, eventos e patrocínios que potencializem a reputação da Oi frente à imprensa e formadores de opinião. | F76: Oi Fibra | G76: Fernanda Fischer | J76: CONCLUÍDO | K76: Fabricio Bindi <fabricio.bindi@oi.net.br> | L76: Livia Marquez Rocha <livia.marquez@oi.net.br>
B77: Oi Fibra | C77: Customer data and offer management​ | D77: Comunicação (marca) | E77: 1. Responsável por desenvolver estratégia de marca da Oi de acordo com a visão e missão da empresa. 2. Criação e gestão de ativos de marca 3. Garantir que todas as mensagens de comunicação estejam alinhadas aos guidelines de Marca. 4. Garantir a gestão, criação e distribuição de conteúdo para todas as plataformas proprietárias Oi (redes sociais, blog), além da gestão, criação e distribuição de conteúdos junto a parceiros de comunicação / influenciadores | F77: Oi Fibra | G77: Fernanda Fischer | J77: CONCLUÍDO | K77: Fabricio Bindi <fabricio.bindi@oi.net.br> | L77: Livia Marquez Rocha <livia.marquez@oi.net.br>
B78: Oi Fibra | C78: Customer data and offer management​ | D78: Estratégia de negociação e compra de mídia | E78: 1. Responsável pela gestão dos principais meios de mídia online e off-line alinhado a estratégia de negócio e comunicação da companhia. 2. Negociação com agências e veículos para compra de mídia online e off-line buscando sempre a eficiência e o melhor mix de meios. 3. Responsável pelo planejamento de campanhas criando os planos de mídia on /off da Oi Fibra e institucional. 4. Gestão direta sobre a estratégia e resultados de mídia paga de canais receptivos (fibra, oi place e novas soluções) e-commerce de fibra com definição dos veículos utilizados medindo as performances de venda, CPA e dispersão. 5. Elaboração das informações detalhadas dos KPIs de campanha de awareness e performance da companhia 6. Garantir separação de xml por produto junto à TI para mensuração e efetividade dos canais | F78: Oi Fibra | G78: Fernanda Fischer | J78: CONCLUÍDO | K78: Fabricio Bindi <fabricio.bindi@oi.net.br> | L78: Livia Marquez Rocha <livia.marquez@oi.net.br>
B79: Oi Fibra | C79: Customer data and offer management​ | D79: Trade Marketing | E79: 1. Responsável por diferenciar produtos e serviços no ponto de venda para maximizar resultados. 2. Desdobramento da Estratégia da comunicação padronizada por canal e região, executando ações para maximização de vendas por região. 3. Negociação e compras de mídia Regional a partir das diretrizes de comunicação. [MF 6.3.2] 4. Coordenar analises e abordagens regionais de mercado identificando contextos que impactem os clientes. 5. Desenvolvimento e coordenação das campanhas de incentivo regionais para potencializar as vendas em todos os canais, alinhado as politicas comerciais. | F79: Oi Fibra | G79: Fernanda Fischer | J79: CONCLUÍDO | K79: Fabricio Bindi <fabricio.bindi@oi.net.br> | L79: Livia Marquez Rocha <livia.marquez@oi.net.br>
B80: Oi Fibra | C80: Customer data and offer management​ | D80: Comunicação (mídia de performance) | E80: 1. Alavancar as vendas dos canais receptivos de produtos e serviços Oi com eficiência, minimizando a dispersão de cobertura, considerando a granularidade do negócio. 2. Maximizar a volumetria dos canais receptivos 3. Responsável pelo relacionamento com a agencia de mídia digital. 4. Criação de campanhas digitais que maximizem os canais receptivos em conjunto com agência. 5. Busca de novos formatos de mídia com objetivo de performance | F80: Oi Fibra | G80: Fernanda Fischer | J80: CONCLUÍDO | K80: Fabricio Bindi <fabricio.bindi@oi.net.br> | L80: Livia Marquez Rocha <livia.marquez@oi.net.br>
B81: Oi Fibra | C81: Customer data and offer management​ | D81: Estratégia de ferramentas, soluções e plataformas | E81: 1. Garantir que a estratégia de Negócio esteja refletida nos processos e ferramentas dos canais de venda / atendimento 2. Interface entre as áreas op. (regionais e canais de aquisição / atendimento / operações) para identificar necessidades de negócio e traduzir em soluções de processos e ferramentas 3. Propor melhorias para evolução das soluções (RTD, Order Entry, APP PAP), priorizando uma relação Omnichanel entre os canais 4. Priorizar as diferentes soluções propostas com base no VPL e foco estratégico 5. Especificar e viabilizar em conjunto com TI soluções de ferramentas sistêmicas que permitam maior otimização e eficiência operacional dos processos de venda/ Atendimento (foco em digitalização) 6. Automatização: Identificar melhorias contínuas nos processos e sistemas com foco em redução/eliminação de custos com Back Offices, sempre buscando a melhor experiência | F81: Oi Fibra | G81: Fernanda Fischer | J81: CONCLUÍDO | K81: Fabricio Bindi <fabricio.bindi@oi.net.br> | L81: Luis Filipe Meira <lfmeira@oi.net.br>
B82: Oi Fibra | C82: Customer data and offer management​ | D82: Operacionalização da Estratégia de Portfolio | E82: 1. Implementação de parâmetros operacionais para mailing: tabelas de oferta e layout para compatibilidade com canal 2. Execução e implantação das ofertas através da aprovação (jurídico, regulatório e tributário) e configuração de ofertas com parâmetros para Otimização de ARPU 3. Gestão e configuração do portfólio de oferta por pdv/canal 4. Suporte para construção de materiais de capacitação de produtos e ofertas 6. Coordenação da implantação de novas ofertas 7. Acompanhamento de performance KPIs | F82: Oi Fibra | G82: Fernanda Fischer | J82: CONCLUÍDO | K82: Fabricio Bindi <fabricio.bindi@oi.net.br> | L82: Luis Filipe Meira <lfmeira@oi.net.br> | M82: Renato Elias <renato.elias@oi.net.br>
B83: Oi Fibra | C83: Application and data management​ | D83: Monitoramento da experiência do cliente | E83: 1. Monitoramento dos principais KPI que refletem a experiência nas jornadas (contestação, ST, etc.) 2. Estabelecer as correlações dos principais indicadores com a Experiência do Cliente 3. Pesquisas ativas da satisfação e das jornadas 4. Gera o indicador NPS Global 5. Gera o indicador NPS das Jornadas 6. Pesquisas Ad Hoc 7. Definir as referencia para os KPIs da experiência 8. Aprofundamento, análises, conhecimento do cliente e insights para transformação da jornada do cliente 9. Acompanhar e Diagnosticar indicadores Regulatório, Rankings e consumidor.gov 10. Garante retroalimentação do monitoramento para empresa inteira | F83: Oi Fibra | G83: Fernanda Fischer | J83: CONCLUÍDO | K83: Fabricio Bindi <fabricio.bindi@oi.net.br> | L83: Fernanda Cristina Lisboa Fischer <fernanda.fischer@oi.net.br> | M83: Thais Rodrigues Goncalves <thais.goncalves@oi.net.br>
B84: Oi Fibra | C84: Customer data and offer management​ | D84: Patrocínio e Experiência | E84: 1. Interagir com diferentes stakeholders, desenvolvendo patrocínios/ eventos que fortaleçam a reputação da marca incentivando crescimento sustentável da empresa.] 2. Aumentar o awareness de fibra e presença regional criando eventos. 3. Co-criação com Trade para projetos de experiência regional 4. Criação e gestão de projetos incentivados para Oi 5. Alinhamento com Oi futuro para melhor integração das marcas e geração de oportunidades | F84: Oi Fibra | G84: Fernanda Fischer | J84: CONCLUÍDO | K84: Fabricio Bindi <fabricio.bindi@oi.net.br> | L84: Livia Marquez Rocha <livia.marquez@oi.net.br>
B85: Oi Fibra | C85: Customer data and offer management​ | D85: Gestão de contratos e pagamentos de parceiros de comunicação | E85: 1. Interface com a controladoria relacionada ao centro de custo da diretoria de comunicação para reports oficiais e visões gerenciais do orçamento. (atualmente ainda pacote PP e com corp) 2. Definição e acompanhamento de processos para pagamentos da área. Controle de orçamento mensal e trimestral de PP e comcorp, incluindo forecast. 3. Controle das especificidades dos pagamentos de mídia (via agencia, prazos diferentes por meio etc).Validação de RCs por cada frente: produção, mídia, trademarketing e pesquisas de marca. 4. Controle de verba de mídia de pacotes adjacentes (exemplos: DRC e Operações) 5. Gestão de contratos - verba e processo de pagamento dos fees incluindo success fee (agencias, parceiros e institutos) | F85: Oi Fibra | G85: Fernanda Fischer | J85: CONCLUÍDO | K85: Fabricio Bindi <fabricio.bindi@oi.net.br> | L85: Livia Marquez Rocha <livia.marquez@oi.net.br>
B86: Oi Fibra | C86: Customer data and offer management​ | D86: Planejamento de Vendas, Canais e S&OP | E86: 1. Garantir o ciclo de previsão de vendas e instalação dos processos de planejamento operacional de vendas incluindo metas (POVE) e S&OP - Sales and Operations Planning), abrangendo as Diretrizes da Oi Fibra e todos as premissas Comerciais (produtos, ofertas, capacidade de vendas de todos os canais e regionais, disponibilidade de rede por região) em conjunto com a Oi Fibra e Canais/Regionais. 2. Responsável por discutir e definir com o time de operações (Oi e Redes Neutras) a capacidade de instalação por ciclos quadrimestrais. (avaliar ajustes). 3. Planejamento e desdobramento orçamentário de gross. 4. Suporte ao modelo de roteirização, capacidade de vendas e delimitação das células de atuação. 5. Gestão do Custo Mínimo em garantia (S&OP x realização) 6. Co-estruturar junto ao trade a confecção da mecânica da campanha de incentivo de toda a força de vendas interna e externa bem como a apuração dos resultados. | F86: Oi Fibra | G86: Fernanda Fischer | J86: CONCLUÍDO | K86: Fabricio Bindi <fabricio.bindi@oi.net.br> | L86: Fernando Vairolatti Del Negro Fonseca (fernando.fonseca@oi.net.br)
B87: Oi Fibra | C87: Customer data and offer management​ | D87: Desenvolvimento, estruturação e implementação de Canais | E87: 1. Definir políticas, processos e procedimentos dos canais offline (PAP, PAPEPS, Teleagentes, entre outros); 2. Definir Política Comercial que garanta sustentabilidade da rede de distribuição e alcance as metas de vendas, receita, qualidade e gestão de custos; 3. Definir política de remuneração visando Buscar padrão de excelência no atendimento aos clientes, alinhados com a proposta de valor da Oi Fibra. 4. Garantir alavancas que garantam maior produtividade e qualidade aos canais 5. Identificar oportunidades de negócio pela otimização dos canais existentes ou desenvolvimento de novos canais 6. Coordenação Nacional dos canais com base nos indicadores de negócios (Produtividade, Qualidade das vendas, CAPU, Rentabilidade, Capilaridade, Resultados operacionais, etc.) 7. Implantar mecanismos para medir aderência dos PDVs aos processos e práticas definidos pelo Canal e demais áreas da companhia. 8. Especificar e utilizar ferramentas de avaliação de desempenho dos Canais e Jornada de Venda 9. Identificar necessidades de revisão/modificação da trilha de capacitação incentivando crescimento individual e da equipe 10. Demandar desenvolvimento de materiais de trade e capacitação 11. Garantir a comunicação entre os Canais e demais áreas da companhia | F87: Oi Fibra | G87: Fernanda Fischer | J87: CONCLUÍDO | K87: Fabricio Bindi <fabricio.bindi@oi.net.br> | L87: Luis Filipe Meira <lfmeira@oi.net.br> | M87: Alexandre Guazelli <alexandre.guazelli@oi.net.br>
B88: Oi Fibra | C88: Customer data and offer management​ | D88: Operação de Canais Nacionais de Vendas | E88: 1. Gestão de relacionamento com EPS e parceiros de vendas nacionais (WEB/Afiliados/Grande Varejo/TLV) 2. Prospecção de novos parceiros e gestão de parceiros de vendas nacionais 3. Responsável pela entrega do resultado dos canais (gestão da performance) 4.Gerir e acompanhar os principais indicadores de qualidade (churn, FPD, aproveitamento e eficácia) 5. Gestão dos indicadores operacionais do dia-a-dia da operação (quartil, tx. de conversão, produtividade, TMA, TMV, etc) 6. Gestão do funil de vendas 7. Otimizar a relação dimensionamento x custo x disponibilidade de mailing por EPS/Operação 8. Garantir a adequação as demandas Regulatórias/Anatel 9. Especificação do modelo de atuação e rotina operacional dos canais (acessos, procedimentos, processos, etc) | F88: Oi Fibra | G88: Fernanda Fischer | J88: CONCLUÍDO | K88: Fabricio Bindi <fabricio.bindi@oi.net.br> | L88: Giovani Cristiano Da Silva <giovani.silva@oi.net.br>
B89: Oi Fibra | C89: Customer data and offer management​ | D89: Operação de canais Regionais de Vendas | E89: 1. Operar os canais regionais de vendas desdobrando as estratégias da Oi Fibra garantindo aderência aos processos e ferramentas 2. Garantir a Aderência dos parceiros em relação modelo de gestão Oi (gestão operacional, ambientação, apresentação pessoal, etc) 3. Entregar resultados nos Canais de Vendas Regionais (operacionais, qualidade, receita, custo, etc) através de acompanhamento diário de indicadores 4. Gestão de capilaridade e produtividade dos canais regionais 5. Dimensionamento de parceiros para entrega de resultados 6. Esteira de prospecção e credenciamento de novos parceiros 7. Fomento de campanhas e ações de vendas visando aceleração de resultados e/ou KPIs específicos 8. Garantir adequação dos canais de vendas regionais frente as regras da Anatel e Órgãos de Defesa do Cliente | F89: Oi Fibra | G89: Fernanda Fischer | J89: CONCLUÍDO | K89: Fabricio Bindi <fabricio.bindi@oi.net.br> | L89: Giovani Cristiano Da Silva <giovani.silva@oi.net.br>
B90: Oi Fibra | C90: Customer data and offer management​ | D90: Operação de trade regional | E90: 1. Executar as atividades de Trade garantindo visibilidade das ofertas e benefícios aos Clientes conforme estratégia; 2. Padronização e aderência das comunicações, estruturação dos PDVs e outras formas de contato com o Cliente conforme estratégia de comunicação e diretrizes da Oi Fibra; 3. Planejamento, produção e logística dos enxovais de campanhas e comunicações de todos os canais de vendas. 4. Gerir orçamentos de verbas regionais (SAV, MAV, VPC e Mídia) com ganhos de rentabilização e gestão de contratos dos fornecedores (agencias, gráfica) 5. Engajar os times de vendas na alavancagem de resultados e disseminação da cultura organizacional através de campanhas de incentivo e endomarketing 6. Benchmark de produtos, oferta e comunicação dos concorrentes 7. Suporte aos Canais de vendas no planejamento e execução das ações de vendas. 8. Gerir a visibilidade das ofertas e serviços através de canais de comunicação/veículos de mídias regionalizadas com alto impacto, frequência, visibilidade, rentabilização e convergência | F90: Oi Fibra | G90: Fernanda Fischer | J90: CONCLUÍDO | K90: Fabricio Bindi <fabricio.bindi@oi.net.br> | L90: Livia Marquez Rocha <livia.marquez@oi.net.br>
B91: Oi Fibra | C91: Customer data and offer management​ | D91: Planejamento das operações de vendas regionais | E91: 1. Gerar informacional dos indicadores suportando a gestão da rotina e resultados (operacionais, qualidade, receita, despesas) 2. Disponibilização dos indicadores de suporte ao negócio (VL, gross, produtividade, capilaridade, quartil, eficácia, FPD, churn, INAD, IQ, custos, saúde financeira, acurácia, TKP) 3. Elaboração e desdobramento das metas POVE e Remuneração Variável de forma granular (UF, cidade, parceiro, GV, GC) 4. Diagnóstico dos desvios com mapeamento das oportunidades e melhorias (PDCA/SDCA) 5. Participação na construção do plano de HPs regional de curto e longo Prazo 6. apoiar no mapeamento da concorrência [MF4-1] 7. Suporte a Gestão regional (i), canais nacionais (ii), confecção de materiais, painéis de controle, padronização entre Regiões e GVs | F91: Oi Fibra | G91: Fernanda Fischer | J91: CONCLUÍDO | K91: Fabricio Bindi <fabricio.bindi@oi.net.br> | L91: Giovani Cristiano Da Silva <giovani.silva@oi.net.br>
B92: Oi Fibra | C92: Customer data and offer management​ | D92: Planejamento das operações de base | E92: 1. Garantir aderência dos contratos à estratégia dos canais de relacionamento da Oi Fibra, refletindo em menor preço e maior qualidade através de RFP’s e revisão dos contratos/prestadores atuais e avaliação de novos parceiros. 2. Criação e gestão de Orçamento/budget Opex das operações 3. Apuração do faturamento de todos os contratos (apuração, emissão de pedidos, acompanhamento fim a fim do fluxo de pagamento dos fornecedores). 4. Responsável pelo Forecast de chamadas para todas as operações (call Center), garantindo o alinhamento da estratégia Oi 5. Monitorar e gerenciar o roteamento das chamadas (24 x 7) entre todos os parceiros (EPSs), garantindo o equilíbrio do nível de serviço entre os parceiro 6. Gerenciar a distribuição e migrações de volume no ambiente Oi (roteamento) 7. Acompanhamento, suporte e ações para correção de desvios com as áreas de Planejamento de cada fornecedor e áreas de operação 8. Gerar informacional dos indicadores suportando a gestão da rotina e resultados (operacionais, qualidade, despesas) 9. Criação e gestão de Orçamento/budget Capex do canal 10. Gestão de demandas Regulatórias (Não perturbe, cautelar, etc) 11. Cadastramento de novos parceiros | F92: Oi Fibra | G92: Fernanda Fischer | J92: CONCLUÍDO | K92: Fabricio Bindi <fabricio.bindi@oi.net.br> | L92: Jomerson Da Silva Almeida <jomerson.almeida@oi.net.br>
B93: Oi Fibra | C93: Customer data and offer management​ | D93: Acompanhamento e Recuperação da cadeia de instalação do cliente (CRV) | E93: 1. Garantir eficiência na Instalação, com maior agilidade no tratamento das pendências, reduzindo atrito com o cliente e custos de reagendamento, em conjunto com os times de Operações, Vendas, Planejamento e Parceiro de Rede Neutra. 2. Monitorar as Ordens de Instalação e Serviço em pendenciamento cliente e parte das pendências técnicas; 3. Garantir o tratamento de pendenciamento seja executado conforme diretrizes estratégicas da Oi Fibra seguindo segmentação de clientes; 4. Realizar a gestão do pendenciamento na esteira de obra e slots para agendamento; 5. Realizar a interface com o cliente para agendamento e tratamento das pendencias 6. Suportar o técnico em campo no tratamento de Correção de OS, Reagendamento e Desistência do Cliente; 7. Suportar o time de Vendas contingenciando falhas sistêmicas | F93: Oi Fibra | G93: Fernanda Fischer | J93: CONCLUÍDO | K93: Fabricio Bindi <fabricio.bindi@oi.net.br> | L93: Fernando Vairolatti Del Negro Fonseca (fernando.fonseca@oi.net.br) | M93: volpe
B94: Oi Fibra | C94: Customer data and offer management​ | D94: Operação de Fidelização e Rentabilização | E94: 1. Gestão de relacionamento com EPS e parceiros (Canais Digitais e Humanos) 2. Garantir a implementação da estratégia em todos os canais 3. Prospecção de novos parceiros e soluções 4. Responsável pela entrega do resultado dos canais 5. Gerir e acompanhar os principais indicadores de qualidade e performance 6. Gestão dos indicadores operacionais do dia-a-dia da operação (quartil, tx. de conversão, produtividade, TMA, TMV, etc) 7. Gestão do funil de rentabilização/fidelização 8. Otimizar a relação dimensionamento x custo x disponibilidade de mailing pelos Canais 9. Execução de pilotos e novas iniciativas 10. Garantir a adequação as demandas Regulatórias/Anatel 11. P&L e LTV do Canal 12. Definição da politica de remuneração 13. Especificação do modelo de atuação e rotina operacional dos canais (acessos, procedimentos, processos, campanhas, etc) 14. Gestão contratual dos parceiros/ferramentas | F94: Oi Fibra | G94: Fernanda Fischer | J94: CONCLUÍDO | K94: Fabricio Bindi <fabricio.bindi@oi.net.br> | L94: Giovani Cristiano Da Silva <giovani.silva@oi.net.br> | M94: Luiz Marcelo Sencier <luiz.sencier@oi.net.br> | N94: Juliana Pimenta <juliana.ribeiro@oi.net.br>
B95: Oi Fibra | C95: Customer care​ | D95: Operações de Atendimento | E95: 1. Responsável por coordenar junto às EPSs e parceiros (canais digitais e humanos) o atendimento aos clientes da Oi Fibra 2. Garantir a implementação da estratégia em todos os canais digitais e humanos 3. Quando necessario, responsável por prospectar de novos parceiros e soluções 4. Responsável pela gestão de resultados de todos os indicadores das operações de atendimento (quartil, FCR, nota de satisfação, tx. de conversão, produtividade, TMA, rate, etc) 5. Gestão do atendimento eletrônico (URA) 6. Otimizar a relação dimensionamento x custo x disponibilidade de mailing pelos Canais 7. Execução de pilotos e novas iniciativas 8. Garantir a adequação as demandas Regulatórias/Anatel 9. Especificação do modelo de atuação e rotina operacional dos canais (acessos, procedimentos, processos, campanhas, etc) 10. Gestão contratual dos parceiros/ferramentas | F95: Oi Fibra | G95: Fernanda Fischer | J95: CONCLUÍDO | K95: Fabricio Bindi <fabricio.bindi@oi.net.br> | L95: Jomerson Da Silva Almeida <jomerson.almeida@oi.net.br>
B96: Oi Fibra | C96: Customer care​ | D96: Operação de Ouvidoria | E96: 1. Implementar a estratégia de atuação nas operações de Ouvidoria (Ouvidoria e BO Anatel) 2. Quando necessário, fazer relacionamento com Anatel 3. Retroalimentar as áreas internas para endereçar a causa raiz dos problemas dos clientes identiuficados em atendimentos e reclamações 4. Garantir a adequação as demandas Regulatórias / Anatel 5. Gestão de relacionamento com EPS e parceiros 6. Responsável pela entrega do resultado conforme metas definidas pela Anatel 7. Gerir e acompanhar os principais indicadores de qualidade e performance 8. Dimensionamento da operação para garantir Nivel de Serviço 9. Especificação da rotina operacional dos canais (acessos, procedimentos, processos, campanhas, etc) 10. Gestão contratual dos parceiros/ferramentas | F96: Oi Fibra | G96: Fernanda Fischer | J96: CONCLUÍDO | K96: Mateus Affonso Bandeira <mateusbandeira2@oi.net.br> | L96: Andressa Mourao <andressa.mourao@oi.net.br>
B97: Oi Fibra | C97: Customer care​ | D97: Operação de Retenção | E97: 1. Gestão de relacionamento com EPS e parceiros (Canais Digitais e Humanos) 2. Garantir a implementação da estratégia em todos os canais (Ativo, Receptivo, RACO e App) 3. Prospecção de novos parceiros e soluções 4. Responsável pela entrega do resultado dos canais 5. Gerir e acompanhar os principais indicadores de qualidade e performance 6. Gestão dos indicadores operacionais do dia-a-dia da operação (quartil, tx. de cancelamento, delta ticket, NS, receita retida, etc) 7. Gestão do funil de retenção 8. Otimizar a relação dimensionamento x custo x tx retenção 9. Operacionalização da estratégia de ativo de reversão 10. Execução de pilotos e novas iniciativas 11. Garantir a adequação as demandas Regulatórias/Anatel 12. P&L e LTV da operação 13. Definição da politica de remuneração 14. Especificação do modelo de atuação e rotina operacional dos canais (acessos, procedimentos, processos, campanhas, etc) 15. Gestão contratual dos parceiros/ferramentas | F97: Oi Fibra | G97: Fernanda Fischer | J97: CONCLUÍDO | K97: Fabricio Bindi <fabricio.bindi@oi.net.br> | L97: Jomerson Da Silva Almeida <jomerson.almeida@oi.net.br>
B98: Oi Fibra | C98: Customer care​ | D98: Estratégia e operação da comunicação com o cliente | E98: 1. Desenvolvimento das jornadas de comunicação com clientes através de canais diretos como e-mail, SMS, WhatsApp, Push, etc) com objetivos: 2. Comerciais (vender, rentabilizar e blindar) 3. Transacionais (faturar, cobrar, agendar...) 4. Relacionais (engajar, celebrar, reconhecer) 5. Care/Incentivos (meio de pagto, uso,...) 6. Definição da estratégia operacional para otimização do resultado (volume de disparos, melhor horário, recorrência...) 7. Martech: Estruturação do MKT Cloud operacionalizando estratégia da Oi Fibra, segmentação de disparos e implantação de estratégia de CRM (IPs, Reputação, Lógica) 8. Parametrização dos dashboards com os principais indicadores de sucesso e gestão na ferramenta | F98: Oi Fibra | G98: Fernanda Fischer | J98: CONCLUÍDO | K98: Fabricio Bindi <fabricio.bindi@oi.net.br> | L98: Fernanda Cristina Lisboa Fischer <fernanda.fischer@oi.net.br> | M98: Thais Rodrigues Goncalves <thais.goncalves@oi.net.br>
B99: Oi Fibra | C99: Customer data and offer management​ | D99: Estratégia de HP / Definição da demanda de HP e Geomarketing | E99: 1. Definição da estratégia de disponibilização de HP por região, alinhada à estratégia de aquisição de clientes da Oi Fibra 2. Implementar e gerenciar processo que garantam direcionamento eficiente de investimentos (Opex) de expansão de rede da Oi Fibra 3. Gestão para Garantir em conjunto com operações e Parceiro de rede neutra a execução do plano de construção de rede dentro do plano definido, potencializando a performance de Vendas 4. Acompanhar a Gestão de qualidade dos HPs construidos (cadastros, S/N, solicitados, viabilidade, etc), bem como sua taxa de ocupação 5. Atendimento aos CDDs de Geomarketing 6. Criar inteligência de identificação de mercado potenciais a serem atendidos com maior capilaridade de Fibra com melhorias da Oi Fibra 7.Identificar oportunidades de mercado na planta de HPs implantados para melhoria de performance e redução do custo de MakeWhole (MW) da Oi Fibra 8. Gestão/Validação do custo de MakeWhole (MW) no contrato juto ao Parceiro de rede neutra 9. Controle de performance de Take Up | F99: Oi Fibra | G99: Fernanda Fischer | J99: CONCLUÍDO | K99: Fabricio Bindi <fabricio.bindi@oi.net.br> | L99: Fernando Vairolatti Del Negro Fonseca (fernando.fonseca@oi.net.br)
B100: Oi Fibra | C100: Customer data and offer management​ | D100: Liberação comercial de HP | E100: 1. Mapear principais etapas e estruturar processo de liberação comercial de Novas Localidades, Municípios e e/ou Estações de Fibra de acordo com as diretrizes da Oi Fibra. 2. Garantir a mobilização das diversas áreas OI e interface com o fornecedor de rede neutra (Ex.:Vtal) para a execução das atividades do checklist de novas localidades FTTH e o lançamento na data planejada. 3. Definir e monitorar os SLAs de cada etapa, atuando como PMO na coordenação das atividades e correção dos desvios. | F100: Oi Fibra | G100: Fernanda Fischer | J100: CONCLUÍDO | K100: Fabricio Bindi <fabricio.bindi@oi.net.br> | L100: Fernando Vairolatti Del Negro Fonseca (fernando.fonseca@oi.net.br)
B101: Oi Fibra | C101: Customer data and offer management​ | D101: Operação orçamentária (pagamento de parceiros / comissionamento / compra de conteúdo / revenue assurance / controladoria) | E101: 1. Responsável pela estratégia orçamentária da Operação Oi Fibra, garantindo as diretrizes corporativas, bem como a execução operacional do serviço ao cliente | F101: Oi Fibra | G101: Fernanda Fischer | J101: CONCLUÍDO | K101: Fabricio Bindi <fabricio.bindi@oi.net.br> | L101: Fernando Vairolatti Del Negro Fonseca (fernando.fonseca@oi.net.br)
...

Sheet Anexo A - DIN TODOS OS SERVIÇOS
A1: CONCLUÍDOS | E1: PENDENTES | H1: Em revisão
A2: Status Anexo A | B2: (Vários itens) | E2: Status Anexo A | F2: (Vários itens) | H2: Status Anexo A | I2: (Vários itens)
A4: Rótulos de Linha | B4: Contagem de Status Anexo A | E4: Rótulos de Linha | F4: Contagem de Status Anexo A | H4: Rótulos de Linha | I4: Contagem de Status Anexo A
A5: Operações de Rede e SI | B5: 69 | E5: Total Geral | H5: Total Geral
A6: RH | B6: 60
A7: Oi Fibra | B7: 48
A8: Sistemas TI | B8: 26
A9: Atendimento | B9: 14
A10: Tesouraria e Análise de Desempenho | B10: 11
A11: Faturamento | B11: 11
A12: Arrecadação e Cobrança | B12: 9
A13: Tráfego | B13: 9
A14: Parceiro de Negócio | B14: 8
A15: Tributos/Fiscal | B15: 6
A16: Contabilidade | B16: 5
A17: Jurídico Consumidor | B17: 5
... A36: Total Geral | B36: 319

Sheet Anexo A -DIN2 TODOS OS SERVIÇOS
E2: CONCLUÍDO (VALIDADO + EXCLUÍDO) | H2: PENDENTE | K2: EM REVISÃO
B3: Áreas | C3: Total de tópicos | E3: Volume | F3: % | H3: Volume | I3: % | K3: Volume | L3: %
B4: Ações restritas | C4: 3 | E4: =IFERROR(VLOOKUP(B4,'Anexo A - DIN TODOS OS SERVIÇOS'!A:B,2,0),"0") -> 3 | F4: =E4/$C$35 -> 0.0094043887 | H4: =IFERROR(VLOOKUP(B4,'Anexo A - DIN TODOS OS SERVIÇOS'!E:F,2,0),"0") -> 0 | I4: =H4/$C$35 -> 0 | K4: =IFERROR(VLOOKUP(B4,'Anexo A - DIN TODOS OS SERVIÇOS'!H:I,2,0),"0") -> 0 | L4: =K4/$C$35 -> 0
B5: Arrecadação e Cobrança | C5: 9 | E5: =IFERROR(VLOOKUP(B5,'Anexo A - DIN TODOS OS SERVIÇOS'!A:B,2,0),"0") -> 9 | F5: =E5/$C$35 -> 0.028213166 | H5: =IFERROR(VLOOKUP(B5,'Anexo A - DIN TODOS OS SERVIÇOS'!E:F,2,0),"0") -> 0 | I5: =H5/$C$35 -> 0 | K5: =IFERROR(VLOOKUP(B5,'Anexo A - DIN TODOS OS SERVIÇOS'!H:I,2,0),"0") -> 0 | L5: =K5/$C$35 -> 0
B6: Atendimento | C6: 14 | E6: =IFERROR(VLOOKUP(B6,'Anexo A - DIN TODOS OS SERVIÇOS'!A:B,2,0),"0") -> 14 | F6: =E6/$C$35 -> 0.043887147 | H6: =IFERROR(VLOOKUP(B6,'Anexo A - DIN TODOS OS SERVIÇOS'!E:F,2,0),"0") -> 0 | I6: =H6/$C$35 -> 0 | K6: =IFERROR(VLOOKUP(B6,'Anexo A - DIN TODOS OS SERVIÇOS'!H:I,2,0),"0") -> 0 | L6: =K6/$C$35 -> 0
B7: Contabilidade | C7: 5 | E7: =IFERROR(VLOOKUP(B7,'Anexo A - DIN TODOS OS SERVIÇOS'!A:B,2,0),"0") -> 5 | F7: =E7/$C$35 -> 0.015673981 | H7: =IFERROR(VLOOKUP(B7,'Anexo A - DIN TODOS OS SERVIÇOS'!E:F,2,0),"0") -> 0 | I7: =H7/$C$35 -> 0 | K7: =IFERROR(VLOOKUP(B7,'Anexo A - DIN TODOS OS SERVIÇOS'!H:I,2,0),"0") -> 0 | L7: =K7/$C$35 -> 0
B8: Crédito | C8: 1 | E8: =IFERROR(VLOOKUP(B8,'Anexo A - DIN TODOS OS SERVIÇOS'!A:B,2,0),"0") -> 1 | F8: =E8/$C$35 -> 0.0031347962 | H8: =IFERROR(VLOOKUP(B8,'Anexo A - DIN TODOS OS SERVIÇOS'!E:F,2,0),"0") -> 0 | I8: =H8/$C$35 -> 0 | K8: =IFERROR(VLOOKUP(B8,'Anexo A - DIN TODOS OS SERVIÇOS'!H:I,2,0),"0") -> 0 | L8: =K8/$C$35 -> 0
B9: DA | C9: 3 | E9: =IFERROR(VLOOKUP(B9,'Anexo A - DIN TODOS OS SERVIÇOS'!A:B,2,0),"0") -> 3 | F9: =E9/$C$35 -> 0.0094043887 | H9: =IFERROR(VLOOKUP(B9,'Anexo A - DIN TODOS OS SERVIÇOS'!E:F,2,0),"0") -> 0 | I9: =H9/$C$35 -> 0 | K9: =IFERROR(VLOOKUP(B9,'Anexo A - DIN TODOS OS SERVIÇOS'!H:I,2,0),"0") -> 0 | L9: =K9/$C$35 -> 0
B10: Faturamento | C10: 11 | E10: =IFERROR(VLOOKUP(B10,'Anexo A - DIN TODOS OS SERVIÇOS'!A:B,2,0),"0") -> 11 | F10: =E10/$C$35 -> 0.034482759 | H10: =IFERROR(VLOOKUP(B10,'Anexo A - DIN TODOS OS SERVIÇOS'!E:F,2,0),"0") -> 0 | I10: =H10/$C$35 -> 0 | K10: =IFERROR(VLOOKUP(B10,'Anexo A - DIN TODOS OS SERVIÇOS'!H:I,2,0),"0") -> 0 | L10: =K10/$C$35 -> 0
B11: Jurídico Consumidor | C11: 5 | E11: =IFERROR(VLOOKUP(B11,'Anexo A - DIN TODOS OS SERVIÇOS'!A:B,2,0),"0") -> 5 | F11: =E11/$C$35 -> 0.015673981 | H11: =IFERROR(VLOOKUP(B11,'Anexo A - DIN TODOS OS SERVIÇOS'!E:F,2,0),"0") -> 0 | I11: =H11/$C$35 -> 0 | K11: =IFERROR(VLOOKUP(B11,'Anexo A - DIN TODOS OS SERVIÇOS'!H:I,2,0),"0") -> 0 | L11: =K11/$C$35 -> 0
B12: Logística | C12: 2 | E12: =IFERROR(VLOOKUP(B12,'Anexo A - DIN TODOS OS SERVIÇOS'!A:B,2,0),"0") -> 2 | F12: =E12/$C$35 -> 0.0062695925 | H12: =IFERROR(VLOOKUP(B12,'Anexo A - DIN TODOS OS SERVIÇOS'!E:F,2,0),"0") -> 0 | I12: =H12/$C$35 -> 0 | K12: =IFERROR(VLOOKUP(B12,'Anexo A - DIN TODOS OS SERVIÇOS'!H:I,2,0),"0") -> 0 | L12: =K12/$C$35 -> 0
B13: Operações de Rede e SI | C13: 69 | E13: =IFERROR(VLOOKUP(B13,'Anexo A - DIN TODOS OS SERVIÇOS'!A:B,2,0),"0") -> 69 | F13: =E13/$C$35 -> 0.21630094 | H13: =IFERROR(VLOOKUP(B13,'Anexo A - DIN TODOS OS SERVIÇOS'!E:F,2,0),"0") -> 0 | I13: =H13/$C$35 -> 0 | K13: =IFERROR(VLOOKUP(B13,'Anexo A - DIN TODOS OS SERVIÇOS'!H:I,2,0),"0") -> 0 | L13: =K13/$C$35 -> 0
B14: Produtos | C14: 1 | E14: =IFERROR(VLOOKUP(B14,'Anexo A - DIN TODOS OS SERVIÇOS'!A:B,2,0),"0") -> 1 | F14: =E14/$C$35 -> 0.0031347962 | H14: =IFERROR(VLOOKUP(B14,'Anexo A - DIN TODOS OS SERVIÇOS'!E:F,2,0),"0") -> 0 | I14: =H14/$C$35 -> 0 | K14: =IFERROR(VLOOKUP(B14,'Anexo A - DIN TODOS OS SERVIÇOS'!H:I,2,0),"0") -> 0 | L14: =K14/$C$35 -> 0
B15: Regulatório | C15: 4 | E15: =IFERROR(VLOOKUP(B15,'Anexo A - DIN TODOS OS SERVIÇOS'!A:B,2,0),"0") -> 4 | F15: =E15/$C$35 -> 0.012539185 | H15: =IFERROR(VLOOKUP(B15,'Anexo A - DIN TODOS OS SERVIÇOS'!E:F,2,0),"0") -> 0 | I15: =H15/$C$35 -> 0 | K15: =IFERROR(VLOOKUP(B15,'Anexo A - DIN TODOS OS SERVIÇOS'!H:I,2,0),"0") -> 0 | L15: =K15/$C$35 -> 0
... B35: Total Geral | C35: 319 | E35: =IFERROR(VLOOKUP(B35,'Anexo A - DIN TODOS OS SERVIÇOS'!A:B,2,0),"0") -> 319 | F35: =E35/$C$35 -> 1 | H35: =IFERROR(VLOOKUP(B35,'Anexo A - DIN TODOS OS SERVIÇOS'!E:F,2,0),"0") -> 0 | I35: =H35/$C$35 -> 0 | K35: =IFERROR(VLOOKUP(B35,'Anexo A - DIN TODOS OS SERVIÇOS'!H:I,2,0),"0") -> 0 | L35: =K35/$C$35 -> 0

Sheet Anexo A -DRAF TODOS OS SERVIÇOS
A1: Topicos
B2: ´MARS | C2: CLIENTCO | F2: 45401 | G2: 45408
A3: Total | B3: 148 | C3: 159 | E3: Pendente | F3: 113 | G3: 95
E4: Concluído | F4: 46 | G4: 64
B23: PENDENTE | C23: =SUM(C24:C33) -> 97 | G23: Rótulos de Linha | H23: Contagem de Status Anexo A
B24: Operações de Rede e SI | C24: 59 | G24: Operações de Rede e SI | H24: 59
B25: Atendimento | C25: 15 | G25: Atendimento | H25: 15
B26: Sistemas TI | C26: 11 | G26: Sistemas TI | H26: 11
B27: Ura | C27: 2 | G27: Ura | H27: 2
B28: Suporte Técnico | C28: 2 | G28: Suporte Técnico | H28: 2
B29: RH | C29: 2 | G29: RH | H29: 2
B30: Logística | C30: 2 | G30: Logística | H30: 2
B31: RA | C31: 2 | G31: RA | H31: 2
B32: Crédito | C32: 1 | G32: Crédito | H32: 1
B33: Vendas (var/ Emp) | C33: 1 | G33: Vendas (var/ Emp) | H33: 1
H39: Concluídos | I39: %
G40: Total | H40: 162 | I40: 0
G41: 45401 | H41: 46 | I41: =H41/H40 -> 0.28395062
G42: 45408 | H42: 64 | I42: =H42/H40 -> 0.39506173
H53: Concluídos | I53: %
G54: Total | H54: 317 | I54: =H54/H54 -> 1
G55: 45399 | H55: 0 | I55: =H55/H54 -> 0
G56: 45401 | H56: 46 | I56: =H56/H54 -> 0.14511041
G57: 45408 | H57: 64 | I57: =H57/H54 -> 0.20189274
G58: 45411 | H58: 95 | I58: =H58/H54 -> 0.29968454
G59: 45414 | H59: 104 | I59: =H59/H54 -> 0.32807571
G60: 45420 | H60: 88 | I60: =H60/H54 -> 0.27760252
G61: 45427 | H61: 162 | I61: =H61/H54 -> 0.51104101
G62: 45433 | H62: 304 | I62: =H62/H54 -> 0.95899054
G63: 45435 | H63: 314 | I63: =H63/H54 -> 0.99053628
G64: 45448 | H64: 317 | I64: =H64/H54 -> 1
G67: 45432 | H67: 237 | I67: =H67/H54 -> 0.74763407

Sheet Draft Anexo A - Dinâmica
B2: Rótulos de Linha | C2: Volume
B3: Access network O&M​ | C3: 3
B4: Customer care​ | C4: 11
B5: Core network O&M​ | C5: 17
B6: Application and data management​ | C6: 20
B7: Bill-to-cash​ | C7: 43
B8: Customer data and offer management​ | C8: 46
B9: Admin personnel​ | C9: 75
B10: Total Geral | C10: 215
B19: Rótulos de Linha | C19: Contagem de VP
B20: Auditoria e GRC | C20: 3
B21: Regulatório e Institucional | C21: 5
B22: Jurídico | C22: 8
B23: Suporte ao Negócio | C23: 8
B24: Operações de Redes e SI | C24: 11
B25: Tecnologia | C25: 19
B26: Oi Fibra | C26: 48
B27: Finanças e Relações com investidores | C27: 55
B28: Pessoas & Cultura | C28: 58
B29: Total Geral | C29: 215

Sheet Draft Anexo A
B2: VP | C2: Resumo dos serviços descritos no TSA. | D2: Topicos | E2: Descrição
B3: Auditoria e GRC | C3: Bill-to-cash​ | D3: Riscos e Controles | E3: - Revisão, atualização e teste de controles do Ambiente de Controles Internos da Companhia que permeiam todos os processos; - Gestão das Alçadas da Companhia que permeiam as principais atividades de aprovação; - Avaliação de Riscos conforme demanda das áreas; - Gestão dos Riscos Corporativos; - Gestão dos documentos da Companhia; - GCN que podem envolver incidentes/crises que impactam o serviço da Fibra.
B4: Auditoria e GRC | C4: Bill-to-cash​ | D4: Conformidade e Sustentabilidade | E4: - Gestão do canal e atendimento às solicitações de direitos previstos na LGPD por parte de titulares de dados pessoais; - Avaliação e adequação de contratos e editais, sob o aspecto de privacidade e proteção de dados pessoais, com fornecedores, parceiros e clientes (empresariais); - Manutenção do registro de operações de tratamento de dados pessoais, na forma do art. 37 da LGPD; - Identificação e registro de transferências internacionais de dados pessoais na forma do art. 33 da LGPD; - Identificação, avaliação e tratamento de riscos de privacidade em processos e projetos da Companhia; - Gestão, tratamento e comunicação - sob demanda - de eventuais incidentes de segurança que envolvam dados pessoais; - Resposta à ofícios e requerimentos de autoridades públicas, relacionados à privacidade; - Gestão do canal de denúncias e apuração de relatos; - Avaliação e adequação da cláusula de Compliance em contratos e editais; - Realização de análise de integridade de terceiros e colaboradores; - Realização de testes detectivos de conflitos de interesse; pagamentos à agentes públicos; doações; Brindes e Presentes e etc; - Resposta à Due Diligence de Terceiros, Parceiros; Investidores e Clientes; - Realização de processos de Partes Relacionadas; Acompanhamento de relacionamento com países em lista de sanções internacionais.
B5: Auditoria e GRC | C5: Bill-to-cash​ | D5: Auditoria Interna | E5: - Apuração de casos fraude; - Auditoria de sistemas e processos que permeiam toda a Cia de acordo com o plano aprovado; - Acompanhamento e “reteste” de ações corretivas; - Monitoramento de fraude em processos críticos.
B6: Finanças e Relações com investidores | C6: Bill-to-cash​ | D6: Execução de ciclos de Billings​ | E6: - A Oi deverá executar o processo de faturamento de terminais fibra, mantendo os sistemas, regras e processos atuais, até a migração total desses clientes. - Execução de todos os ciclos de billings (majoritários e minoritários) em todos os sistemas de faturamento existentes no parque de TI. - Resolução dos problemas encontrados durante o processamento.
B7: Finanças e Relações com investidores | C7: Bill-to-cash​ | D7: Tarifação de chamadas, dados e eventos ​ | E7: - Realização do processo de Tarifação de Voz, SVA e 0500 mantendo os sistemas, regras, processos e produtos e ofertas atuais, até a migração total desses clientes. - Resolução dos problemas encontrados durante o processamento.
B8: Finanças e Relações com investidores | C8: Bill-to-cash​ | D8: Emissão de termos de quitação​ | E8: - Emissão do termo de quitação referentes aos pagamentos das últimas faturas dos clientes fibra. - Resolução dos problemas encontrados durante o processamento. - Todas as pendências de emissão dos termos de quitação anteriores a data do fechamento do contrato deverão ser regularizadas.
B9: Finanças e Relações com investidores | C9: Bill-to-cash​ | D9: Validação do billings gerados - consistência, qualidade e confiabilidade ​ | E9: - A Oi irá executar o processo de validação prévia de faturas de terminais fibra, mantendo os sistemas, regras e processos atuais, até a migração total desses clientes. - Corrigir e reportar o tratamento adotado em caso de desvios identificados mantendo os sistemas, regras, processos e performance atuais, até a migração total desses clientes. -Executar as validações de consistência sobre o ciclo de billing executado.
B10: Finanças e Relações com investidores | C10: Bill-to-cash​ | D10: Disponibilização de faturas online e customizadas ​ | E10: - Oi irá disponibilizar as faturas de terminais fibra, mantendo os sistemas, regras e processos atuais, até a migração total desses clientes, nos formatos e layout atuais (online e customizadas) para clientes varejo e empresarial. - Carga dos spools faturados nas ferramentas que disponibilizam online os documentos de faturamento. - Resolução dos problemas encontrados durante o processamento. - Eventuais necessidades de alterações deverão ser discutidas em relação à custo e prazo.
B11: Finanças e Relações com investidores | C11: Bill-to-cash​ | D11: Envio dos spools para as print centers ​ | E11: - Oi irá disponibilizar os spools de faturas de terminais fibra para as print centers atuais da Oi (e remunerar os print centers), mantendo os sistemas, regras e processos atuais, até a migração total desses clientes, nos formatos e layout atuais (online e customizadas) para clientes varejo e empresarial. - Conferência do faturamento gerado e consistências cadastrais. - Disponibilização dos documentos para as empresas de postagem.
B12: Finanças e Relações com investidores | C12: Bill-to-cash​ | D12: Postagem das faturas para os clientes ​ | E12: - Oi irá disponibilizar os documentos de faturamento de terminais fibra para as empresas de postagem, mantendo os sistemas, regras e processos atuais, até a migração total desses clientes, nos formatos e layout atuais (online e customizadas) para clientes varejo e empresarial. - Os clientes digitais terão seu envio da forma que solicitaram, seja via email ou whatsapp
B13: Finanças e Relações com investidores | C13: Bill-to-cash​ | D13: Execução dos processos de garantia da receita ​ | E13: - Execução mensal de análise de variação da receita de serviços recorrentes dos segmentos varejo e empresarial nas principais alavancas (gross, churn, interrupções de faturamento, migrações, variações de clientes da base, etc) - Análise mensal das alavancas NTFGA (motivo de Terminais não Faturarem e Gerarem Assinatura) para serviços pós pagos. - Acompanhamento mensal da despesa de ITX e análise dos desvios (VOIP)
... B217: Tecnologia | C217: Application and data management​ | D217: Dados históricos anteriores à migração (chamados de clientes que demandem informações históricas)​ | E217: - Implementar mecânica para viabilizar o tratamento de chamados de clientes que demandem informações históricas anteriores aos dados migrados massivamente para as bases das Compradoras.

Sheet Draft Anexo B
B2: VP | C2: Status (23/05) | D2: Custo Anexo B (5 UPI´s) | F2: Custo Anexo B (1 UPI)
D3: FTE | E3: Custo | F3: FTE | G3: Custo
B4: Auditoria e GRC | C4: Concluído | D4: 3 | E4: 712092 | F4: 3 | G4: 712092
